{
  "type": "Feature",
  "properties": {
    "gn:admin1_code":"18.0",
    "gn:asciiname":"Madjavi",
    "gn:country_code":"BJ",
    "gn:dem":161,
    "gn:feature_class":"P",
    "gn:feature_code":"PPL",
    "gn:name":"Madjavi",
    "gn:population":0,
    "gn:timezone":"Africa/Porto-Novo",
    "iso:country":"BJ",
    "wof:name":"Madjavi",
    "wof:placetype":"locality"
},
  "geometry": {"coordinates":[1.93333,7.33333],"type":"Point"}
}