{
  "type": "Feature",
  "properties": {
    "gn:admin1_code":"10.0",
    "gn:admin2_code":"7669355.0",
    "gn:asciiname":"Nikki-Wenou",
    "gn:country_code":"BJ",
    "gn:dem":452,
    "gn:feature_class":"P",
    "gn:feature_code":"PPL",
    "gn:name":"Nikki-W\u00e9nou",
    "gn:population":0,
    "gn:timezone":"Africa/Porto-Novo",
    "iso:country":"BJ",
    "name:und_x_variant":[
        "Nikki-Wepu",
        "Nikki-Ou\u00e9nou",
        "Nikki-W\u00e9nou"
    ],
    "wof:name":"Nikki-Wenou",
    "wof:placetype":"locality"
},
  "geometry": {"coordinates":[3.27282,9.91175],"type":"Point"}
}