{
  "type": "Feature",
  "properties": {
    "gn:admin1_code":"8.0",
    "gn:asciiname":"Sekanon",
    "gn:country_code":"BJ",
    "gn:dem":184,
    "gn:feature_class":"P",
    "gn:feature_code":"PPL",
    "gn:name":"S\u00e9kanon",
    "gn:population":0,
    "gn:timezone":"Africa/Porto-Novo",
    "iso:country":"BJ",
    "name:und_x_variant":[
        "Sakannou",
        "S\u00e9kanon"
    ],
    "wof:name":"Sekanon",
    "wof:placetype":"locality"
},
  "geometry": {"coordinates":[1.03331,10.71232],"type":"Point"}
}