{
  "type": "Feature",
  "properties": {
    "gn:admin1_code":"13.0",
    "gn:asciiname":"Bakou",
    "gn:country_code":"BJ",
    "gn:dem":454,
    "gn:feature_class":"P",
    "gn:feature_code":"PPL",
    "gn:name":"Bakou",
    "gn:population":0,
    "gn:timezone":"Africa/Porto-Novo",
    "iso:country":"BJ",
    "wof:name":"Bakou",
    "wof:placetype":"locality"
},
  "geometry": {"coordinates":[1.62079,9.78127],"type":"Point"}
}