{
  "type": "Feature",
  "properties": {
    "gn:admin1_code":"7.0",
    "gn:asciiname":"Niirigou",
    "gn:country_code":"BJ",
    "gn:dem":272,
    "gn:feature_class":"P",
    "gn:feature_code":"PPL",
    "gn:name":"Niirigou",
    "gn:population":0,
    "gn:timezone":"Africa/Porto-Novo",
    "iso:country":"BJ",
    "wof:name":"Niirigou",
    "wof:placetype":"locality"
},
  "geometry": {"coordinates":[2.5416,11.34319],"type":"Point"}
}