{
  "type": "Feature",
  "properties": {
    "gn:admin1_code":"8.0",
    "gn:asciiname":"Koutchounchoungou",
    "gn:country_code":"BJ",
    "gn:dem":263,
    "gn:feature_class":"P",
    "gn:feature_code":"PPL",
    "gn:name":"Koutchounchoungou",
    "gn:population":0,
    "gn:timezone":"Africa/Porto-Novo",
    "iso:country":"BJ",
    "wof:name":"Koutchounchoungou",
    "wof:placetype":"locality"
},
  "geometry": {"coordinates":[1.17588,10.34234],"type":"Point"}
}