{
  "type": "Feature",
  "properties": {
    "gn:admin1_code":"7.0",
    "gn:asciiname":"Kofouno",
    "gn:country_code":"BJ",
    "gn:dem":185,
    "gn:feature_class":"P",
    "gn:feature_code":"PPL",
    "gn:name":"Kofouno",
    "gn:population":0,
    "gn:timezone":"Africa/Porto-Novo",
    "iso:country":"BJ",
    "wof:name":"Kofouno",
    "wof:placetype":"locality"
},
  "geometry": {"coordinates":[3.08445,12.00903],"type":"Point"}
}