{
  "type": "Feature",
  "properties": {
    "gn:admin1_code":"13.0",
    "gn:admin2_code":"7669263.0",
    "gn:admin3_code":"11790011.0",
    "gn:asciiname":"Badjoude",
    "gn:country_code":"BJ",
    "gn:dem":470,
    "gn:feature_class":"P",
    "gn:feature_code":"PPL",
    "gn:name":"Badjoud\u00e8",
    "gn:population":0,
    "gn:timezone":"Africa/Porto-Novo",
    "iso:country":"BJ",
    "name:ceb_x_preferred":[
        "Badjoud\u00e8"
    ],
    "name:ita_x_preferred":[
        "Badjoud\u00e8"
    ],
    "name:msa_x_preferred":[
        "Badjoud\u00e8"
    ],
    "name:swe_x_preferred":[
        "Badjoud\u00e8"
    ],
    "name:und_x_variant":[
        "Dompago",
        "Batloud\u00e9",
        "Badjoud\u00e8"
    ],
    "wof:name":"Badjoude",
    "wof:placetype":"locality"
},
  "geometry": {"coordinates":[1.41141,9.71693],"type":"Point"}
}