{
  "type": "Feature",
  "properties": {
    "gn:admin1_code":"8.0",
    "gn:admin2_code":"7874156.0",
    "gn:admin3_code":"11790224.0",
    "gn:asciiname":"Tayakou",
    "gn:country_code":"BJ",
    "gn:dem":235,
    "gn:feature_class":"P",
    "gn:feature_code":"PPL",
    "gn:name":"Tayakou",
    "gn:population":0,
    "gn:timezone":"Africa/Porto-Novo",
    "iso:country":"BJ",
    "name:ceb_x_preferred":[
        "Tayakou"
    ],
    "name:ita_x_preferred":[
        "Taiakou"
    ],
    "name:msa_x_preferred":[
        "Taiakou"
    ],
    "name:swe_x_preferred":[
        "Taiakou"
    ],
    "name:und_x_variant":[
        "Ta\u00efacou",
        "Ta\u00efakou",
        "Tayakou"
    ],
    "wof:name":"Tayakou",
    "wof:placetype":"locality"
},
  "geometry": {"coordinates":[1.2026,10.54265],"type":"Point"}
}