{
  "type": "Feature",
  "properties": {
    "gn:admin1_code":"8.0",
    "gn:asciiname":"Angara-Debou",
    "gn:country_code":"BJ",
    "gn:dem":315,
    "gn:feature_class":"P",
    "gn:feature_code":"PPL",
    "gn:name":"Angara-D\u00e9bou",
    "gn:population":0,
    "gn:timezone":"Africa/Porto-Novo",
    "iso:country":"BJ",
    "name:und_x_variant":[
        "Angara Deburu",
        "Angara-D\u00e9bu",
        "Angara-D\u00e9bou"
    ],
    "wof:name":"Angara-Debou",
    "wof:placetype":"locality"
},
  "geometry": {"coordinates":[3.05886,11.32454],"type":"Point"}
}