{
  "type": "Feature",
  "properties": {
    "gn:admin1_code":"9.0",
    "gn:admin2_code":"7874154.0",
    "gn:admin3_code":"11837720.0",
    "gn:asciiname":"So-Ava",
    "gn:country_code":"BJ",
    "gn:dem":1,
    "gn:feature_class":"P",
    "gn:feature_code":"PPLA3",
    "gn:name":"So-Ava",
    "gn:population":0,
    "gn:timezone":"Africa/Porto-Novo",
    "iso:country":"BJ",
    "name:fra_x_preferred":[
        "S\u00f4-Ava"
    ],
    "name:frr_x_preferred":[
        "S\u00f4-Ava"
    ],
    "name:ita_x_preferred":[
        "S\u00f4-Ava"
    ],
    "name:msa_x_preferred":[
        "S\u00f4-Ava"
    ],
    "name:nld_x_preferred":[
        "S\u00f4-Ava"
    ],
    "name:spa_x_preferred":[
        "S\u00f4-Ava"
    ],
    "name:swe_x_preferred":[
        "S\u00f4-Ava"
    ],
    "name:und_x_variant":[
        "S\u00f4 Avo",
        "S\u00f4-Ava",
        "So",
        "So-Awa"
    ],
    "name:zho_x_preferred":[
        "\u7d22\u963f\u74e6"
    ],
    "wof:name":"So-Ava",
    "wof:placetype":"locality"
},
  "geometry": {"coordinates":[2.40193,6.49245],"type":"Point"}
}