{
  "type": "Feature",
  "properties": {
    "gn:admin1_code":"16.0",
    "gn:asciiname":"Gbedjehoun",
    "gn:country_code":"BJ",
    "gn:dem":40,
    "gn:feature_class":"P",
    "gn:feature_code":"PPL",
    "gn:name":"Gb\u00e8djehoun",
    "gn:population":0,
    "gn:timezone":"Africa/Porto-Novo",
    "iso:country":"BJ",
    "wof:name":"Gbedjehoun",
    "wof:placetype":"locality"
},
  "geometry": {"coordinates":[2.62999,6.5829],"type":"Point"}
}