{
  "type": "Feature",
  "properties": {
    "gn:admin1_code":"18.0",
    "gn:asciiname":"Agounogon",
    "gn:country_code":"BJ",
    "gn:dem":132,
    "gn:feature_class":"P",
    "gn:feature_code":"PPL",
    "gn:name":"Agounogon",
    "gn:population":0,
    "gn:timezone":"Africa/Porto-Novo",
    "iso:country":"BJ",
    "wof:name":"Agounogon",
    "wof:placetype":"locality"
},
  "geometry": {"coordinates":[1.98333,7.38333],"type":"Point"}
}