{
  "type": "Feature",
  "properties": {
    "gn:admin1_code":"13.0",
    "gn:asciiname":"Djenkeme",
    "gn:country_code":"BJ",
    "gn:dem":412,
    "gn:feature_class":"P",
    "gn:feature_code":"PPL",
    "gn:name":"Djenk\u00e8me",
    "gn:population":0,
    "gn:timezone":"Africa/Porto-Novo",
    "iso:country":"BJ",
    "wof:name":"Djenkeme",
    "wof:placetype":"locality"
},
  "geometry": {"coordinates":[1.42556,9.46335],"type":"Point"}
}