{
  "type": "Feature",
  "properties": {
    "gn:admin1_code":"17.0",
    "gn:asciiname":"Oke-Odo",
    "gn:country_code":"BJ",
    "gn:dem":207,
    "gn:feature_class":"P",
    "gn:feature_code":"PPL",
    "gn:name":"Ok\u00e9-Odo",
    "gn:population":0,
    "gn:timezone":"Africa/Porto-Novo",
    "iso:country":"BJ",
    "wof:name":"Oke-Odo",
    "wof:placetype":"locality"
},
  "geometry": {"coordinates":[2.73932,7.43356],"type":"Point"}
}