{
  "type": "Feature",
  "properties": {
    "gn:admin1_code":"7.0",
    "gn:asciiname":"Kassapoula",
    "gn:country_code":"BJ",
    "gn:dem":330,
    "gn:feature_class":"P",
    "gn:feature_code":"PPL",
    "gn:name":"Kassapoula",
    "gn:population":0,
    "gn:timezone":"Africa/Porto-Novo",
    "iso:country":"BJ",
    "wof:name":"Kassapoula",
    "wof:placetype":"locality"
},
  "geometry": {"coordinates":[2.75796,10.7277],"type":"Point"}
}