{
  "type": "Feature",
  "properties": {
    "gn:admin1_code":"7.0",
    "gn:asciiname":"Yabo",
    "gn:country_code":"BJ",
    "gn:dem":280,
    "gn:feature_class":"P",
    "gn:feature_code":"PPL",
    "gn:name":"Yabo",
    "gn:population":0,
    "gn:timezone":"Africa/Porto-Novo",
    "iso:country":"BJ",
    "wof:name":"Yabo",
    "wof:placetype":"locality"
},
  "geometry": {"coordinates":[2.51496,11.29737],"type":"Point"}
}