{
  "type": "Feature",
  "properties": {
    "gn:admin1_code":"7.0",
    "gn:asciiname":"Toke-Banta",
    "gn:country_code":"BJ",
    "gn:dem":307,
    "gn:feature_class":"P",
    "gn:feature_code":"PPL",
    "gn:name":"Tok\u00e9-Banta",
    "gn:population":0,
    "gn:timezone":"Africa/Porto-Novo",
    "iso:country":"BJ",
    "wof:name":"Toke-Banta",
    "wof:placetype":"locality"
},
  "geometry": {"coordinates":[2.41483,11.3077],"type":"Point"}
}