{
  "type": "Feature",
  "properties": {
    "gn:admin1_code":"8.0",
    "gn:admin2_code":"10344466.0",
    "gn:admin3_code":"11789894.0",
    "gn:asciiname":"Datori",
    "gn:country_code":"BJ",
    "gn:dem":163,
    "gn:feature_class":"P",
    "gn:feature_code":"PPL",
    "gn:name":"Datori",
    "gn:population":0,
    "gn:timezone":"Africa/Porto-Novo",
    "iso:country":"BJ",
    "name:ceb_x_preferred":[
        "Datori"
    ],
    "name:ita_x_preferred":[
        "Datori"
    ],
    "name:msa_x_preferred":[
        "Datori"
    ],
    "name:swe_x_preferred":[
        "Datori"
    ],
    "name:und_x_variant":[
        "Datori-Tiokossi"
    ],
    "wof:name":"Datori",
    "wof:placetype":"locality"
},
  "geometry": {"coordinates":[0.78281,10.40851],"type":"Point"}
}