{
  "type": "Feature",
  "properties": {
    "gn:admin1_code":"8.0",
    "gn:asciiname":"Sinmpererou",
    "gn:country_code":"BJ",
    "gn:dem":408,
    "gn:feature_class":"P",
    "gn:feature_code":"PPL",
    "gn:name":"Sinmp\u00e9r\u00e9rou",
    "gn:population":0,
    "gn:timezone":"Africa/Porto-Novo",
    "iso:country":"BJ",
    "wof:name":"Sinmpererou",
    "wof:placetype":"locality"
},
  "geometry": {"coordinates":[1.92268,10.19215],"type":"Point"}
}