{
  "type": "Feature",
  "properties": {
    "gn:admin1_code":"13.0",
    "gn:asciiname":"Serediounga",
    "gn:country_code":"BJ",
    "gn:dem":399,
    "gn:feature_class":"P",
    "gn:feature_code":"PPL",
    "gn:name":"Serediounga",
    "gn:population":0,
    "gn:timezone":"Africa/Porto-Novo",
    "iso:country":"BJ",
    "wof:name":"Serediounga",
    "wof:placetype":"locality"
},
  "geometry": {"coordinates":[1.77709,9.51777],"type":"Point"}
}