{
  "type": "Feature",
  "properties": {
    "gn:admin1_code":"7.0",
    "gn:asciiname":"Woniouroukou",
    "gn:country_code":"BJ",
    "gn:dem":307,
    "gn:feature_class":"P",
    "gn:feature_code":"PPL",
    "gn:name":"Woniouroukou",
    "gn:population":0,
    "gn:timezone":"Africa/Porto-Novo",
    "iso:country":"BJ",
    "wof:name":"Woniouroukou",
    "wof:placetype":"locality"
},
  "geometry": {"coordinates":[2.77961,11.06331],"type":"Point"}
}