{
  "type": "Feature",
  "properties": {
    "gn:admin1_code":"12.0",
    "gn:asciiname":"Bolime",
    "gn:country_code":"BJ",
    "gn:dem":153,
    "gn:feature_class":"P",
    "gn:feature_code":"PPL",
    "gn:name":"Bolim\u00e8",
    "gn:population":0,
    "gn:timezone":"Africa/Porto-Novo",
    "iso:country":"BJ",
    "wof:name":"Bolime",
    "wof:placetype":"locality"
},
  "geometry": {"coordinates":[1.86667,6.93333],"type":"Point"}
}