{
  "type": "Feature",
  "properties": {
    "gn:admin1_code":"11.0",
    "gn:asciiname":"Bikoro",
    "gn:country_code":"BJ",
    "gn:dem":206,
    "gn:feature_class":"P",
    "gn:feature_code":"PPL",
    "gn:name":"Bikoro",
    "gn:population":0,
    "gn:timezone":"Africa/Porto-Novo",
    "iso:country":"BJ",
    "name:fra_x_preferred":[
        "Bikoro"
    ],
    "name:ita_x_preferred":[
        "Bikoro"
    ],
    "name:pol_x_preferred":[
        "Bikoro"
    ],
    "name:ron_x_preferred":[
        "Bikoro"
    ],
    "name:spa_x_preferred":[
        "Bikoro"
    ],
    "name:zho_x_preferred":[
        "\u6bd4\u79d1\u7f85"
    ],
    "wof:name":"Bikoro",
    "wof:placetype":"locality"
},
  "geometry": {"coordinates":[1.65884,7.86325],"type":"Point"}
}