{
  "type": "Feature",
  "properties": {
    "gn:admin1_code":"10.0",
    "gn:asciiname":"Pepekino",
    "gn:country_code":"BJ",
    "gn:dem":336,
    "gn:feature_class":"P",
    "gn:feature_code":"PPL",
    "gn:name":"P\u00e9p\u00e9kino",
    "gn:population":0,
    "gn:timezone":"Africa/Porto-Novo",
    "iso:country":"BJ",
    "name:und_x_variant":[
        "P\u00e9p\u00e9kino"
    ],
    "wof:name":"Pepekino",
    "wof:placetype":"locality"
},
  "geometry": {"coordinates":[2.70513,9.35289],"type":"Point"}
}