{
  "type": "Feature",
  "properties": {
    "gn:admin1_code":"7.0",
    "gn:admin2_code":"7668935.0",
    "gn:admin3_code":"11790271.0",
    "gn:asciiname":"Oune",
    "gn:country_code":"BJ",
    "gn:dem":301,
    "gn:feature_class":"P",
    "gn:feature_code":"PPL",
    "gn:name":"Oun\u00e9",
    "gn:population":0,
    "gn:timezone":"Africa/Porto-Novo",
    "iso:country":"BJ",
    "name:ceb_x_preferred":[
        "Oun\u00e9"
    ],
    "name:ita_x_preferred":[
        "Ounet"
    ],
    "name:msa_x_preferred":[
        "Ounet"
    ],
    "name:swe_x_preferred":[
        "Ounet"
    ],
    "name:und_x_variant":[
        "Unet"
    ],
    "wof:name":"Oune",
    "wof:placetype":"locality"
},
  "geometry": {"coordinates":[2.41646,11.23617],"type":"Point"}
}