{
  "type": "Feature",
  "properties": {
    "gn:admin1_code":"7.0",
    "gn:asciiname":"Birikirou",
    "gn:country_code":"BJ",
    "gn:dem":282,
    "gn:feature_class":"P",
    "gn:feature_code":"PPL",
    "gn:name":"Birikirou",
    "gn:population":0,
    "gn:timezone":"Africa/Porto-Novo",
    "iso:country":"BJ",
    "wof:name":"Birikirou",
    "wof:placetype":"locality"
},
  "geometry": {"coordinates":[2.84481,11.14454],"type":"Point"}
}