{
  "type": "Feature",
  "properties": {
    "gn:admin1_code":"11.0",
    "gn:asciiname":"Sandeou",
    "gn:country_code":"BJ",
    "gn:dem":172,
    "gn:feature_class":"P",
    "gn:feature_code":"PPL",
    "gn:name":"Sand\u00e9ou",
    "gn:population":0,
    "gn:timezone":"Africa/Porto-Novo",
    "iso:country":"BJ",
    "wof:name":"Sandeou",
    "wof:placetype":"locality"
},
  "geometry": {"coordinates":[2.71221,8.11329],"type":"Point"}
}