{
  "type": "Feature",
  "properties": {
    "gn:admin1_code":"8.0",
    "gn:asciiname":"Sekougourou",
    "gn:country_code":"BJ",
    "gn:dem":395,
    "gn:feature_class":"P",
    "gn:feature_code":"PPL",
    "gn:name":"S\u00e9kougourou",
    "gn:population":0,
    "gn:timezone":"Africa/Porto-Novo",
    "iso:country":"BJ",
    "name:und_x_variant":[
        "S\u00e9cougourou",
        "S\u00e9kougourou"
    ],
    "wof:name":"Sekougourou",
    "wof:placetype":"locality"
},
  "geometry": {"coordinates":[1.74848,10.38727],"type":"Point"}
}