{
  "type": "Feature",
  "properties": {
    "gn:admin1_code":"10.0",
    "gn:asciiname":"Dari",
    "gn:country_code":"BJ",
    "gn:dem":359,
    "gn:feature_class":"P",
    "gn:feature_code":"PPL",
    "gn:name":"Dari",
    "gn:population":0,
    "gn:timezone":"Africa/Porto-Novo",
    "iso:country":"BJ",
    "name:ceb_x_preferred":[
        "Dari"
    ],
    "name:deu_x_preferred":[
        "Dari"
    ],
    "name:ell_x_preferred":[
        "\u039d\u03c4\u03b1\u03c1\u03af"
    ],
    "name:fas_x_preferred":[
        "\u062f\u0631\u06cc"
    ],
    "name:ind_x_preferred":[
        "Dari"
    ],
    "name:ita_x_preferred":[
        "Dari"
    ],
    "name:jpn_x_preferred":[
        "\u30c0\u30ea\u30fc\u8a9e"
    ],
    "name:kur_x_preferred":[
        "Der\u00ee"
    ],
    "name:slk_x_preferred":[
        "Dar\u00edj\u010dina"
    ],
    "name:spa_x_preferred":[
        "Dari"
    ],
    "name:sun_x_preferred":[
        "Dari"
    ],
    "name:swe_x_preferred":[
        "Dari"
    ],
    "name:vie_x_preferred":[
        "Dari"
    ],
    "wof:name":"Dari",
    "wof:placetype":"locality"
},
  "geometry": {"coordinates":[2.87348,9.54744],"type":"Point"}
}