{
  "type": "Feature",
  "properties": {
    "gn:admin1_code":"8.0",
    "gn:asciiname":"Koi",
    "gn:country_code":"BJ",
    "gn:dem":261,
    "gn:feature_class":"P",
    "gn:feature_code":"PPL",
    "gn:name":"Koi",
    "gn:population":0,
    "gn:timezone":"Africa/Porto-Novo",
    "iso:country":"BJ",
    "wof:name":"Koi",
    "wof:placetype":"locality"
},
  "geometry": {"coordinates":[3.16796,11.2143],"type":"Point"}
}