{
  "type": "Feature",
  "properties": {
    "gn:admin1_code":"18.0",
    "gn:asciiname":"Gueguezogon",
    "gn:country_code":"BJ",
    "gn:dem":159,
    "gn:feature_class":"P",
    "gn:feature_code":"PPL",
    "gn:name":"Gu\u00e9gu\u00e9zogon",
    "gn:population":0,
    "gn:timezone":"Africa/Porto-Novo",
    "iso:country":"BJ",
    "wof:name":"Gueguezogon",
    "wof:placetype":"locality"
},
  "geometry": {"coordinates":[1.94461,7.17195],"type":"Point"}
}