{
  "type": "Feature",
  "properties": {
    "gn:admin1_code":"8.0",
    "gn:asciiname":"Tassoukouati",
    "gn:country_code":"BJ",
    "gn:dem":143,
    "gn:feature_class":"P",
    "gn:feature_code":"PPL",
    "gn:name":"Tassoukouati",
    "gn:population":0,
    "gn:timezone":"Africa/Porto-Novo",
    "iso:country":"BJ",
    "wof:name":"Tassoukouati",
    "wof:placetype":"locality"
},
  "geometry": {"coordinates":[0.78352,10.44675],"type":"Point"}
}