{
  "type": "Feature",
  "properties": {
    "gn:admin1_code":"13.0",
    "gn:asciiname":"Assion",
    "gn:country_code":"BJ",
    "gn:dem":302,
    "gn:feature_class":"P",
    "gn:feature_code":"PPL",
    "gn:name":"Assion",
    "gn:population":0,
    "gn:timezone":"Africa/Porto-Novo",
    "iso:country":"BJ",
    "wof:name":"Assion",
    "wof:placetype":"locality"
},
  "geometry": {"coordinates":[1.67488,8.61108],"type":"Point"}
}