{
  "type": "Feature",
  "properties": {
    "gn:admin1_code":"8.0",
    "gn:admin2_code":"10344467.0",
    "gn:admin3_code":"11789887.0",
    "gn:asciiname":"Manta",
    "gn:country_code":"BJ",
    "gn:dem":215,
    "gn:feature_class":"P",
    "gn:feature_code":"PPL",
    "gn:name":"Manta",
    "gn:population":0,
    "gn:timezone":"Africa/Porto-Novo",
    "iso:country":"BJ",
    "name:ceb_x_preferred":[
        "Manta"
    ],
    "name:fra_x_preferred":[
        "Manta"
    ],
    "name:heb_x_preferred":[
        "\u05de\u05e0\u05d8\u05d4"
    ],
    "name:ita_x_preferred":[
        "Manta"
    ],
    "name:msa_x_preferred":[
        "Manta"
    ],
    "name:swe_x_preferred":[
        "Manta"
    ],
    "wof:name":"Manta",
    "wof:placetype":"locality"
},
  "geometry": {"coordinates":[1.10782,10.35972],"type":"Point"}
}