{
  "type": "Feature",
  "properties": {
    "gn:admin1_code":"10.0",
    "gn:asciiname":"Orokekekparou",
    "gn:country_code":"BJ",
    "gn:dem":433,
    "gn:feature_class":"P",
    "gn:feature_code":"PPL",
    "gn:name":"Orok\u00e9k\u00e9kparou",
    "gn:population":0,
    "gn:timezone":"Africa/Porto-Novo",
    "iso:country":"BJ",
    "wof:name":"Orokekekparou",
    "wof:placetype":"locality"
},
  "geometry": {"coordinates":[3.31533,10.23733],"type":"Point"}
}