{
  "type": "Feature",
  "properties": {
    "gn:admin1_code":"8.0",
    "gn:asciiname":"Kalepoihon",
    "gn:country_code":"BJ",
    "gn:dem":148,
    "gn:feature_class":"P",
    "gn:feature_code":"PPL",
    "gn:name":"Kal\u00e9poihon",
    "gn:population":0,
    "gn:timezone":"Africa/Porto-Novo",
    "iso:country":"BJ",
    "wof:name":"Kalepoihon",
    "wof:placetype":"locality"
},
  "geometry": {"coordinates":[0.86511,10.70074],"type":"Point"}
}