{
  "type": "Feature",
  "properties": {
    "gn:admin1_code":"8.0",
    "gn:asciiname":"Koamogou",
    "gn:country_code":"BJ",
    "gn:dem":555,
    "gn:feature_class":"P",
    "gn:feature_code":"PPL",
    "gn:name":"Koamogou",
    "gn:population":0,
    "gn:timezone":"Africa/Porto-Novo",
    "iso:country":"BJ",
    "wof:name":"Koamogou",
    "wof:placetype":"locality"
},
  "geometry": {"coordinates":[1.34731,10.6243],"type":"Point"}
}