{
  "type": "Feature",
  "properties": {
    "gn:admin1_code":"8.0",
    "gn:asciiname":"Dabogohoun",
    "gn:country_code":"BJ",
    "gn:dem":148,
    "gn:feature_class":"P",
    "gn:feature_code":"PPL",
    "gn:name":"Dabogohoun",
    "gn:population":0,
    "gn:timezone":"Africa/Porto-Novo",
    "iso:country":"BJ",
    "wof:name":"Dabogohoun",
    "wof:placetype":"locality"
},
  "geometry": {"coordinates":[0.99011,10.9338],"type":"Point"}
}