{
  "type": "Feature",
  "properties": {
    "gn:admin1_code":"7.0",
    "gn:asciiname":"Gombeti Kwara",
    "gn:country_code":"BJ",
    "gn:dem":208,
    "gn:feature_class":"P",
    "gn:feature_code":"PPL",
    "gn:name":"Gomb\u00e9ti Kwara",
    "gn:population":0,
    "gn:timezone":"Africa/Porto-Novo",
    "iso:country":"BJ",
    "name:und_x_variant":[
        "Gomb\u00e9tikoara",
        "Gomb\u00e9ti Kwara"
    ],
    "wof:name":"Gombeti Kwara",
    "wof:placetype":"locality"
},
  "geometry": {"coordinates":[2.94009,12.26841],"type":"Point"}
}