{
  "type": "Feature",
  "properties": {
    "gn:admin1_code":"18.0",
    "gn:asciiname":"Agblagato",
    "gn:country_code":"BJ",
    "gn:dem":154,
    "gn:feature_class":"P",
    "gn:feature_code":"PPL",
    "gn:name":"Agblagato",
    "gn:population":0,
    "gn:timezone":"Africa/Porto-Novo",
    "iso:country":"BJ",
    "wof:name":"Agblagato",
    "wof:placetype":"locality"
},
  "geometry": {"coordinates":[1.95,7.46667],"type":"Point"}
}