{
  "type": "Feature",
  "properties": {
    "gn:admin1_code":"7.0",
    "gn:asciiname":"Gamali",
    "gn:country_code":"BJ",
    "gn:dem":294,
    "gn:feature_class":"P",
    "gn:feature_code":"PPL",
    "gn:name":"Gamali",
    "gn:population":0,
    "gn:timezone":"Africa/Porto-Novo",
    "iso:country":"BJ",
    "wof:name":"Gamali",
    "wof:placetype":"locality"
},
  "geometry": {"coordinates":[2.89615,11.04372],"type":"Point"}
}