{
  "type": "Feature",
  "properties": {
    "gn:admin1_code":"18.0",
    "gn:asciiname":"Tchiomegon",
    "gn:country_code":"BJ",
    "gn:dem":151,
    "gn:feature_class":"P",
    "gn:feature_code":"PPL",
    "gn:name":"Tchiom\u00e9gon",
    "gn:population":0,
    "gn:timezone":"Africa/Porto-Novo",
    "iso:country":"BJ",
    "wof:name":"Tchiomegon",
    "wof:placetype":"locality"
},
  "geometry": {"coordinates":[1.78333,7.35],"type":"Point"}
}