{
  "type": "Feature",
  "properties": {
    "gn:admin1_code":"9.0",
    "gn:asciiname":"Agoukame",
    "gn:country_code":"BJ",
    "gn:dem":26,
    "gn:feature_class":"P",
    "gn:feature_code":"PPL",
    "gn:name":"Agoukam\u00e8",
    "gn:population":0,
    "gn:timezone":"Africa/Porto-Novo",
    "iso:country":"BJ",
    "wof:name":"Agoukame",
    "wof:placetype":"locality"
},
  "geometry": {"coordinates":[1.99347,6.3816],"type":"Point"}
}