{
  "type": "Feature",
  "properties": {
    "gn:admin1_code":"8.0",
    "gn:asciiname":"Kanpouya",
    "gn:country_code":"BJ",
    "gn:dem":573,
    "gn:feature_class":"P",
    "gn:feature_code":"PPL",
    "gn:name":"Kanpouya",
    "gn:population":0,
    "gn:timezone":"Africa/Porto-Novo",
    "iso:country":"BJ",
    "name:und_x_variant":[
        "Campouya",
        "Kanpouya"
    ],
    "wof:name":"Kanpouya",
    "wof:placetype":"locality"
},
  "geometry": {"coordinates":[1.61017,10.41065],"type":"Point"}
}