{
  "type": "Feature",
  "properties": {
    "gn:admin1_code":"10.0",
    "gn:asciiname":"Kpererou",
    "gn:country_code":"BJ",
    "gn:dem":292,
    "gn:feature_class":"P",
    "gn:feature_code":"PPL",
    "gn:name":"Kp\u00e9r\u00e9rou",
    "gn:population":0,
    "gn:timezone":"Africa/Porto-Novo",
    "iso:country":"BJ",
    "name:und_x_variant":[
        "P\u00e9r\u00e9rou",
        "Kp\u00e9r\u00e9rou"
    ],
    "wof:name":"Kpererou",
    "wof:placetype":"locality"
},
  "geometry": {"coordinates":[2.31481,9.40777],"type":"Point"}
}