{
  "type": "Feature",
  "properties": {
    "gn:admin1_code":"8.0",
    "gn:asciiname":"Bounkossorou",
    "gn:country_code":"BJ",
    "gn:dem":473,
    "gn:feature_class":"P",
    "gn:feature_code":"PPL",
    "gn:name":"Bounkossorou",
    "gn:population":0,
    "gn:timezone":"Africa/Porto-Novo",
    "iso:country":"BJ",
    "name:und_x_variant":[
        "Boucoussourou",
        "Bounkossorou"
    ],
    "wof:name":"Bounkossorou",
    "wof:placetype":"locality"
},
  "geometry": {"coordinates":[1.74853,10.59683],"type":"Point"}
}