{
  "type": "Feature",
  "properties": {
    "gn:admin1_code":"8.0",
    "gn:asciiname":"Kakou",
    "gn:country_code":"BJ",
    "gn:dem":341,
    "gn:feature_class":"P",
    "gn:feature_code":"PPL",
    "gn:name":"Kakou",
    "gn:population":0,
    "gn:timezone":"Africa/Porto-Novo",
    "iso:country":"BJ",
    "wof:name":"Kakou",
    "wof:placetype":"locality"
},
  "geometry": {"coordinates":[1.39209,10.02102],"type":"Point"}
}