{
  "type": "Feature",
  "properties": {
    "gn:admin1_code":"7.0",
    "gn:asciiname":"Kolomi",
    "gn:country_code":"BJ",
    "gn:dem":310,
    "gn:feature_class":"P",
    "gn:feature_code":"PPL",
    "gn:name":"Kolomi",
    "gn:population":0,
    "gn:timezone":"Africa/Porto-Novo",
    "iso:country":"BJ",
    "wof:name":"Kolomi",
    "wof:placetype":"locality"
},
  "geometry": {"coordinates":[2.72421,10.8452],"type":"Point"}
}