{
  "type": "Feature",
  "properties": {
    "gn:admin1_code":"15.0",
    "gn:asciiname":"Agbodranfo",
    "gn:country_code":"BJ",
    "gn:dem":24,
    "gn:feature_class":"P",
    "gn:feature_code":"PPL",
    "gn:name":"Agbodranfo",
    "gn:population":0,
    "gn:timezone":"Africa/Porto-Novo",
    "iso:country":"BJ",
    "wof:name":"Agbodranfo",
    "wof:placetype":"locality"
},
  "geometry": {"coordinates":[1.72241,6.75715],"type":"Point"}
}