{
  "type": "Feature",
  "properties": {
    "gn:admin1_code":"10.0",
    "gn:asciiname":"Niegoussourou",
    "gn:country_code":"BJ",
    "gn:dem":355,
    "gn:feature_class":"P",
    "gn:feature_code":"PPL",
    "gn:name":"Ni\u00e9goussourou",
    "gn:population":0,
    "gn:timezone":"Africa/Porto-Novo",
    "iso:country":"BJ",
    "wof:name":"Niegoussourou",
    "wof:placetype":"locality"
},
  "geometry": {"coordinates":[2.46171,10.18721],"type":"Point"}
}