{
  "type": "Feature",
  "properties": {
    "gn:admin1_code":"8.0",
    "gn:asciiname":"Direpouro",
    "gn:country_code":"BJ",
    "gn:dem":353,
    "gn:feature_class":"P",
    "gn:feature_code":"PPL",
    "gn:name":"Dir\u00e9pouro",
    "gn:population":0,
    "gn:timezone":"Africa/Porto-Novo",
    "iso:country":"BJ",
    "wof:name":"Direpouro",
    "wof:placetype":"locality"
},
  "geometry": {"coordinates":[1.54858,10.06009],"type":"Point"}
}