{
  "type": "Feature",
  "properties": {
    "gn:admin1_code":"10.0",
    "gn:asciiname":"Kpere",
    "gn:country_code":"BJ",
    "gn:dem":264,
    "gn:feature_class":"P",
    "gn:feature_code":"PPL",
    "gn:name":"Kp\u00e9r\u00e9",
    "gn:population":0,
    "gn:timezone":"Africa/Porto-Novo",
    "iso:country":"BJ",
    "wof:name":"Kpere",
    "wof:placetype":"locality"
},
  "geometry": {"coordinates":[2.26355,9.1518],"type":"Point"}
}