{
  "type": "Feature",
  "properties": {
    "gn:admin1_code":"7.0",
    "gn:asciiname":"Bedarou",
    "gn:country_code":"BJ",
    "gn:dem":333,
    "gn:feature_class":"P",
    "gn:feature_code":"PPL",
    "gn:name":"B\u00e9darou",
    "gn:population":0,
    "gn:timezone":"Africa/Porto-Novo",
    "iso:country":"BJ",
    "wof:name":"Bedarou",
    "wof:placetype":"locality"
},
  "geometry": {"coordinates":[2.98447,10.78845],"type":"Point"}
}