{
  "type": "Feature",
  "properties": {
    "gn:admin1_code":"8.0",
    "gn:asciiname":"Koussega",
    "gn:country_code":"BJ",
    "gn:dem":189,
    "gn:feature_class":"P",
    "gn:feature_code":"PPL",
    "gn:name":"Kouss\u00e9ga",
    "gn:population":0,
    "gn:timezone":"Africa/Porto-Novo",
    "iso:country":"BJ",
    "wof:name":"Koussega",
    "wof:placetype":"locality"
},
  "geometry": {"coordinates":[0.9791,10.82132],"type":"Point"}
}