{
  "type": "Feature",
  "properties": {
    "gn:admin1_code":"8.0",
    "gn:asciiname":"Amberi Goumbi",
    "gn:country_code":"BJ",
    "gn:dem":192,
    "gn:feature_class":"P",
    "gn:feature_code":"PPL",
    "gn:name":"Amb\u00e9ri Goumbi",
    "gn:population":0,
    "gn:timezone":"Africa/Porto-Novo",
    "iso:country":"BJ",
    "name:und_x_variant":[
        "Anb\u00e9ri-Goumbi",
        "Amb\u00e9ri Goumbi"
    ],
    "wof:name":"Amberi Goumbi",
    "wof:placetype":"locality"
},
  "geometry": {"coordinates":[3.33585,11.57608],"type":"Point"}
}