{
  "type": "Feature",
  "properties": {
    "gn:admin1_code":"18.0",
    "gn:asciiname":"Koukouekame",
    "gn:country_code":"BJ",
    "gn:dem":194,
    "gn:feature_class":"P",
    "gn:feature_code":"PPL",
    "gn:name":"Koukou\u00e9kam\u00e9",
    "gn:population":0,
    "gn:timezone":"Africa/Porto-Novo",
    "iso:country":"BJ",
    "wof:name":"Koukouekame",
    "wof:placetype":"locality"
},
  "geometry": {"coordinates":[1.76765,7.49597],"type":"Point"}
}