{
  "type": "Feature",
  "properties": {
    "gn:admin1_code":"9.0",
    "gn:asciiname":"Agla",
    "gn:country_code":"BJ",
    "gn:dem":6,
    "gn:feature_class":"P",
    "gn:feature_code":"PPL",
    "gn:name":"Agla",
    "gn:population":0,
    "gn:timezone":"Africa/Porto-Novo",
    "iso:country":"BJ",
    "wof:name":"Agla",
    "wof:placetype":"locality"
},
  "geometry": {"coordinates":[2.36336,6.38438],"type":"Point"}
}