{
  "type": "Feature",
  "properties": {
    "gn:admin1_code":"13.0",
    "gn:asciiname":"Terekouka",
    "gn:country_code":"BJ",
    "gn:dem":437,
    "gn:feature_class":"P",
    "gn:feature_code":"PPL",
    "gn:name":"T\u00e9r\u00e9kouka",
    "gn:population":0,
    "gn:timezone":"Africa/Porto-Novo",
    "iso:country":"BJ",
    "wof:name":"Terekouka",
    "wof:placetype":"locality"
},
  "geometry": {"coordinates":[1.59607,9.6236],"type":"Point"}
}