{
  "type": "Feature",
  "properties": {
    "gn:admin1_code":"11.0",
    "gn:asciiname":"Atchapa",
    "gn:country_code":"BJ",
    "gn:dem":123,
    "gn:feature_class":"P",
    "gn:feature_code":"PPL",
    "gn:name":"Atchapa",
    "gn:population":0,
    "gn:timezone":"Africa/Porto-Novo",
    "iso:country":"BJ",
    "wof:name":"Atchapa",
    "wof:placetype":"locality"
},
  "geometry": {"coordinates":[2.39174,8.01886],"type":"Point"}
}