{
  "type": "Feature",
  "properties": {
    "gn:admin1_code":"8.0",
    "gn:asciiname":"Tale",
    "gn:country_code":"BJ",
    "gn:dem":179,
    "gn:feature_class":"P",
    "gn:feature_code":"PPL",
    "gn:name":"Tal\u00e9",
    "gn:population":0,
    "gn:timezone":"Africa/Porto-Novo",
    "iso:country":"BJ",
    "name:ceb_x_preferred":[
        "Tale"
    ],
    "name:deu_x_preferred":[
        "Tale"
    ],
    "name:snd_x_preferred":[
        "\u062f\u0627\u0633\u062a\u0627\u0646"
    ],
    "name:swe_x_preferred":[
        "Tale"
    ],
    "name:tel_x_preferred":[
        "\u0c1f\u0c47\u0c32\u0c4d"
    ],
    "wof:name":"Tale",
    "wof:placetype":"locality"
},
  "geometry": {"coordinates":[1.09269,10.84061],"type":"Point"}
}