{
  "type": "Feature",
  "properties": {
    "gn:admin1_code":"8.0",
    "gn:asciiname":"Touga",
    "gn:country_code":"BJ",
    "gn:dem":239,
    "gn:feature_class":"P",
    "gn:feature_code":"PPL",
    "gn:name":"Touga",
    "gn:population":0,
    "gn:timezone":"Africa/Porto-Novo",
    "iso:country":"BJ",
    "name:und_x_variant":[
        "Tougo",
        "Touga"
    ],
    "wof:name":"Touga",
    "wof:placetype":"locality"
},
  "geometry": {"coordinates":[1.03641,10.52082],"type":"Point"}
}