{
  "type": "Feature",
  "properties": {
    "gn:admin1_code":"10.0",
    "gn:asciiname":"Darou Kourarou",
    "gn:country_code":"BJ",
    "gn:dem":350,
    "gn:feature_class":"P",
    "gn:feature_code":"PPL",
    "gn:name":"Darou Kourarou",
    "gn:population":0,
    "gn:timezone":"Africa/Porto-Novo",
    "iso:country":"BJ",
    "wof:name":"Darou Kourarou",
    "wof:placetype":"locality"
},
  "geometry": {"coordinates":[2.57323,9.40475],"type":"Point"}
}