{
  "type": "Feature",
  "properties": {
    "gn:admin1_code":"12.0",
    "gn:admin2_code":"10344472.0",
    "gn:admin3_code":"11789978.0",
    "gn:asciiname":"Lonkly",
    "gn:country_code":"BJ",
    "gn:dem":130,
    "gn:feature_class":"P",
    "gn:feature_code":"PPL",
    "gn:name":"Lonkly",
    "gn:population":0,
    "gn:timezone":"Africa/Porto-Novo",
    "iso:country":"BJ",
    "name:ceb_x_preferred":[
        "Lonkly"
    ],
    "name:ita_x_preferred":[
        "Lonkly"
    ],
    "name:msa_x_preferred":[
        "Lonkly"
    ],
    "name:swe_x_preferred":[
        "Lonkly"
    ],
    "name:und_x_variant":[
        "Lonkli"
    ],
    "wof:name":"Lonkly",
    "wof:placetype":"locality"
},
  "geometry": {"coordinates":[1.67516,7.14109],"type":"Point"}
}