{
  "type": "Feature",
  "properties": {
    "gn:admin1_code":"10.0",
    "gn:asciiname":"Gorobane",
    "gn:country_code":"BJ",
    "gn:dem":340,
    "gn:feature_class":"P",
    "gn:feature_code":"PPL",
    "gn:name":"Goroban\u00e9",
    "gn:population":0,
    "gn:timezone":"Africa/Porto-Novo",
    "iso:country":"BJ",
    "wof:name":"Gorobane",
    "wof:placetype":"locality"
},
  "geometry": {"coordinates":[3.2809,10.07043],"type":"Point"}
}