{
  "type": "Feature",
  "properties": {
    "gn:admin1_code":"8.0",
    "gn:asciiname":"Touloua",
    "gn:country_code":"BJ",
    "gn:dem":197,
    "gn:feature_class":"P",
    "gn:feature_code":"PPL",
    "gn:name":"Touloua",
    "gn:population":0,
    "gn:timezone":"Africa/Porto-Novo",
    "iso:country":"BJ",
    "wof:name":"Touloua",
    "wof:placetype":"locality"
},
  "geometry": {"coordinates":[3.35515,11.61397],"type":"Point"}
}