{
  "type": "Feature",
  "properties": {
    "gn:admin1_code":"13.0",
    "gn:asciiname":"Kpamalangou",
    "gn:country_code":"BJ",
    "gn:dem":391,
    "gn:feature_class":"P",
    "gn:feature_code":"PPL",
    "gn:name":"Kpamalangou",
    "gn:population":0,
    "gn:timezone":"Africa/Porto-Novo",
    "iso:country":"BJ",
    "name:und_x_variant":[
        "Pambalao",
        "Kpamalangou"
    ],
    "wof:name":"Kpamalangou",
    "wof:placetype":"locality"
},
  "geometry": {"coordinates":[1.70311,9.75124],"type":"Point"}
}