{
  "type": "Feature",
  "properties": {
    "gn:admin1_code":"8.0",
    "gn:asciiname":"Damon",
    "gn:country_code":"BJ",
    "gn:dem":190,
    "gn:feature_class":"P",
    "gn:feature_code":"PPL",
    "gn:name":"Damon",
    "gn:population":0,
    "gn:timezone":"Africa/Porto-Novo",
    "iso:country":"BJ",
    "name:cat_x_preferred":[
        "Damon"
    ],
    "name:deu_x_preferred":[
        "Damon"
    ],
    "name:ell_x_preferred":[
        "\u0394\u03ac\u03bc\u03c9\u03bd"
    ],
    "name:fas_x_preferred":[
        "\u062f\u06cc\u0645\u0648\u0646"
    ],
    "name:fra_x_preferred":[
        "Damon"
    ],
    "name:ita_x_preferred":[
        "Damon"
    ],
    "name:kor_x_preferred":[
        "\ub370\uc774\uba3c"
    ],
    "name:nld_x_preferred":[
        "Damon"
    ],
    "name:slk_x_preferred":[
        "Dam\u00f3n"
    ],
    "name:swe_x_preferred":[
        "Damon"
    ],
    "wof:name":"Damon",
    "wof:placetype":"locality"
},
  "geometry": {"coordinates":[1.02835,10.68413],"type":"Point"}
}