{
  "type": "Feature",
  "properties": {
    "gn:admin1_code":"12.0",
    "gn:asciiname":"Akodebakou",
    "gn:country_code":"BJ",
    "gn:dem":142,
    "gn:feature_class":"P",
    "gn:feature_code":"PPL",
    "gn:name":"Akod\u00e9bakou",
    "gn:population":0,
    "gn:timezone":"Africa/Porto-Novo",
    "iso:country":"BJ",
    "wof:name":"Akodebakou",
    "wof:placetype":"locality"
},
  "geometry": {"coordinates":[1.66952,6.89999],"type":"Point"}
}