{
  "type": "Feature",
  "properties": {
    "gn:admin1_code":"10.0",
    "gn:asciiname":"Soubo",
    "gn:country_code":"BJ",
    "gn:dem":362,
    "gn:feature_class":"P",
    "gn:feature_code":"PPL",
    "gn:name":"Soubo",
    "gn:population":0,
    "gn:timezone":"Africa/Porto-Novo",
    "iso:country":"BJ",
    "wof:name":"Soubo",
    "wof:placetype":"locality"
},
  "geometry": {"coordinates":[2.82631,10.06817],"type":"Point"}
}