{
  "type": "Feature",
  "properties": {
    "gn:admin1_code":"18.0",
    "gn:asciiname":"Dovi-Cogbe",
    "gn:country_code":"BJ",
    "gn:dem":38,
    "gn:feature_class":"P",
    "gn:feature_code":"PPL",
    "gn:name":"Dovi-Cogb\u00e9",
    "gn:population":0,
    "gn:timezone":"Africa/Porto-Novo",
    "iso:country":"BJ",
    "wof:name":"Dovi-Cogbe",
    "wof:placetype":"locality"
},
  "geometry": {"coordinates":[2.34401,7.16691],"type":"Point"}
}