{
  "type": "Feature",
  "properties": {
    "gn:admin1_code":"8.0",
    "gn:asciiname":"Tennpobre",
    "gn:country_code":"BJ",
    "gn:dem":415,
    "gn:feature_class":"P",
    "gn:feature_code":"PPL",
    "gn:name":"Tennpobr\u00e9",
    "gn:population":0,
    "gn:timezone":"Africa/Porto-Novo",
    "iso:country":"BJ",
    "name:und_x_variant":[
        "Daro-Tempobr\u00e9",
        "Tennpobr\u00e9"
    ],
    "wof:name":"Tennpobre",
    "wof:placetype":"locality"
},
  "geometry": {"coordinates":[1.55645,10.56486],"type":"Point"}
}