{
  "type": "Feature",
  "properties": {
    "gn:admin1_code":"18.0",
    "gn:asciiname":"Djesi",
    "gn:country_code":"BJ",
    "gn:dem":160,
    "gn:feature_class":"P",
    "gn:feature_code":"PPL",
    "gn:name":"Dj\u00e9si",
    "gn:population":0,
    "gn:timezone":"Africa/Porto-Novo",
    "iso:country":"BJ",
    "name:und_x_variant":[
        "Djessi",
        "Dj\u00e9si"
    ],
    "wof:name":"Djesi",
    "wof:placetype":"locality"
},
  "geometry": {"coordinates":[1.94293,7.37778],"type":"Point"}
}