{
  "type": "Feature",
  "properties": {
    "gn:admin1_code":"8.0",
    "gn:asciiname":"Bouessinakourou",
    "gn:country_code":"BJ",
    "gn:dem":411,
    "gn:feature_class":"P",
    "gn:feature_code":"PPL",
    "gn:name":"Bouessinakourou",
    "gn:population":0,
    "gn:timezone":"Africa/Porto-Novo",
    "iso:country":"BJ",
    "wof:name":"Bouessinakourou",
    "wof:placetype":"locality"
},
  "geometry": {"coordinates":[1.75282,10.2215],"type":"Point"}
}