{
  "type": "Feature",
  "properties": {
    "gn:admin1_code":"7.0",
    "gn:asciiname":"Sinmperekou",
    "gn:country_code":"BJ",
    "gn:dem":287,
    "gn:feature_class":"P",
    "gn:feature_code":"PPL",
    "gn:name":"Sinmp\u00e9r\u00e9kou",
    "gn:population":0,
    "gn:timezone":"Africa/Porto-Novo",
    "iso:country":"BJ",
    "wof:name":"Sinmperekou",
    "wof:placetype":"locality"
},
  "geometry": {"coordinates":[2.48463,11.32158],"type":"Point"}
}