{
  "type": "Feature",
  "properties": {
    "gn:admin1_code":"18.0",
    "gn:asciiname":"Agblome-Levi",
    "gn:country_code":"BJ",
    "gn:dem":218,
    "gn:feature_class":"P",
    "gn:feature_code":"PPL",
    "gn:name":"Agblom\u00e9-L\u00e9vi",
    "gn:population":0,
    "gn:timezone":"Africa/Porto-Novo",
    "iso:country":"BJ",
    "wof:name":"Agblome-Levi",
    "wof:placetype":"locality"
},
  "geometry": {"coordinates":[1.96667,7.18333],"type":"Point"}
}