{
  "type": "Feature",
  "properties": {
    "gn:admin1_code":"13.0",
    "gn:admin2_code":"10344470.0",
    "gn:admin3_code":"11789982.0",
    "gn:asciiname":"Penessoulou",
    "gn:country_code":"BJ",
    "gn:dem":401,
    "gn:feature_class":"P",
    "gn:feature_code":"PPL",
    "gn:name":"P\u00e9n\u00e9ssoulou",
    "gn:population":0,
    "gn:timezone":"Africa/Porto-Novo",
    "iso:country":"BJ",
    "name:ita_x_preferred":[
        "P\u00e9n\u00e9ssoulou"
    ],
    "name:msa_x_preferred":[
        "P\u00e9n\u00e9ssoulou"
    ],
    "name:und_x_variant":[
        "Penesolu",
        "P\u00e9messoulou",
        "P\u00e9n\u00e9soulou",
        "Penesulu",
        "P\u00e9n\u00e9ssoulou"
    ],
    "wof:name":"Penessoulou",
    "wof:placetype":"locality"
},
  "geometry": {"coordinates":[1.54973,9.24064],"type":"Point"}
}