{
  "type": "Feature",
  "properties": {
    "gn:admin1_code":"10.0",
    "gn:asciiname":"Yougourokparou",
    "gn:country_code":"BJ",
    "gn:dem":408,
    "gn:feature_class":"P",
    "gn:feature_code":"PPL",
    "gn:name":"Yougourokparou",
    "gn:population":0,
    "gn:timezone":"Africa/Porto-Novo",
    "iso:country":"BJ",
    "wof:name":"Yougourokparou",
    "wof:placetype":"locality"
},
  "geometry": {"coordinates":[3.38479,10.28622],"type":"Point"}
}