{
  "type": "Feature",
  "properties": {
    "gn:admin1_code":"12.0",
    "gn:asciiname":"Akpave",
    "gn:country_code":"BJ",
    "gn:dem":53,
    "gn:feature_class":"P",
    "gn:feature_code":"PPL",
    "gn:name":"Akpav\u00e9",
    "gn:population":0,
    "gn:timezone":"Africa/Porto-Novo",
    "iso:country":"BJ",
    "wof:name":"Akpave",
    "wof:placetype":"locality"
},
  "geometry": {"coordinates":[1.95,6.76667],"type":"Point"}
}