{
  "type": "Feature",
  "properties": {
    "gn:admin1_code":"8.0",
    "gn:asciiname":"Berekossou",
    "gn:country_code":"BJ",
    "gn:dem":348,
    "gn:feature_class":"P",
    "gn:feature_code":"PPL",
    "gn:name":"B\u00e9r\u00e9kossou",
    "gn:population":0,
    "gn:timezone":"Africa/Porto-Novo",
    "iso:country":"BJ",
    "wof:name":"Berekossou",
    "wof:placetype":"locality"
},
  "geometry": {"coordinates":[2.076,10.69654],"type":"Point"}
}