{
  "type": "Feature",
  "properties": {
    "gn:admin1_code":"13.0",
    "gn:asciiname":"Kpao",
    "gn:country_code":"BJ",
    "gn:dem":435,
    "gn:feature_class":"P",
    "gn:feature_code":"PPL",
    "gn:name":"Kpao",
    "gn:population":0,
    "gn:timezone":"Africa/Porto-Novo",
    "iso:country":"BJ",
    "wof:name":"Kpao",
    "wof:placetype":"locality"
},
  "geometry": {"coordinates":[1.56745,9.4602],"type":"Point"}
}