{
  "type": "Feature",
  "properties": {
    "gn:admin1_code":"11.0",
    "gn:asciiname":"Takete",
    "gn:country_code":"BJ",
    "gn:dem":240,
    "gn:feature_class":"P",
    "gn:feature_code":"PPL",
    "gn:name":"Tak\u00e9t\u00e9",
    "gn:population":0,
    "gn:timezone":"Africa/Porto-Novo",
    "iso:country":"BJ",
    "wof:name":"Takete",
    "wof:placetype":"locality"
},
  "geometry": {"coordinates":[1.65112,8.07003],"type":"Point"}
}