{
  "type": "Feature",
  "properties": {
    "gn:admin1_code":"8.0",
    "gn:asciiname":"Goussonbouya",
    "gn:country_code":"BJ",
    "gn:dem":409,
    "gn:feature_class":"P",
    "gn:feature_code":"PPL",
    "gn:name":"Goussonbouya",
    "gn:population":0,
    "gn:timezone":"Africa/Porto-Novo",
    "iso:country":"BJ",
    "wof:name":"Goussonbouya",
    "wof:placetype":"locality"
},
  "geometry": {"coordinates":[1.63327,10.03942],"type":"Point"}
}