{
  "type": "Feature",
  "properties": {
    "gn:admin1_code":"16.0",
    "gn:asciiname":"Avabodji",
    "gn:country_code":"BJ",
    "gn:dem":1,
    "gn:feature_class":"P",
    "gn:feature_code":"PPL",
    "gn:name":"Avabodji",
    "gn:population":0,
    "gn:timezone":"Africa/Porto-Novo",
    "iso:country":"BJ",
    "wof:name":"Avabodji",
    "wof:placetype":"locality"
},
  "geometry": {"coordinates":[2.53581,6.52337],"type":"Point"}
}