{
  "type": "Feature",
  "properties": {
    "gn:admin1_code":"10.0",
    "gn:asciiname":"Weragando",
    "gn:country_code":"BJ",
    "gn:dem":434,
    "gn:feature_class":"P",
    "gn:feature_code":"PPL",
    "gn:name":"W\u00e9ragando",
    "gn:population":0,
    "gn:timezone":"Africa/Porto-Novo",
    "iso:country":"BJ",
    "wof:name":"Weragando",
    "wof:placetype":"locality"
},
  "geometry": {"coordinates":[3.01845,9.8904],"type":"Point"}
}