{
  "type": "Feature",
  "properties": {
    "gn:admin1_code":"10.0",
    "gn:asciiname":"Kouboure",
    "gn:country_code":"BJ",
    "gn:dem":373,
    "gn:feature_class":"P",
    "gn:feature_code":"PPL",
    "gn:name":"Koubour\u00e9",
    "gn:population":0,
    "gn:timezone":"Africa/Porto-Novo",
    "iso:country":"BJ",
    "wof:name":"Kouboure",
    "wof:placetype":"locality"
},
  "geometry": {"coordinates":[2.94393,9.84646],"type":"Point"}
}