{
  "type": "Feature",
  "properties": {
    "gn:admin1_code":"18.0",
    "gn:asciiname":"Sinhoue-Zoume",
    "gn:country_code":"BJ",
    "gn:dem":69,
    "gn:feature_class":"P",
    "gn:feature_code":"PPL",
    "gn:name":"Sinhou\u00e9-Zoum\u00e9",
    "gn:population":0,
    "gn:timezone":"Africa/Porto-Novo",
    "iso:country":"BJ",
    "wof:name":"Sinhoue-Zoume",
    "wof:placetype":"locality"
},
  "geometry": {"coordinates":[1.98333,7.01667],"type":"Point"}
}