{
  "type": "Feature",
  "properties": {
    "gn:admin1_code":"13.0",
    "gn:asciiname":"Kokoourhou",
    "gn:country_code":"BJ",
    "gn:dem":444,
    "gn:feature_class":"P",
    "gn:feature_code":"PPL",
    "gn:name":"Kokoourhou",
    "gn:population":0,
    "gn:timezone":"Africa/Porto-Novo",
    "iso:country":"BJ",
    "name:und_x_variant":[
        "Kokourou",
        "Kokoourhou"
    ],
    "wof:name":"Kokoourhou",
    "wof:placetype":"locality"
},
  "geometry": {"coordinates":[1.5866,9.5094],"type":"Point"}
}