{
  "type": "Feature",
  "properties": {
    "gn:admin1_code":"13.0",
    "gn:asciiname":"Babanzaoure",
    "gn:cc2":"BJ",
    "gn:country_code":"BJ",
    "gn:dem":472,
    "gn:feature_class":"P",
    "gn:feature_code":"PPL",
    "gn:name":"Babanzaour\u00e9",
    "gn:population":0,
    "gn:timezone":"Africa/Porto-Novo",
    "iso:country":"BJ",
    "name:und_x_variant":[
        "Dori",
        "Babanzaour\u00e9"
    ],
    "wof:name":"Babanzaoure",
    "wof:placetype":"locality"
},
  "geometry": {"coordinates":[1.55,9.75],"type":"Point"}
}