{
  "type": "Feature",
  "properties": {
    "gn:admin1_code":"8.0",
    "gn:asciiname":"Takissari",
    "gn:country_code":"BJ",
    "gn:dem":534,
    "gn:feature_class":"P",
    "gn:feature_code":"PPL",
    "gn:name":"Takissari",
    "gn:population":0,
    "gn:timezone":"Africa/Porto-Novo",
    "iso:country":"BJ",
    "name:und_x_variant":[
        "Taguissar\u00e9",
        "Takissari"
    ],
    "wof:name":"Takissari",
    "wof:placetype":"locality"
},
  "geometry": {"coordinates":[1.47248,10.40938],"type":"Point"}
}