{
  "type": "Feature",
  "properties": {
    "gn:admin1_code":"7.0",
    "gn:asciiname":"Gamarou",
    "gn:country_code":"BJ",
    "gn:dem":277,
    "gn:feature_class":"P",
    "gn:feature_code":"PPL",
    "gn:name":"Gamarou",
    "gn:population":0,
    "gn:timezone":"Africa/Porto-Novo",
    "iso:country":"BJ",
    "wof:name":"Gamarou",
    "wof:placetype":"locality"
},
  "geometry": {"coordinates":[2.52988,11.36138],"type":"Point"}
}