{
  "type": "Feature",
  "properties": {
    "gn:admin1_code":"10.0",
    "gn:asciiname":"Tourou",
    "gn:country_code":"BJ",
    "gn:dem":374,
    "gn:feature_class":"P",
    "gn:feature_code":"PPL",
    "gn:name":"Tourou",
    "gn:population":0,
    "gn:timezone":"Africa/Porto-Novo",
    "iso:country":"BJ",
    "wof:name":"Tourou",
    "wof:placetype":"locality"
},
  "geometry": {"coordinates":[2.5476,9.34479],"type":"Point"}
}