{
  "type": "Feature",
  "properties": {
    "gn:admin1_code":"8.0",
    "gn:asciiname":"Nyianande",
    "gn:country_code":"BJ",
    "gn:dem":201,
    "gn:feature_class":"P",
    "gn:feature_code":"PPL",
    "gn:name":"Nyianand\u00e9",
    "gn:population":0,
    "gn:timezone":"Africa/Porto-Novo",
    "iso:country":"BJ",
    "wof:name":"Nyianande",
    "wof:placetype":"locality"
},
  "geometry": {"coordinates":[0.83509,10.36755],"type":"Point"}
}