{
  "type": "Feature",
  "properties": {
    "gn:admin1_code":"10.0",
    "gn:asciiname":"Malounkoulou",
    "gn:country_code":"BJ",
    "gn:dem":383,
    "gn:feature_class":"P",
    "gn:feature_code":"PPL",
    "gn:name":"Malounkoulou",
    "gn:population":0,
    "gn:timezone":"Africa/Porto-Novo",
    "iso:country":"BJ",
    "wof:name":"Malounkoulou",
    "wof:placetype":"locality"
},
  "geometry": {"coordinates":[3.06667,9.23333],"type":"Point"}
}