{
  "type": "Feature",
  "properties": {
    "gn:admin1_code":"13.0",
    "gn:asciiname":"Mansar",
    "gn:country_code":"BJ",
    "gn:dem":449,
    "gn:feature_class":"P",
    "gn:feature_code":"PPL",
    "gn:name":"Mansar",
    "gn:population":0,
    "gn:timezone":"Africa/Porto-Novo",
    "iso:country":"BJ",
    "name:ceb_x_preferred":[
        "Mansar"
    ],
    "name:swe_x_preferred":[
        "Mansar"
    ],
    "wof:name":"Mansar",
    "wof:placetype":"locality"
},
  "geometry": {"coordinates":[1.49987,9.75301],"type":"Point"}
}