{
  "type": "Feature",
  "properties": {
    "gn:admin1_code":"8.0",
    "gn:asciiname":"Sinwa",
    "gn:country_code":"BJ",
    "gn:dem":320,
    "gn:feature_class":"P",
    "gn:feature_code":"PPL",
    "gn:name":"Sinwa",
    "gn:population":0,
    "gn:timezone":"Africa/Porto-Novo",
    "iso:country":"BJ",
    "wof:name":"Sinwa",
    "wof:placetype":"locality"
},
  "geometry": {"coordinates":[3.42156,11.0272],"type":"Point"}
}