{
  "type": "Feature",
  "properties": {
    "gn:admin1_code":"8.0",
    "gn:asciiname":"Niaro",
    "gn:country_code":"BJ",
    "gn:dem":537,
    "gn:feature_class":"P",
    "gn:feature_code":"PPL",
    "gn:name":"Niaro",
    "gn:population":0,
    "gn:timezone":"Africa/Porto-Novo",
    "iso:country":"BJ",
    "name:und_x_variant":[
        "Nioro",
        "Niaro"
    ],
    "wof:name":"Niaro",
    "wof:placetype":"locality"
},
  "geometry": {"coordinates":[1.5994,10.19661],"type":"Point"}
}