{
  "type": "Feature",
  "properties": {
    "gn:admin1_code":"7.0",
    "gn:asciiname":"Lougounzi",
    "gn:country_code":"BJ",
    "gn:dem":326,
    "gn:feature_class":"P",
    "gn:feature_code":"PPL",
    "gn:name":"Lougounzi",
    "gn:population":0,
    "gn:timezone":"Africa/Porto-Novo",
    "iso:country":"BJ",
    "wof:name":"Lougounzi",
    "wof:placetype":"locality"
},
  "geometry": {"coordinates":[3.60565,10.84282],"type":"Point"}
}