{
  "type": "Feature",
  "properties": {
    "gn:admin1_code":"7.0",
    "gn:asciiname":"Fetegou",
    "gn:country_code":"BJ",
    "gn:dem":293,
    "gn:feature_class":"P",
    "gn:feature_code":"PPL",
    "gn:name":"F\u00e9t\u00e9gou",
    "gn:population":0,
    "gn:timezone":"Africa/Porto-Novo",
    "iso:country":"BJ",
    "wof:name":"Fetegou",
    "wof:placetype":"locality"
},
  "geometry": {"coordinates":[2.3942,11.34452],"type":"Point"}
}