{
  "type": "Feature",
  "properties": {
    "gn:admin1_code":"13.0",
    "gn:asciiname":"Tiwabera",
    "gn:country_code":"BJ",
    "gn:dem":398,
    "gn:feature_class":"P",
    "gn:feature_code":"PPL",
    "gn:name":"Tiwab\u00e9ra",
    "gn:population":0,
    "gn:timezone":"Africa/Porto-Novo",
    "iso:country":"BJ",
    "wof:name":"Tiwabera",
    "wof:placetype":"locality"
},
  "geometry": {"coordinates":[1.78073,9.86456],"type":"Point"}
}