{
  "type": "Feature",
  "properties": {
    "gn:admin1_code":"18.0",
    "gn:asciiname":"Gnassata",
    "gn:country_code":"BJ",
    "gn:dem":158,
    "gn:feature_class":"P",
    "gn:feature_code":"PPL",
    "gn:name":"Gnassata",
    "gn:population":0,
    "gn:timezone":"Africa/Porto-Novo",
    "iso:country":"BJ",
    "wof:name":"Gnassata",
    "wof:placetype":"locality"
},
  "geometry": {"coordinates":[1.97007,7.23894],"type":"Point"}
}