{
  "type": "Feature",
  "properties": {
    "gn:admin1_code":"10.0",
    "gn:asciiname":"Douerou",
    "gn:country_code":"BJ",
    "gn:dem":371,
    "gn:feature_class":"P",
    "gn:feature_code":"PPL",
    "gn:name":"Dou\u00e9rou",
    "gn:population":0,
    "gn:timezone":"Africa/Porto-Novo",
    "iso:country":"BJ",
    "name:und_x_variant":[
        "Dou\u00e9rou"
    ],
    "wof:name":"Douerou",
    "wof:placetype":"locality"
},
  "geometry": {"coordinates":[2.55876,9.30516],"type":"Point"}
}