{
  "type": "Feature",
  "properties": {
    "gn:admin1_code":"11.0",
    "gn:asciiname":"Kofeogboni",
    "gn:country_code":"BJ",
    "gn:dem":236,
    "gn:feature_class":"P",
    "gn:feature_code":"PPL",
    "gn:name":"Kof\u00e9ogboni",
    "gn:population":0,
    "gn:timezone":"Africa/Porto-Novo",
    "iso:country":"BJ",
    "wof:name":"Kofeogboni",
    "wof:placetype":"locality"
},
  "geometry": {"coordinates":[1.68333,7.98333],"type":"Point"}
}