{
  "type": "Feature",
  "properties": {
    "gn:admin1_code":"12.0",
    "gn:asciiname":"Kpodaha",
    "gn:country_code":"BJ",
    "gn:dem":107,
    "gn:feature_class":"P",
    "gn:feature_code":"PPL",
    "gn:name":"Kpodaha",
    "gn:population":0,
    "gn:timezone":"Africa/Porto-Novo",
    "iso:country":"BJ",
    "wof:name":"Kpodaha",
    "wof:placetype":"locality"
},
  "geometry": {"coordinates":[1.70483,6.82374],"type":"Point"}
}