{
  "type": "Feature",
  "properties": {
    "gn:admin1_code":"8.0",
    "gn:asciiname":"Tindawanga",
    "gn:country_code":"BJ",
    "gn:dem":148,
    "gn:feature_class":"P",
    "gn:feature_code":"PPL",
    "gn:name":"Tindawanga",
    "gn:population":0,
    "gn:timezone":"Africa/Porto-Novo",
    "iso:country":"BJ",
    "wof:name":"Tindawanga",
    "wof:placetype":"locality"
},
  "geometry": {"coordinates":[0.82737,10.64461],"type":"Point"}
}