{
  "type": "Feature",
  "properties": {
    "gn:admin1_code":"10.0",
    "gn:asciiname":"Gando Matchore",
    "gn:country_code":"BJ",
    "gn:dem":359,
    "gn:feature_class":"P",
    "gn:feature_code":"PPL",
    "gn:name":"Gando Matchor\u00e9",
    "gn:population":0,
    "gn:timezone":"Africa/Porto-Novo",
    "iso:country":"BJ",
    "wof:name":"Gando Matchore",
    "wof:placetype":"locality"
},
  "geometry": {"coordinates":[3.23046,10.20919],"type":"Point"}
}