{
  "type": "Feature",
  "properties": {
    "gn:admin1_code":"8.0",
    "gn:asciiname":"Bourogourou",
    "gn:country_code":"BJ",
    "gn:dem":362,
    "gn:feature_class":"P",
    "gn:feature_code":"PPL",
    "gn:name":"Bourogourou",
    "gn:population":0,
    "gn:timezone":"Africa/Porto-Novo",
    "iso:country":"BJ",
    "wof:name":"Bourogourou",
    "wof:placetype":"locality"
},
  "geometry": {"coordinates":[2.03685,10.46517],"type":"Point"}
}