{
  "type": "Feature",
  "properties": {
    "gn:admin1_code":"11.0",
    "gn:asciiname":"Sabalagban",
    "gn:country_code":"BJ",
    "gn:dem":182,
    "gn:feature_class":"P",
    "gn:feature_code":"PPL",
    "gn:name":"Sabalagban",
    "gn:population":0,
    "gn:timezone":"Africa/Porto-Novo",
    "iso:country":"BJ",
    "wof:name":"Sabalagban",
    "wof:placetype":"locality"
},
  "geometry": {"coordinates":[2.19828,8.01332],"type":"Point"}
}