{
  "type": "Feature",
  "properties": {
    "gn:admin1_code":"8.0",
    "gn:asciiname":"Sein",
    "gn:country_code":"BJ",
    "gn:dem":264,
    "gn:feature_class":"P",
    "gn:feature_code":"PPL",
    "gn:name":"Sein",
    "gn:population":0,
    "gn:timezone":"Africa/Porto-Novo",
    "iso:country":"BJ",
    "name:deu_x_preferred":[
        "Sein"
    ],
    "name:fra_x_preferred":[
        "Sein"
    ],
    "name:nld_x_preferred":[
        "Sein"
    ],
    "wof:name":"Sein",
    "wof:placetype":"locality"
},
  "geometry": {"coordinates":[3.55204,11.29247],"type":"Point"}
}