{
  "type": "Feature",
  "properties": {
    "gn:admin1_code":"13.0",
    "gn:asciiname":"Sonaholou",
    "gn:country_code":"BJ",
    "gn:dem":435,
    "gn:feature_class":"P",
    "gn:feature_code":"PPL",
    "gn:name":"Sonaholou",
    "gn:population":0,
    "gn:timezone":"Africa/Porto-Novo",
    "iso:country":"BJ",
    "name:und_x_variant":[
        "Sanahollou",
        "Sonaholou"
    ],
    "wof:name":"Sonaholou",
    "wof:placetype":"locality"
},
  "geometry": {"coordinates":[1.39847,9.68339],"type":"Point"}
}