{
  "type": "Feature",
  "properties": {
    "gn:admin1_code":"8.0",
    "gn:asciiname":"Kokoirle",
    "gn:country_code":"BJ",
    "gn:dem":154,
    "gn:feature_class":"P",
    "gn:feature_code":"PPL",
    "gn:name":"Kokoirl\u00e9",
    "gn:population":0,
    "gn:timezone":"Africa/Porto-Novo",
    "iso:country":"BJ",
    "wof:name":"Kokoirle",
    "wof:placetype":"locality"
},
  "geometry": {"coordinates":[0.89811,10.64629],"type":"Point"}
}