{
  "type": "Feature",
  "properties": {
    "gn:admin1_code":"10.0",
    "gn:asciiname":"Semankale",
    "gn:country_code":"BJ",
    "gn:dem":323,
    "gn:feature_class":"P",
    "gn:feature_code":"PPL",
    "gn:name":"S\u00e9mankal\u00e9",
    "gn:population":0,
    "gn:timezone":"Africa/Porto-Novo",
    "iso:country":"BJ",
    "wof:name":"Semankale",
    "wof:placetype":"locality"
},
  "geometry": {"coordinates":[2.98623,10.33824],"type":"Point"}
}