{
  "type": "Feature",
  "properties": {
    "gn:admin1_code":"13.0",
    "gn:asciiname":"Korolongouzir",
    "gn:country_code":"BJ",
    "gn:dem":404,
    "gn:feature_class":"P",
    "gn:feature_code":"PPL",
    "gn:name":"Korolongouzir",
    "gn:population":0,
    "gn:timezone":"Africa/Porto-Novo",
    "iso:country":"BJ",
    "name:und_x_variant":[
        "Korolongzi",
        "Korolongouzir"
    ],
    "wof:name":"Korolongouzir",
    "wof:placetype":"locality"
},
  "geometry": {"coordinates":[1.79278,9.64284],"type":"Point"}
}