{
  "type": "Feature",
  "properties": {
    "gn:admin1_code":"7.0",
    "gn:asciiname":"Dassare",
    "gn:country_code":"BJ",
    "gn:dem":326,
    "gn:feature_class":"P",
    "gn:feature_code":"PPL",
    "gn:name":"Dassar\u00e9",
    "gn:population":0,
    "gn:timezone":"Africa/Porto-Novo",
    "iso:country":"BJ",
    "wof:name":"Dassare",
    "wof:placetype":"locality"
},
  "geometry": {"coordinates":[2.67028,10.70253],"type":"Point"}
}