{
  "type": "Feature",
  "properties": {
    "gn:admin1_code":"12.0",
    "gn:asciiname":"Dotota",
    "gn:country_code":"BJ",
    "gn:dem":70,
    "gn:feature_class":"P",
    "gn:feature_code":"PPL",
    "gn:name":"Dotota",
    "gn:population":0,
    "gn:timezone":"Africa/Porto-Novo",
    "iso:country":"BJ",
    "wof:name":"Dotota",
    "wof:placetype":"locality"
},
  "geometry": {"coordinates":[1.86667,7.15],"type":"Point"}
}