{
  "type": "Feature",
  "properties": {
    "gn:admin1_code":"8.0",
    "gn:asciiname":"Pabate",
    "gn:country_code":"BJ",
    "gn:dem":457,
    "gn:feature_class":"P",
    "gn:feature_code":"PPL",
    "gn:name":"Pabat\u00e9",
    "gn:population":0,
    "gn:timezone":"Africa/Porto-Novo",
    "iso:country":"BJ",
    "wof:name":"Pabate",
    "wof:placetype":"locality"
},
  "geometry": {"coordinates":[1.47631,10.4703],"type":"Point"}
}