{
  "type": "Feature",
  "properties": {
    "gn:admin1_code":"10.0",
    "gn:asciiname":"Takou",
    "gn:country_code":"BJ",
    "gn:dem":458,
    "gn:feature_class":"P",
    "gn:feature_code":"PPL",
    "gn:name":"Takou",
    "gn:population":0,
    "gn:timezone":"Africa/Porto-Novo",
    "iso:country":"BJ",
    "wof:name":"Takou",
    "wof:placetype":"locality"
},
  "geometry": {"coordinates":[3.21468,9.84916],"type":"Point"}
}