{
  "type": "Feature",
  "properties": {
    "gn:admin1_code":"9.0",
    "gn:asciiname":"Zogbohoue",
    "gn:country_code":"BJ",
    "gn:dem":9,
    "gn:feature_class":"P",
    "gn:feature_code":"PPL",
    "gn:name":"Zogbohoue",
    "gn:population":0,
    "gn:timezone":"Africa/Porto-Novo",
    "iso:country":"BJ",
    "wof:name":"Zogbohoue",
    "wof:placetype":"locality"
},
  "geometry": {"coordinates":[2.37801,6.38756],"type":"Point"}
}