{
  "type": "Feature",
  "properties": {
    "gn:admin1_code":"8.0",
    "gn:asciiname":"Tiessikourbou",
    "gn:country_code":"BJ",
    "gn:dem":459,
    "gn:feature_class":"P",
    "gn:feature_code":"PPL",
    "gn:name":"Tiessikourbou",
    "gn:population":0,
    "gn:timezone":"Africa/Porto-Novo",
    "iso:country":"BJ",
    "wof:name":"Tiessikourbou",
    "wof:placetype":"locality"
},
  "geometry": {"coordinates":[1.39217,10.41331],"type":"Point"}
}