{
  "type": "Feature",
  "properties": {
    "gn:admin1_code":"12.0",
    "gn:asciiname":"Locoha",
    "gn:country_code":"BJ",
    "gn:dem":153,
    "gn:feature_class":"P",
    "gn:feature_code":"PPL",
    "gn:name":"Locoha",
    "gn:population":0,
    "gn:timezone":"Africa/Porto-Novo",
    "iso:country":"BJ",
    "wof:name":"Locoha",
    "wof:placetype":"locality"
},
  "geometry": {"coordinates":[1.68333,6.91667],"type":"Point"}
}