{
  "type": "Feature",
  "properties": {
    "gn:admin1_code":"10.0",
    "gn:asciiname":"Boun",
    "gn:country_code":"BJ",
    "gn:dem":344,
    "gn:feature_class":"P",
    "gn:feature_code":"PPL",
    "gn:name":"Boun",
    "gn:population":0,
    "gn:timezone":"Africa/Porto-Novo",
    "iso:country":"BJ",
    "wof:name":"Boun",
    "wof:placetype":"locality"
},
  "geometry": {"coordinates":[2.52361,9.24019],"type":"Point"}
}