{
  "type": "Feature",
  "properties": {
    "gn:admin1_code":"8.0",
    "gn:asciiname":"Djessekou-Sinngreu",
    "gn:country_code":"BJ",
    "gn:dem":441,
    "gn:feature_class":"P",
    "gn:feature_code":"PPL",
    "gn:name":"Dj\u00e9ss\u00e9kou-Sinngreu",
    "gn:population":0,
    "gn:timezone":"Africa/Porto-Novo",
    "iso:country":"BJ",
    "wof:name":"Djessekou-Sinngreu",
    "wof:placetype":"locality"
},
  "geometry": {"coordinates":[1.64594,9.99667],"type":"Point"}
}