{
  "type": "Feature",
  "properties": {
    "gn:admin1_code":"8.0",
    "gn:asciiname":"Titonzi-Kaouta",
    "gn:country_code":"BJ",
    "gn:dem":188,
    "gn:feature_class":"P",
    "gn:feature_code":"PPL",
    "gn:name":"Titonzi-Kaouta",
    "gn:population":0,
    "gn:timezone":"Africa/Porto-Novo",
    "iso:country":"BJ",
    "wof:name":"Titonzi-Kaouta",
    "wof:placetype":"locality"
},
  "geometry": {"coordinates":[1.01673,10.66741],"type":"Point"}
}