{
  "type": "Feature",
  "properties": {
    "gn:admin1_code":"10.0",
    "gn:asciiname":"Nalou",
    "gn:country_code":"BJ",
    "gn:dem":416,
    "gn:feature_class":"P",
    "gn:feature_code":"PPL",
    "gn:name":"Nalou",
    "gn:population":0,
    "gn:timezone":"Africa/Porto-Novo",
    "iso:country":"BJ",
    "wof:name":"Nalou",
    "wof:placetype":"locality"
},
  "geometry": {"coordinates":[2.89642,9.93145],"type":"Point"}
}