{
  "type": "Feature",
  "properties": {
    "gn:admin1_code":"8.0",
    "gn:asciiname":"Sourou",
    "gn:country_code":"BJ",
    "gn:dem":293,
    "gn:feature_class":"P",
    "gn:feature_code":"PPL",
    "gn:name":"Sourou",
    "gn:population":0,
    "gn:timezone":"Africa/Porto-Novo",
    "iso:country":"BJ",
    "name:ceb_x_preferred":[
        "Sourou"
    ],
    "name:deu_x_preferred":[
        "Sourou"
    ],
    "name:fra_x_preferred":[
        "Sourou"
    ],
    "name:swe_x_preferred":[
        "Sourou"
    ],
    "wof:name":"Sourou",
    "wof:placetype":"locality"
},
  "geometry": {"coordinates":[3.0678,11.4395],"type":"Point"}
}