{
  "type": "Feature",
  "properties": {
    "gn:admin1_code":"8.0",
    "gn:asciiname":"Souroubora",
    "gn:country_code":"BJ",
    "gn:dem":343,
    "gn:feature_class":"P",
    "gn:feature_code":"PPL",
    "gn:name":"Souroubora",
    "gn:population":0,
    "gn:timezone":"Africa/Porto-Novo",
    "iso:country":"BJ",
    "wof:name":"Souroubora",
    "wof:placetype":"locality"
},
  "geometry": {"coordinates":[2.04452,10.34168],"type":"Point"}
}