{
  "type": "Feature",
  "properties": {
    "gn:admin1_code":"10.0",
    "gn:asciiname":"Gangoulo",
    "gn:country_code":"BJ",
    "gn:dem":423,
    "gn:feature_class":"P",
    "gn:feature_code":"PPL",
    "gn:name":"Gangoulo",
    "gn:population":0,
    "gn:timezone":"Africa/Porto-Novo",
    "iso:country":"BJ",
    "wof:name":"Gangoulo",
    "wof:placetype":"locality"
},
  "geometry": {"coordinates":[3.13913,9.63434],"type":"Point"}
}