{
  "type": "Feature",
  "properties": {
    "gn:admin1_code":"11.0",
    "gn:asciiname":"Agbaton",
    "gn:country_code":"BJ",
    "gn:dem":227,
    "gn:feature_class":"P",
    "gn:feature_code":"PPL",
    "gn:name":"Agbaton",
    "gn:population":0,
    "gn:timezone":"Africa/Porto-Novo",
    "iso:country":"BJ",
    "wof:name":"Agbaton",
    "wof:placetype":"locality"
},
  "geometry": {"coordinates":[1.68891,7.82395],"type":"Point"}
}