{
  "type": "Feature",
  "properties": {
    "gn:admin1_code":"9.0",
    "gn:asciiname":"Allodossicodji",
    "gn:country_code":"BJ",
    "gn:dem":29,
    "gn:feature_class":"P",
    "gn:feature_code":"PPL",
    "gn:name":"Allodossicodji",
    "gn:population":0,
    "gn:timezone":"Africa/Porto-Novo",
    "iso:country":"BJ",
    "name:und_x_variant":[
        "Aladassicodji",
        "Allodossicodji"
    ],
    "wof:name":"Allodossicodji",
    "wof:placetype":"locality"
},
  "geometry": {"coordinates":[2.1375,6.43711],"type":"Point"}
}