{
  "type": "Feature",
  "properties": {
    "gn:admin1_code":"8.0",
    "gn:asciiname":"Tiouka",
    "gn:country_code":"BJ",
    "gn:dem":167,
    "gn:feature_class":"P",
    "gn:feature_code":"PPL",
    "gn:name":"Tiouka",
    "gn:population":0,
    "gn:timezone":"Africa/Porto-Novo",
    "iso:country":"BJ",
    "wof:name":"Tiouka",
    "wof:placetype":"locality"
},
  "geometry": {"coordinates":[0.9042,10.83176],"type":"Point"}
}