{
  "type": "Feature",
  "properties": {
    "gn:admin1_code":"13.0",
    "gn:asciiname":"Tikouka",
    "gn:country_code":"BJ",
    "gn:dem":471,
    "gn:feature_class":"P",
    "gn:feature_code":"PPL",
    "gn:name":"Tikouka",
    "gn:population":0,
    "gn:timezone":"Africa/Porto-Novo",
    "iso:country":"BJ",
    "wof:name":"Tikouka",
    "wof:placetype":"locality"
},
  "geometry": {"coordinates":[1.58329,9.6118],"type":"Point"}
}