{
  "type": "Feature",
  "properties": {
    "gn:admin1_code":"8.0",
    "gn:asciiname":"Tinetine",
    "gn:country_code":"BJ",
    "gn:dem":165,
    "gn:feature_class":"P",
    "gn:feature_code":"PPL",
    "gn:name":"Tin\u00e9tine",
    "gn:population":0,
    "gn:timezone":"Africa/Porto-Novo",
    "iso:country":"BJ",
    "wof:name":"Tinetine",
    "wof:placetype":"locality"
},
  "geometry": {"coordinates":[1.09896,10.98117],"type":"Point"}
}