{
  "type": "Feature",
  "properties": {
    "gn:admin1_code":"18.0",
    "gn:asciiname":"Glogougon",
    "gn:country_code":"BJ",
    "gn:dem":168,
    "gn:feature_class":"P",
    "gn:feature_code":"PPL",
    "gn:name":"Glogougon",
    "gn:population":0,
    "gn:timezone":"Africa/Porto-Novo",
    "iso:country":"BJ",
    "wof:name":"Glogougon",
    "wof:placetype":"locality"
},
  "geometry": {"coordinates":[1.8866,7.35327],"type":"Point"}
}