{
  "type": "Feature",
  "properties": {
    "gn:admin1_code":"8.0",
    "gn:asciiname":"Kane",
    "gn:country_code":"BJ",
    "gn:dem":151,
    "gn:feature_class":"P",
    "gn:feature_code":"PPL",
    "gn:name":"Kan\u00e9",
    "gn:population":0,
    "gn:timezone":"Africa/Porto-Novo",
    "iso:country":"BJ",
    "name:bel_x_preferred":[
        "\u041a\u0435\u0439\u043d"
    ],
    "name:bul_x_preferred":[
        "\u041a\u0435\u0439\u043d"
    ],
    "name:cat_x_preferred":[
        "Kane"
    ],
    "name:ceb_x_preferred":[
        "Kane"
    ],
    "name:ces_x_preferred":[
        "Kane"
    ],
    "name:deu_x_preferred":[
        "Kane"
    ],
    "name:fin_x_preferred":[
        "Kane"
    ],
    "name:fra_x_preferred":[
        "Kane"
    ],
    "name:ita_x_preferred":[
        "Kane"
    ],
    "name:jpn_x_preferred":[
        "\u30b1\u30a4\u30f3"
    ],
    "name:nld_x_preferred":[
        "Kane"
    ],
    "name:nor_x_preferred":[
        "Kane"
    ],
    "name:pol_x_preferred":[
        "Kane"
    ],
    "name:por_x_preferred":[
        "Kane"
    ],
    "name:ron_x_preferred":[
        "Kane"
    ],
    "name:rus_x_preferred":[
        "\u041a\u0435\u0439\u043d"
    ],
    "name:sco_x_preferred":[
        "Kane"
    ],
    "name:spa_x_preferred":[
        "Kane"
    ],
    "name:srp_x_preferred":[
        "\u041a\u0435\u0458\u043d"
    ],
    "name:swe_x_preferred":[
        "Kane"
    ],
    "name:tur_x_preferred":[
        "Kane"
    ],
    "name:ukr_x_preferred":[
        "\u041a\u0435\u0439\u043d"
    ],
    "name:vie_x_preferred":[
        "Kane"
    ],
    "name:vol_x_preferred":[
        "Kane"
    ],
    "wof:name":"Kane",
    "wof:placetype":"locality"
},
  "geometry": {"coordinates":[0.85641,10.63912],"type":"Point"}
}