{
  "type": "Feature",
  "properties": {
    "gn:admin1_code":"7.0",
    "gn:admin2_code":"10344469.0",
    "gn:asciiname":"Sori",
    "gn:country_code":"BJ",
    "gn:dem":327,
    "gn:feature_class":"P",
    "gn:feature_code":"PPL",
    "gn:name":"Sori",
    "gn:population":0,
    "gn:timezone":"Africa/Porto-Novo",
    "iso:country":"BJ",
    "name:ceb_x_preferred":[
        "Sori"
    ],
    "name:fra_x_preferred":[
        "Sori"
    ],
    "name:ita_x_preferred":[
        "Sori"
    ],
    "name:msa_x_preferred":[
        "Sori"
    ],
    "name:swe_x_preferred":[
        "Sori"
    ],
    "name:und_x_variant":[
        "Sor"
    ],
    "wof:name":"Sori",
    "wof:placetype":"locality"
},
  "geometry": {"coordinates":[2.77878,10.72015],"type":"Point"}
}