{
  "type": "Feature",
  "properties": {
    "gn:admin1_code":"15.0",
    "gn:asciiname":"Djanglame",
    "gn:country_code":"BJ",
    "gn:dem":5,
    "gn:feature_class":"P",
    "gn:feature_code":"PPL",
    "gn:name":"Djanglam\u00e9",
    "gn:population":0,
    "gn:timezone":"Africa/Porto-Novo",
    "iso:country":"BJ",
    "name:ceb_x_preferred":[
        "Djanglam\u00e9"
    ],
    "name:ita_x_preferred":[
        "Djanglanm\u00e8"
    ],
    "name:msa_x_preferred":[
        "Djanglanm\u00e8"
    ],
    "name:swe_x_preferred":[
        "Djanglam\u00e9"
    ],
    "name:und_x_variant":[
        "Djanglanm\u00e9",
        "Djanglam\u00e9"
    ],
    "wof:name":"Djanglame",
    "wof:placetype":"locality"
},
  "geometry": {"coordinates":[1.81355,6.40673],"type":"Point"}
}