{
  "type": "Feature",
  "properties": {
    "gn:admin1_code":"10.0",
    "gn:asciiname":"Ga Yakabou",
    "gn:country_code":"BJ",
    "gn:dem":342,
    "gn:feature_class":"P",
    "gn:feature_code":"PPL",
    "gn:name":"Ga Yakabou",
    "gn:population":0,
    "gn:timezone":"Africa/Porto-Novo",
    "iso:country":"BJ",
    "wof:name":"Ga Yakabou",
    "wof:placetype":"locality"
},
  "geometry": {"coordinates":[2.55753,9.41119],"type":"Point"}
}