{
  "type": "Feature",
  "properties": {
    "gn:admin1_code":"15.0",
    "gn:asciiname":"Kpenou",
    "gn:country_code":"BJ",
    "gn:dem":15,
    "gn:feature_class":"P",
    "gn:feature_code":"PPL",
    "gn:name":"Kp\u00e9nou",
    "gn:population":0,
    "gn:timezone":"Africa/Porto-Novo",
    "iso:country":"BJ",
    "wof:name":"Kpenou",
    "wof:placetype":"locality"
},
  "geometry": {"coordinates":[1.76868,6.58006],"type":"Point"}
}