{
  "type": "Feature",
  "properties": {
    "gn:admin1_code":"10.0",
    "gn:asciiname":"Tamoussia",
    "gn:country_code":"BJ",
    "gn:dem":379,
    "gn:feature_class":"P",
    "gn:feature_code":"PPL",
    "gn:name":"Tamoussia",
    "gn:population":0,
    "gn:timezone":"Africa/Porto-Novo",
    "iso:country":"BJ",
    "wof:name":"Tamoussia",
    "wof:placetype":"locality"
},
  "geometry": {"coordinates":[2.7165,9.76818],"type":"Point"}
}