{
  "type": "Feature",
  "properties": {
    "gn:admin1_code":"11.0",
    "gn:admin2_code":"8260647.0",
    "gn:asciiname":"Koko",
    "gn:country_code":"BJ",
    "gn:dem":239,
    "gn:feature_class":"P",
    "gn:feature_code":"PPL",
    "gn:name":"Koko",
    "gn:population":0,
    "gn:timezone":"Africa/Porto-Novo",
    "iso:country":"BJ",
    "wof:name":"Koko",
    "wof:placetype":"locality"
},
  "geometry": {"coordinates":[1.83658,8.37488],"type":"Point"}
}