{
  "type": "Feature",
  "properties": {
    "gn:admin1_code":"10.0",
    "gn:asciiname":"Pourari",
    "gn:country_code":"BJ",
    "gn:dem":308,
    "gn:feature_class":"P",
    "gn:feature_code":"PPL",
    "gn:name":"Pourari",
    "gn:population":0,
    "gn:timezone":"Africa/Porto-Novo",
    "iso:country":"BJ",
    "wof:name":"Pourari",
    "wof:placetype":"locality"
},
  "geometry": {"coordinates":[2.38344,9.27183],"type":"Point"}
}