{
  "type": "Feature",
  "properties": {
    "gn:admin1_code":"8.0",
    "gn:asciiname":"Kounokogou",
    "gn:country_code":"BJ",
    "gn:dem":293,
    "gn:feature_class":"P",
    "gn:feature_code":"PPL",
    "gn:name":"Kounokogou",
    "gn:population":0,
    "gn:timezone":"Africa/Porto-Novo",
    "iso:country":"BJ",
    "wof:name":"Kounokogou",
    "wof:placetype":"locality"
},
  "geometry": {"coordinates":[1.1509,10.22216],"type":"Point"}
}