{
  "type": "Feature",
  "properties": {
    "gn:admin1_code":"13.0",
    "gn:asciiname":"Anoun",
    "gn:country_code":"BJ",
    "gn:dem":424,
    "gn:feature_class":"P",
    "gn:feature_code":"PPL",
    "gn:name":"Anoun",
    "gn:population":0,
    "gn:timezone":"Africa/Porto-Novo",
    "iso:country":"BJ",
    "name:und_x_variant":[
        "Kossar Aroum",
        "Anoun"
    ],
    "wof:name":"Anoun",
    "wof:placetype":"locality"
},
  "geometry": {"coordinates":[1.4891,9.70784],"type":"Point"}
}