{
  "type": "Feature",
  "properties": {
    "gn:admin1_code":"10.0",
    "gn:asciiname":"Suinrou",
    "gn:country_code":"BJ",
    "gn:dem":372,
    "gn:feature_class":"P",
    "gn:feature_code":"PPL",
    "gn:name":"Suinrou",
    "gn:population":0,
    "gn:timezone":"Africa/Porto-Novo",
    "iso:country":"BJ",
    "wof:name":"Suinrou",
    "wof:placetype":"locality"
},
  "geometry": {"coordinates":[2.62154,9.7854],"type":"Point"}
}