{
  "type": "Feature",
  "properties": {
    "gn:admin1_code":"0.0",
    "gn:asciiname":"Avlo",
    "gn:country_code":"BJ",
    "gn:dem":64,
    "gn:feature_class":"P",
    "gn:feature_code":"PPL",
    "gn:name":"Avlo",
    "gn:population":0,
    "gn:timezone":"Africa/Porto-Novo",
    "iso:country":"BJ",
    "wof:name":"Avlo",
    "wof:placetype":"locality"
},
  "geometry": {"coordinates":[1.89178,6.29386],"type":"Point"}
}