{
  "type": "Feature",
  "properties": {
    "gn:admin1_code":"8.0",
    "gn:asciiname":"Tiangoubou",
    "gn:country_code":"BJ",
    "gn:dem":337,
    "gn:feature_class":"P",
    "gn:feature_code":"PPL",
    "gn:name":"Tiangoubou",
    "gn:population":0,
    "gn:timezone":"Africa/Porto-Novo",
    "iso:country":"BJ",
    "wof:name":"Tiangoubou",
    "wof:placetype":"locality"
},
  "geometry": {"coordinates":[1.31943,10.65409],"type":"Point"}
}