{
  "type": "Feature",
  "properties": {
    "gn:admin1_code":"8.0",
    "gn:asciiname":"Tandafa",
    "gn:country_code":"BJ",
    "gn:dem":379,
    "gn:feature_class":"P",
    "gn:feature_code":"PPL",
    "gn:name":"Tandafa",
    "gn:population":0,
    "gn:timezone":"Africa/Porto-Novo",
    "iso:country":"BJ",
    "wof:name":"Tandafa",
    "wof:placetype":"locality"
},
  "geometry": {"coordinates":[1.63422,10.69187],"type":"Point"}
}