{
  "type": "Feature",
  "properties": {
    "gn:admin1_code":"13.0",
    "gn:asciiname":"Palarhou",
    "gn:country_code":"BJ",
    "gn:dem":429,
    "gn:feature_class":"P",
    "gn:feature_code":"PPL",
    "gn:name":"Palarhou",
    "gn:population":0,
    "gn:timezone":"Africa/Porto-Novo",
    "iso:country":"BJ",
    "wof:name":"Palarhou",
    "wof:placetype":"locality"
},
  "geometry": {"coordinates":[1.65507,9.61244],"type":"Point"}
}