{
  "type": "Feature",
  "properties": {
    "gn:admin1_code":"13.0",
    "gn:asciiname":"Tchoue",
    "gn:cc2":"BJ",
    "gn:country_code":"BJ",
    "gn:dem":440,
    "gn:feature_class":"P",
    "gn:feature_code":"PPL",
    "gn:name":"Tchou\u00e9",
    "gn:population":0,
    "gn:timezone":"Africa/Porto-Novo",
    "iso:country":"BJ",
    "name:und_x_variant":[
        "Djou\u00e9",
        "Tchou\u00e9"
    ],
    "wof:name":"Tchoue",
    "wof:placetype":"locality"
},
  "geometry": {"coordinates":[1.46667,9.61667],"type":"Point"}
}