{
  "type": "Feature",
  "properties": {
    "gn:admin1_code":"18.0",
    "gn:asciiname":"Sopa-Tangagon",
    "gn:country_code":"BJ",
    "gn:dem":171,
    "gn:feature_class":"P",
    "gn:feature_code":"PPL",
    "gn:name":"Sopa-Tangagon",
    "gn:population":0,
    "gn:timezone":"Africa/Porto-Novo",
    "iso:country":"BJ",
    "wof:name":"Sopa-Tangagon",
    "wof:placetype":"locality"
},
  "geometry": {"coordinates":[1.96667,7.41667],"type":"Point"}
}