{
  "type": "Feature",
  "properties": {
    "gn:admin1_code":"8.0",
    "gn:asciiname":"Massangari",
    "gn:country_code":"BJ",
    "gn:dem":206,
    "gn:feature_class":"P",
    "gn:feature_code":"PPL",
    "gn:name":"Massangari",
    "gn:population":0,
    "gn:timezone":"Africa/Porto-Novo",
    "iso:country":"BJ",
    "wof:name":"Massangari",
    "wof:placetype":"locality"
},
  "geometry": {"coordinates":[3.29417,11.35146],"type":"Point"}
}