{
  "type": "Feature",
  "properties": {
    "gn:admin1_code":"13.0",
    "gn:asciiname":"Alitokoum",
    "gn:country_code":"BJ",
    "gn:dem":419,
    "gn:feature_class":"P",
    "gn:feature_code":"PPL",
    "gn:name":"Alitokoum",
    "gn:population":0,
    "gn:timezone":"Africa/Porto-Novo",
    "iso:country":"BJ",
    "wof:name":"Alitokoum",
    "wof:placetype":"locality"
},
  "geometry": {"coordinates":[1.38112,9.75225],"type":"Point"}
}