{
  "type": "Feature",
  "properties": {
    "gn:admin1_code":"13.0",
    "gn:asciiname":"Kemeni",
    "gn:country_code":"BJ",
    "gn:dem":421,
    "gn:feature_class":"P",
    "gn:feature_code":"PPL",
    "gn:name":"K\u00e9m\u00e9ni",
    "gn:population":0,
    "gn:timezone":"Africa/Porto-Novo",
    "iso:country":"BJ",
    "name:und_x_variant":[
        "Aw\u00e9",
        "K\u00e9m\u00e9ni"
    ],
    "wof:name":"Kemeni",
    "wof:placetype":"locality"
},
  "geometry": {"coordinates":[1.57642,9.30731],"type":"Point"}
}