{
  "type": "Feature",
  "properties": {
    "gn:admin1_code":"8.0",
    "gn:asciiname":"Namoutiaga",
    "gn:country_code":"BJ",
    "gn:dem":208,
    "gn:feature_class":"P",
    "gn:feature_code":"PPL",
    "gn:name":"Namoutiaga",
    "gn:population":0,
    "gn:timezone":"Africa/Porto-Novo",
    "iso:country":"BJ",
    "wof:name":"Namoutiaga",
    "wof:placetype":"locality"
},
  "geometry": {"coordinates":[0.9433,10.45501],"type":"Point"}
}