{
  "type": "Feature",
  "properties": {
    "gn:admin1_code":"12.0",
    "gn:admin2_code":"10344475.0",
    "gn:admin3_code":"11790015.0",
    "gn:asciiname":"Lalo",
    "gn:country_code":"BJ",
    "gn:dem":112,
    "gn:feature_class":"P",
    "gn:feature_code":"PPL",
    "gn:name":"Lalo",
    "gn:population":0,
    "gn:timezone":"Africa/Porto-Novo",
    "iso:country":"BJ",
    "name:ceb_x_preferred":[
        "Lalo"
    ],
    "name:fra_x_preferred":[
        "Lalo"
    ],
    "name:frr_x_preferred":[
        "Lalo"
    ],
    "name:ita_x_preferred":[
        "Lalo"
    ],
    "name:msa_x_preferred":[
        "Lalo"
    ],
    "name:nld_x_preferred":[
        "Lalo"
    ],
    "name:pol_x_preferred":[
        "Lalo"
    ],
    "name:spa_x_preferred":[
        "Lalo"
    ],
    "name:swe_x_preferred":[
        "Lalo"
    ],
    "name:urd_x_preferred":[
        "\u0644\u0627\u0644\u0648"
    ],
    "name:zho_x_preferred":[
        "\u62c9\u6d1b"
    ],
    "wof:name":"Lalo",
    "wof:placetype":"locality"
},
  "geometry": {"coordinates":[1.88994,6.92869],"type":"Point"}
}