{
  "type": "Feature",
  "properties": {
    "gn:admin1_code":"11.0",
    "gn:asciiname":"Pepelou",
    "gn:country_code":"BJ",
    "gn:dem":262,
    "gn:feature_class":"P",
    "gn:feature_code":"PPL",
    "gn:name":"P\u00e9p\u00e9lou",
    "gn:population":0,
    "gn:timezone":"Africa/Porto-Novo",
    "iso:country":"BJ",
    "wof:name":"Pepelou",
    "wof:placetype":"locality"
},
  "geometry": {"coordinates":[1.69448,8.11674],"type":"Point"}
}