{
  "type": "Feature",
  "properties": {
    "gn:admin1_code":"10.0",
    "gn:admin2_code":"7669269.0",
    "gn:admin3_code":"11790205.0",
    "gn:asciiname":"Serarou",
    "gn:country_code":"BJ",
    "gn:dem":341,
    "gn:feature_class":"P",
    "gn:feature_code":"PPL",
    "gn:name":"S\u00e9rarou",
    "gn:population":0,
    "gn:timezone":"Africa/Porto-Novo",
    "iso:country":"BJ",
    "name:ceb_x_preferred":[
        "S\u00e9rarou"
    ],
    "name:ita_x_preferred":[
        "Sirarou"
    ],
    "name:msa_x_preferred":[
        "Sirarou"
    ],
    "name:swe_x_preferred":[
        "S\u00e9rarou"
    ],
    "name:und_x_variant":[
        "Seraru",
        "S\u00e9narou",
        "Sirarou",
        "S\u00e9rarou"
    ],
    "wof:name":"Serarou",
    "wof:placetype":"locality"
},
  "geometry": {"coordinates":[2.64293,9.58901],"type":"Point"}
}