{
  "type": "Feature",
  "properties": {
    "gn:admin1_code":"10.0",
    "gn:asciiname":"Sakaro",
    "gn:country_code":"BJ",
    "gn:dem":375,
    "gn:feature_class":"P",
    "gn:feature_code":"PPL",
    "gn:name":"Sakaro",
    "gn:population":0,
    "gn:timezone":"Africa/Porto-Novo",
    "iso:country":"BJ",
    "wof:name":"Sakaro",
    "wof:placetype":"locality"
},
  "geometry": {"coordinates":[2.37465,10.11228],"type":"Point"}
}