{
  "type": "Feature",
  "properties": {
    "gn:admin1_code":"8.0",
    "gn:asciiname":"Kouolohon",
    "gn:country_code":"BJ",
    "gn:dem":233,
    "gn:feature_class":"P",
    "gn:feature_code":"PPL",
    "gn:name":"Kouolohon",
    "gn:population":0,
    "gn:timezone":"Africa/Porto-Novo",
    "iso:country":"BJ",
    "wof:name":"Kouolohon",
    "wof:placetype":"locality"
},
  "geometry": {"coordinates":[1.08272,10.64365],"type":"Point"}
}