{
  "type": "Feature",
  "properties": {
    "gn:admin1_code":"10.0",
    "gn:asciiname":"Forane Kparou",
    "gn:country_code":"BJ",
    "gn:dem":335,
    "gn:feature_class":"P",
    "gn:feature_code":"PPL",
    "gn:name":"Foran\u00e9 Kparou",
    "gn:population":0,
    "gn:timezone":"Africa/Porto-Novo",
    "iso:country":"BJ",
    "name:und_x_variant":[
        "Foran\u00e9 Kparou"
    ],
    "wof:name":"Forane Kparou",
    "wof:placetype":"locality"
},
  "geometry": {"coordinates":[2.55944,9.40225],"type":"Point"}
}