{
  "type": "Feature",
  "properties": {
    "gn:admin1_code":"8.0",
    "gn:asciiname":"Tapounta",
    "gn:country_code":"BJ",
    "gn:dem":300,
    "gn:feature_class":"P",
    "gn:feature_code":"PPL",
    "gn:name":"Tapounta",
    "gn:population":0,
    "gn:timezone":"Africa/Porto-Novo",
    "iso:country":"BJ",
    "name:und_x_variant":[
        "Tapouta",
        "Tapounta"
    ],
    "wof:name":"Tapounta",
    "wof:placetype":"locality"
},
  "geometry": {"coordinates":[1.31373,10.08989],"type":"Point"}
}