{
  "type": "Feature",
  "properties": {
    "gn:admin1_code":"11.0",
    "gn:asciiname":"Mondji",
    "gn:country_code":"BJ",
    "gn:dem":193,
    "gn:feature_class":"P",
    "gn:feature_code":"PPL",
    "gn:name":"Mondji",
    "gn:population":0,
    "gn:timezone":"Africa/Porto-Novo",
    "iso:country":"BJ",
    "wof:name":"Mondji",
    "wof:placetype":"locality"
},
  "geometry": {"coordinates":[1.98333,8.06667],"type":"Point"}
}