{
  "type": "Feature",
  "properties": {
    "gn:admin1_code":"9.0",
    "gn:asciiname":"Kouzoume",
    "gn:country_code":"BJ",
    "gn:dem":40,
    "gn:feature_class":"P",
    "gn:feature_code":"PPL",
    "gn:name":"Kouzoum\u00e9",
    "gn:population":0,
    "gn:timezone":"Africa/Porto-Novo",
    "iso:country":"BJ",
    "name:und_x_variant":[
        "Couzoum\u00e9",
        "Kouzoum\u00e9"
    ],
    "wof:name":"Kouzoume",
    "wof:placetype":"locality"
},
  "geometry": {"coordinates":[2.03248,6.46618],"type":"Point"}
}