{
  "type": "Feature",
  "properties": {
    "gn:admin1_code":"8.0",
    "gn:asciiname":"Bourouyore",
    "gn:country_code":"BJ",
    "gn:dem":236,
    "gn:feature_class":"P",
    "gn:feature_code":"PPL",
    "gn:name":"Bourouyor\u00e9",
    "gn:population":0,
    "gn:timezone":"Africa/Porto-Novo",
    "iso:country":"BJ",
    "wof:name":"Bourouyore",
    "wof:placetype":"locality"
},
  "geometry": {"coordinates":[1.02719,10.81808],"type":"Point"}
}