{
  "type": "Feature",
  "properties": {
    "gn:admin1_code":"10.0",
    "gn:asciiname":"Guero",
    "gn:country_code":"BJ",
    "gn:dem":404,
    "gn:feature_class":"P",
    "gn:feature_code":"PPL",
    "gn:name":"Gu\u00e9ro",
    "gn:population":0,
    "gn:timezone":"Africa/Porto-Novo",
    "iso:country":"BJ",
    "name:dan_x_preferred":[
        "Guero"
    ],
    "name:fra_x_preferred":[
        "Guero"
    ],
    "name:glg_x_preferred":[
        "Guero"
    ],
    "name:heb_x_preferred":[
        "Guero"
    ],
    "name:hrv_x_preferred":[
        "Guero"
    ],
    "name:hun_x_preferred":[
        "Guero"
    ],
    "name:ita_x_preferred":[
        "Guero"
    ],
    "name:por_x_preferred":[
        "Guero"
    ],
    "name:rus_x_preferred":[
        "Guero"
    ],
    "name:spa_x_preferred":[
        "Guero"
    ],
    "name:swe_x_preferred":[
        "Guero"
    ],
    "wof:name":"Guero",
    "wof:placetype":"locality"
},
  "geometry": {"coordinates":[2.97406,9.72807],"type":"Point"}
}