{
  "type": "Feature",
  "properties": {
    "gn:admin1_code":"13.0",
    "gn:asciiname":"Saovsar",
    "gn:country_code":"BJ",
    "gn:dem":451,
    "gn:feature_class":"P",
    "gn:feature_code":"PPL",
    "gn:name":"Saovsar",
    "gn:population":0,
    "gn:timezone":"Africa/Porto-Novo",
    "iso:country":"BJ",
    "name:und_x_variant":[
        "Tamsar",
        "Saovsar"
    ],
    "wof:name":"Saovsar",
    "wof:placetype":"locality"
},
  "geometry": {"coordinates":[1.53854,9.68954],"type":"Point"}
}