{
  "type": "Feature",
  "properties": {
    "gn:admin1_code":"18.0",
    "gn:asciiname":"Ketekpa",
    "gn:country_code":"BJ",
    "gn:dem":135,
    "gn:feature_class":"P",
    "gn:feature_code":"PPL",
    "gn:name":"K\u00e9t\u00e9kpa",
    "gn:population":0,
    "gn:timezone":"Africa/Porto-Novo",
    "iso:country":"BJ",
    "wof:name":"Ketekpa",
    "wof:placetype":"locality"
},
  "geometry": {"coordinates":[1.93075,7.18351],"type":"Point"}
}