{
  "type": "Feature",
  "properties": {
    "gn:admin1_code":"8.0",
    "gn:asciiname":"Gountia",
    "gn:country_code":"BJ",
    "gn:dem":353,
    "gn:feature_class":"P",
    "gn:feature_code":"PPL",
    "gn:name":"Gountia",
    "gn:population":0,
    "gn:timezone":"Africa/Porto-Novo",
    "iso:country":"BJ",
    "wof:name":"Gountia",
    "wof:placetype":"locality"
},
  "geometry": {"coordinates":[2.09721,10.20563],"type":"Point"}
}