{
  "type": "Feature",
  "properties": {
    "gn:admin1_code":"11.0",
    "gn:asciiname":"Iaiadji",
    "gn:country_code":"BJ",
    "gn:dem":145,
    "gn:feature_class":"P",
    "gn:feature_code":"PPL",
    "gn:name":"Iaiadji",
    "gn:population":0,
    "gn:timezone":"Africa/Porto-Novo",
    "iso:country":"BJ",
    "name:und_x_variant":[
        "Hebenogon",
        "Iaiadji"
    ],
    "wof:name":"Iaiadji",
    "wof:placetype":"locality"
},
  "geometry": {"coordinates":[1.929,7.63356],"type":"Point"}
}