{
  "type": "Feature",
  "properties": {
    "gn:admin1_code":"10.0",
    "gn:asciiname":"Boue Takarou",
    "gn:country_code":"BJ",
    "gn:dem":349,
    "gn:feature_class":"P",
    "gn:feature_code":"PPL",
    "gn:name":"Bou\u00e9 Takarou",
    "gn:population":0,
    "gn:timezone":"Africa/Porto-Novo",
    "iso:country":"BJ",
    "wof:name":"Boue Takarou",
    "wof:placetype":"locality"
},
  "geometry": {"coordinates":[2.53446,9.91517],"type":"Point"}
}