{
  "type": "Feature",
  "properties": {
    "gn:admin1_code":"10.0",
    "gn:asciiname":"Guini",
    "gn:country_code":"BJ",
    "gn:dem":338,
    "gn:feature_class":"P",
    "gn:feature_code":"PPL",
    "gn:name":"Guini",
    "gn:population":0,
    "gn:timezone":"Africa/Porto-Novo",
    "iso:country":"BJ",
    "name:und_x_variant":[
        "Igini",
        "Guiny",
        "Guini"
    ],
    "wof:name":"Guini",
    "wof:placetype":"locality"
},
  "geometry": {"coordinates":[2.57951,8.93555],"type":"Point"}
}