{
  "type": "Feature",
  "properties": {
    "gn:admin1_code":"8.0",
    "gn:asciiname":"Fokounfa",
    "gn:country_code":"BJ",
    "gn:dem":393,
    "gn:feature_class":"P",
    "gn:feature_code":"PPL",
    "gn:name":"Fokounfa",
    "gn:population":0,
    "gn:timezone":"Africa/Porto-Novo",
    "iso:country":"BJ",
    "wof:name":"Fokounfa",
    "wof:placetype":"locality"
},
  "geometry": {"coordinates":[1.30299,10.21406],"type":"Point"}
}