{
  "type": "Feature",
  "properties": {
    "gn:admin1_code":"10.0",
    "gn:asciiname":"Sondou",
    "gn:country_code":"BJ",
    "gn:dem":399,
    "gn:feature_class":"P",
    "gn:feature_code":"PPL",
    "gn:name":"Sondou",
    "gn:population":0,
    "gn:timezone":"Africa/Porto-Novo",
    "iso:country":"BJ",
    "wof:name":"Sondou",
    "wof:placetype":"locality"
},
  "geometry": {"coordinates":[2.97544,9.81896],"type":"Point"}
}