{
  "type": "Feature",
  "properties": {
    "gn:admin1_code":"8.0",
    "gn:asciiname":"Takonta",
    "gn:country_code":"BJ",
    "gn:dem":324,
    "gn:feature_class":"P",
    "gn:feature_code":"PPL",
    "gn:name":"Takonta",
    "gn:population":0,
    "gn:timezone":"Africa/Porto-Novo",
    "iso:country":"BJ",
    "name:und_x_variant":[
        "Takouenta",
        "Takonta"
    ],
    "wof:name":"Takonta",
    "wof:placetype":"locality"
},
  "geometry": {"coordinates":[1.38994,10.06294],"type":"Point"}
}