{
  "type": "Feature",
  "properties": {
    "gn:admin1_code":"17.0",
    "gn:asciiname":"Igolo",
    "gn:country_code":"BJ",
    "gn:dem":45,
    "gn:feature_class":"P",
    "gn:feature_code":"PPL",
    "gn:name":"Igolo",
    "gn:population":0,
    "gn:timezone":"Africa/Porto-Novo",
    "iso:country":"BJ",
    "wof:name":"Igolo",
    "wof:placetype":"locality"
},
  "geometry": {"coordinates":[2.73417,6.64873],"type":"Point"}
}