{
  "type": "Feature",
  "properties": {
    "gn:admin1_code":"18.0",
    "gn:asciiname":"Dovi-Dove",
    "gn:country_code":"BJ",
    "gn:dem":74,
    "gn:feature_class":"P",
    "gn:feature_code":"PPL",
    "gn:name":"Dovi-Dov\u00e8",
    "gn:population":0,
    "gn:timezone":"Africa/Porto-Novo",
    "iso:country":"BJ",
    "wof:name":"Dovi-Dove",
    "wof:placetype":"locality"
},
  "geometry": {"coordinates":[2.38108,7.17907],"type":"Point"}
}