{
  "type": "Feature",
  "properties": {
    "gn:admin1_code":"7.0",
    "gn:asciiname":"Zibo",
    "gn:country_code":"BJ",
    "gn:dem":320,
    "gn:feature_class":"P",
    "gn:feature_code":"PPL",
    "gn:name":"Zibo",
    "gn:population":0,
    "gn:timezone":"Africa/Porto-Novo",
    "iso:country":"BJ",
    "name:afr_x_preferred":[
        "Zibo"
    ],
    "name:ara_x_preferred":[
        "\u0632\u064a\u0628\u0648"
    ],
    "name:ast_x_preferred":[
        "Zibo"
    ],
    "name:bul_x_preferred":[
        "\u0414\u0437\u044a\u0431\u043e"
    ],
    "name:bxr_x_preferred":[
        "\u0426\u0437\u044b\u0431\u043e"
    ],
    "name:cat_x_preferred":[
        "Zibo"
    ],
    "name:cdo_x_preferred":[
        "C\u1e73\u0306-b\u00e1uk"
    ],
    "name:ceb_x_preferred":[
        "Zibo"
    ],
    "name:ces_x_preferred":[
        "C'-po"
    ],
    "name:dan_x_preferred":[
        "Zibo"
    ],
    "name:deu_x_preferred":[
        "Zibo"
    ],
    "name:eus_x_preferred":[
        "Zibo"
    ],
    "name:fas_x_preferred":[
        "\u0632\u0627\u06cc\u0628\u0648"
    ],
    "name:fin_x_preferred":[
        "Zibo"
    ],
    "name:fra_x_preferred":[
        "Zibo"
    ],
    "name:glg_x_preferred":[
        "Zibo"
    ],
    "name:heb_x_preferred":[
        "\u05d6\u05d9\u05d1\u05d5"
    ],
    "name:ind_x_preferred":[
        "Zibo"
    ],
    "name:ita_x_preferred":[
        "Zibo"
    ],
    "name:jpn_x_preferred":[
        "\u30b7\u535a\u5e02"
    ],
    "name:kik_x_preferred":[
        "Zibo"
    ],
    "name:kir_x_preferred":[
        "\u0426\u0437\u044b\u0431\u043e"
    ],
    "name:kor_x_preferred":[
        "\ucbd4\ubcf4\uc2dc"
    ],
    "name:mlg_x_preferred":[
        "Zibo"
    ],
    "name:nld_x_preferred":[
        "Zibo"
    ],
    "name:nno_x_preferred":[
        "Zibo"
    ],
    "name:nor_x_preferred":[
        "Zibo"
    ],
    "name:pan_x_preferred":[
        "\u0a1c\u0a3c\u0a40\u0a2c\u0a4b"
    ],
    "name:pol_x_preferred":[
        "Zibo"
    ],
    "name:por_x_preferred":[
        "Zibo"
    ],
    "name:rus_x_preferred":[
        "\u0426\u0437\u044b\u0431\u043e"
    ],
    "name:spa_x_preferred":[
        "Zibo"
    ],
    "name:swe_x_preferred":[
        "Zibo"
    ],
    "name:tgl_x_preferred":[
        "Zibo"
    ],
    "name:tur_x_preferred":[
        "Zibo"
    ],
    "name:uig_x_preferred":[
        "\u0632\u0649\u0628\u0648 \u0634\u06d5\u06be\u0649\u0631\u0649"
    ],
    "name:urd_x_preferred":[
        "\u0632\u06cc\u0628\u0648"
    ],
    "name:vie_x_preferred":[
        "Truy B\u00e1c"
    ],
    "name:war_x_preferred":[
        "Zibo"
    ],
    "name:wuu_x_preferred":[
        "\u6dc4\u535a\u5e02"
    ],
    "name:zho_x_preferred":[
        "\u6dc4\u535a\u5e02"
    ],
    "wof:name":"Zibo",
    "wof:placetype":"locality"
},
  "geometry": {"coordinates":[3.64759,10.767],"type":"Point"}
}