{
  "type": "Feature",
  "properties": {
    "gn:admin1_code":"7.0",
    "gn:asciiname":"Zibo",
    "gn:country_code":"BJ",
    "gn:dem":320,
    "gn:feature_class":"P",
    "gn:feature_code":"PPL",
    "gn:name":"Zibo",
    "gn:population":0,
    "gn:timezone":"Africa/Porto-Novo",
    "iso:country":"BJ",
    "wof:name":"Zibo",
    "wof:placetype":"locality"
},
  "geometry": {"coordinates":[3.64759,10.767],"type":"Point"}
}