{
  "type": "Feature",
  "properties": {
    "gn:admin1_code":"7.0",
    "gn:asciiname":"Gomarou",
    "gn:country_code":"BJ",
    "gn:dem":314,
    "gn:feature_class":"P",
    "gn:feature_code":"PPL",
    "gn:name":"Gomarou",
    "gn:population":0,
    "gn:timezone":"Africa/Porto-Novo",
    "iso:country":"BJ",
    "wof:name":"Gomarou",
    "wof:placetype":"locality"
},
  "geometry": {"coordinates":[2.80641,11.04592],"type":"Point"}
}