{
  "type": "Feature",
  "properties": {
    "gn:admin1_code":"0.0",
    "gn:asciiname":"Samerinega",
    "gn:country_code":"BJ",
    "gn:dem":419,
    "gn:feature_class":"P",
    "gn:feature_code":"PPL",
    "gn:name":"Sam\u00e9rin\u00e9ga",
    "gn:population":0,
    "gn:timezone":"Africa/Porto-Novo",
    "iso:country":"BJ",
    "wof:name":"Samerinega",
    "wof:placetype":"locality"
},
  "geometry": {"coordinates":[3.14217,9.24674],"type":"Point"}
}