{
  "type": "Feature",
  "properties": {
    "gn:admin1_code":"8.0",
    "gn:asciiname":"Loaka",
    "gn:country_code":"BJ",
    "gn:dem":161,
    "gn:feature_class":"P",
    "gn:feature_code":"PPL",
    "gn:name":"Loaka",
    "gn:population":0,
    "gn:timezone":"Africa/Porto-Novo",
    "iso:country":"BJ",
    "wof:name":"Loaka",
    "wof:placetype":"locality"
},
  "geometry": {"coordinates":[0.92837,10.87569],"type":"Point"}
}