{
  "type": "Feature",
  "properties": {
    "gn:admin1_code":"13.0",
    "gn:asciiname":"Kawala",
    "gn:country_code":"BJ",
    "gn:dem":420,
    "gn:feature_class":"P",
    "gn:feature_code":"PPL",
    "gn:name":"Kawala",
    "gn:population":0,
    "gn:timezone":"Africa/Porto-Novo",
    "iso:country":"BJ",
    "wof:name":"Kawala",
    "wof:placetype":"locality"
},
  "geometry": {"coordinates":[1.52106,9.46132],"type":"Point"}
}