{
  "type": "Feature",
  "properties": {
    "gn:admin1_code":"7.0",
    "gn:asciiname":"Bakayere",
    "gn:country_code":"BJ",
    "gn:dem":282,
    "gn:feature_class":"P",
    "gn:feature_code":"PPL",
    "gn:name":"Bakay\u00e9r\u00e9",
    "gn:population":0,
    "gn:timezone":"Africa/Porto-Novo",
    "iso:country":"BJ",
    "wof:name":"Bakayere",
    "wof:placetype":"locality"
},
  "geometry": {"coordinates":[2.86636,11.06527],"type":"Point"}
}