{
  "type": "Feature",
  "properties": {
    "gn:admin1_code":"8.0",
    "gn:asciiname":"Tassita",
    "gn:country_code":"BJ",
    "gn:dem":338,
    "gn:feature_class":"P",
    "gn:feature_code":"PPL",
    "gn:name":"Tassita",
    "gn:population":0,
    "gn:timezone":"Africa/Porto-Novo",
    "iso:country":"BJ",
    "wof:name":"Tassita",
    "wof:placetype":"locality"
},
  "geometry": {"coordinates":[1.42626,10.081],"type":"Point"}
}