{
  "type": "Feature",
  "properties": {
    "gn:admin1_code":"7.0",
    "gn:asciiname":"Saho",
    "gn:country_code":"BJ",
    "gn:dem":269,
    "gn:feature_class":"P",
    "gn:feature_code":"PPL",
    "gn:name":"Saho",
    "gn:population":0,
    "gn:timezone":"Africa/Porto-Novo",
    "iso:country":"BJ",
    "wof:name":"Saho",
    "wof:placetype":"locality"
},
  "geometry": {"coordinates":[2.31137,11.42354],"type":"Point"}
}