{
  "type": "Feature",
  "properties": {
    "gn:admin1_code":"10.0",
    "gn:asciiname":"Darno",
    "gn:country_code":"BJ",
    "gn:dem":305,
    "gn:feature_class":"P",
    "gn:feature_code":"PPL",
    "gn:name":"Darno",
    "gn:population":0,
    "gn:timezone":"Africa/Porto-Novo",
    "iso:country":"BJ",
    "wof:name":"Darno",
    "wof:placetype":"locality"
},
  "geometry": {"coordinates":[2.46325,9.65752],"type":"Point"}
}