{
  "type": "Feature",
  "properties": {
    "gn:admin1_code":"10.0",
    "gn:asciiname":"Sinaou",
    "gn:country_code":"BJ",
    "gn:dem":266,
    "gn:feature_class":"P",
    "gn:feature_code":"PPL",
    "gn:name":"Sinaou",
    "gn:population":0,
    "gn:timezone":"Africa/Porto-Novo",
    "iso:country":"BJ",
    "wof:name":"Sinaou",
    "wof:placetype":"locality"
},
  "geometry": {"coordinates":[2.24691,9.16983],"type":"Point"}
}