{
  "type": "Feature",
  "properties": {
    "gn:admin1_code":"7.0",
    "gn:asciiname":"Batia",
    "gn:country_code":"BJ",
    "gn:dem":295,
    "gn:feature_class":"P",
    "gn:feature_code":"PPL",
    "gn:name":"Batia",
    "gn:population":0,
    "gn:timezone":"Africa/Porto-Novo",
    "iso:country":"BJ",
    "name:ceb_x_preferred":[
        "Batia"
    ],
    "name:fra_x_preferred":[
        "Batia"
    ],
    "name:swe_x_preferred":[
        "Batia"
    ],
    "name:war_x_preferred":[
        "Batia"
    ],
    "wof:name":"Batia",
    "wof:placetype":"locality"
},
  "geometry": {"coordinates":[2.99845,11.18927],"type":"Point"}
}