{
  "type": "Feature",
  "properties": {
    "gn:admin1_code":"7.0",
    "gn:asciiname":"Velela",
    "gn:country_code":"BJ",
    "gn:dem":296,
    "gn:feature_class":"P",
    "gn:feature_code":"PPL",
    "gn:name":"V\u00e9l\u00e9la",
    "gn:population":0,
    "gn:timezone":"Africa/Porto-Novo",
    "iso:country":"BJ",
    "name:und_x_variant":[
        "V\u00e9la",
        "V\u00e9l\u00e9la"
    ],
    "wof:name":"Velela",
    "wof:placetype":"locality"
},
  "geometry": {"coordinates":[3.70572,10.89073],"type":"Point"}
}