{
  "type": "Feature",
  "properties": {
    "gn:admin1_code":"11.0",
    "gn:asciiname":"Moteo",
    "gn:country_code":"BJ",
    "gn:dem":260,
    "gn:feature_class":"P",
    "gn:feature_code":"PPL",
    "gn:name":"Mot\u00e9o",
    "gn:population":0,
    "gn:timezone":"Africa/Porto-Novo",
    "iso:country":"BJ",
    "name:und_x_variant":[
        "Mateo",
        "Mot\u00e9o"
    ],
    "wof:name":"Moteo",
    "wof:placetype":"locality"
},
  "geometry": {"coordinates":[2.60371,8.20502],"type":"Point"}
}