{
  "type": "Feature",
  "properties": {
    "gn:admin1_code":"18.0",
    "gn:asciiname":"Houndo",
    "gn:country_code":"BJ",
    "gn:dem":164,
    "gn:feature_class":"P",
    "gn:feature_code":"PPL",
    "gn:name":"Houndo",
    "gn:population":0,
    "gn:timezone":"Africa/Porto-Novo",
    "iso:country":"BJ",
    "wof:name":"Houndo",
    "wof:placetype":"locality"
},
  "geometry": {"coordinates":[1.98649,7.10151],"type":"Point"}
}