{
  "type": "Feature",
  "properties": {
    "gn:admin1_code":"7.0",
    "gn:admin2_code":"10344468.0",
    "gn:admin3_code":"11789885.0",
    "gn:asciiname":"Segbana",
    "gn:country_code":"BJ",
    "gn:dem":272,
    "gn:feature_class":"P",
    "gn:feature_code":"PPL",
    "gn:name":"S\u00e9gbana",
    "gn:population":0,
    "gn:timezone":"Africa/Porto-Novo",
    "iso:country":"BJ",
    "name:azb_x_preferred":[
        "\u0633\u0642\u0628\u0627\u0646\u0627"
    ],
    "name:fas_x_preferred":[
        "\u0633\u06af\u0628\u0627\u0646\u0627"
    ],
    "name:fin_x_preferred":[
        "S\u00e9gbana"
    ],
    "name:fra_x_preferred":[
        "Segbana"
    ],
    "name:frr_x_preferred":[
        "S\u00e9gbana"
    ],
    "name:ita_x_preferred":[
        "S\u00e9gbana"
    ],
    "name:msa_x_preferred":[
        "S\u00e9gbana"
    ],
    "name:nld_x_preferred":[
        "Segbana"
    ],
    "name:pol_x_preferred":[
        "S\u00e9gbana"
    ],
    "name:por_x_preferred":[
        "Segbana"
    ],
    "name:ron_x_preferred":[
        "S\u00e9gbana"
    ],
    "name:spa_x_preferred":[
        "Segbana"
    ],
    "name:swe_x_preferred":[
        "S\u00e9gbana"
    ],
    "name:zho_x_preferred":[
        "\u585e\u5df4\u7d0d"
    ],
    "wof:name":"Segbana",
    "wof:placetype":"locality"
},
  "geometry": {"coordinates":[3.69429,10.92821],"type":"Point"}
}