{
  "type": "Feature",
  "properties": {
    "gn:admin1_code":"8.0",
    "gn:asciiname":"Segbekerou",
    "gn:country_code":"BJ",
    "gn:dem":405,
    "gn:feature_class":"P",
    "gn:feature_code":"PPL",
    "gn:name":"Segb\u00e9k\u00e9rou",
    "gn:population":0,
    "gn:timezone":"Africa/Porto-Novo",
    "iso:country":"BJ",
    "name:und_x_variant":[
        "Simb\u00e9k\u00e9rou",
        "Segb\u00e9k\u00e9rou"
    ],
    "wof:name":"Segbekerou",
    "wof:placetype":"locality"
},
  "geometry": {"coordinates":[1.71153,10.21437],"type":"Point"}
}