{
  "type": "Feature",
  "properties": {
    "gn:admin1_code":"8.0",
    "gn:asciiname":"Manafaga",
    "gn:country_code":"BJ",
    "gn:dem":575,
    "gn:feature_class":"P",
    "gn:feature_code":"PPL",
    "gn:name":"Manafaga",
    "gn:population":0,
    "gn:timezone":"Africa/Porto-Novo",
    "iso:country":"BJ",
    "wof:name":"Manafaga",
    "wof:placetype":"locality"
},
  "geometry": {"coordinates":[1.51667,10.36667],"type":"Point"}
}