{
  "type": "Feature",
  "properties": {
    "gn:admin1_code":"10.0",
    "gn:asciiname":"Sonhore",
    "gn:country_code":"BJ",
    "gn:dem":344,
    "gn:feature_class":"P",
    "gn:feature_code":"PPL",
    "gn:name":"Sonhor\u00e9",
    "gn:population":0,
    "gn:timezone":"Africa/Porto-Novo",
    "iso:country":"BJ",
    "wof:name":"Sonhore",
    "wof:placetype":"locality"
},
  "geometry": {"coordinates":[2.84032,9.55133],"type":"Point"}
}