{
  "type": "Feature",
  "properties": {
    "gn:admin1_code":"13.0",
    "gn:asciiname":"Mofir",
    "gn:country_code":"BJ",
    "gn:dem":400,
    "gn:feature_class":"P",
    "gn:feature_code":"PPL",
    "gn:name":"Mofir",
    "gn:population":0,
    "gn:timezone":"Africa/Porto-Novo",
    "iso:country":"BJ",
    "wof:name":"Mofir",
    "wof:placetype":"locality"
},
  "geometry": {"coordinates":[1.61755,9.9629],"type":"Point"}
}