{
  "type": "Feature",
  "properties": {
    "gn:admin1_code":"8.0",
    "gn:asciiname":"Niakohoum",
    "gn:country_code":"BJ",
    "gn:dem":145,
    "gn:feature_class":"P",
    "gn:feature_code":"PPL",
    "gn:name":"Niakohoum",
    "gn:population":0,
    "gn:timezone":"Africa/Porto-Novo",
    "iso:country":"BJ",
    "wof:name":"Niakohoum",
    "wof:placetype":"locality"
},
  "geometry": {"coordinates":[0.86837,10.79021],"type":"Point"}
}