{
  "type": "Feature",
  "properties": {
    "gn:admin1_code":"8.0",
    "gn:asciiname":"Narfoungue",
    "gn:country_code":"BJ",
    "gn:dem":435,
    "gn:feature_class":"P",
    "gn:feature_code":"PPL",
    "gn:name":"Narfoungu\u00e9",
    "gn:population":0,
    "gn:timezone":"Africa/Porto-Novo",
    "iso:country":"BJ",
    "wof:name":"Narfoungue",
    "wof:placetype":"locality"
},
  "geometry": {"coordinates":[1.66979,10.00528],"type":"Point"}
}