{
  "type": "Feature",
  "properties": {
    "gn:admin1_code":"7.0",
    "gn:asciiname":"Tobe",
    "gn:country_code":"BJ",
    "gn:dem":279,
    "gn:feature_class":"P",
    "gn:feature_code":"PPL",
    "gn:name":"Tob\u00e9",
    "gn:population":0,
    "gn:timezone":"Africa/Porto-Novo",
    "iso:country":"BJ",
    "name:ceb_x_preferred":[
        "Tobe"
    ],
    "name:deu_x_preferred":[
        "Tobe"
    ],
    "name:swe_x_preferred":[
        "Tobe"
    ],
    "wof:name":"Tobe",
    "wof:placetype":"locality"
},
  "geometry": {"coordinates":[2.29883,11.38039],"type":"Point"}
}