{
  "type": "Feature",
  "properties": {
    "gn:admin1_code":"7.0",
    "gn:asciiname":"Gandokpe",
    "gn:country_code":"BJ",
    "gn:dem":272,
    "gn:feature_class":"P",
    "gn:feature_code":"PPL",
    "gn:name":"Gandokp\u00e9",
    "gn:population":0,
    "gn:timezone":"Africa/Porto-Novo",
    "iso:country":"BJ",
    "wof:name":"Gandokpe",
    "wof:placetype":"locality"
},
  "geometry": {"coordinates":[2.92121,11.15687],"type":"Point"}
}