{
  "type": "Feature",
  "properties": {
    "gn:admin1_code":"10.0",
    "gn:asciiname":"Ganou",
    "gn:country_code":"BJ",
    "gn:dem":389,
    "gn:feature_class":"P",
    "gn:feature_code":"PPL",
    "gn:name":"Ganou",
    "gn:population":0,
    "gn:timezone":"Africa/Porto-Novo",
    "iso:country":"BJ",
    "wof:name":"Ganou",
    "wof:placetype":"locality"
},
  "geometry": {"coordinates":[2.62205,9.38908],"type":"Point"}
}