{
  "type": "Feature",
  "properties": {
    "gn:admin1_code":"18.0",
    "gn:asciiname":"Linsa",
    "gn:cc2":"BJ",
    "gn:country_code":"BJ",
    "gn:dem":161,
    "gn:feature_class":"P",
    "gn:feature_code":"PPL",
    "gn:name":"Linsa",
    "gn:population":0,
    "gn:timezone":"Africa/Porto-Novo",
    "iso:country":"BJ",
    "name:und_x_variant":[
        "Kl\u00e9bogan",
        "Linsa"
    ],
    "wof:name":"Linsa",
    "wof:placetype":"locality"
},
  "geometry": {"coordinates":[1.88333,7.36667],"type":"Point"}
}