{
  "type": "Feature",
  "properties": {
    "gn:admin1_code":"11.0",
    "gn:admin2_code":"8260649.0",
    "gn:admin3_code":"11790032.0",
    "gn:asciiname":"Kilibo",
    "gn:country_code":"BJ",
    "gn:dem":301,
    "gn:feature_class":"P",
    "gn:feature_code":"PPL",
    "gn:name":"Kilibo",
    "gn:population":0,
    "gn:timezone":"Africa/Porto-Novo",
    "iso:country":"BJ",
    "wof:name":"Kilibo",
    "wof:placetype":"locality"
},
  "geometry": {"coordinates":[2.5999,8.57615],"type":"Point"}
}