{
  "type": "Feature",
  "properties": {
    "gn:admin1_code":"7.0",
    "gn:asciiname":"Pako",
    "gn:country_code":"BJ",
    "gn:dem":260,
    "gn:feature_class":"P",
    "gn:feature_code":"PPL",
    "gn:name":"Pako",
    "gn:population":0,
    "gn:timezone":"Africa/Porto-Novo",
    "iso:country":"BJ",
    "wof:name":"Pako",
    "wof:placetype":"locality"
},
  "geometry": {"coordinates":[2.53767,11.56226],"type":"Point"}
}