{
  "type": "Feature",
  "properties": {
    "gn:admin1_code":"7.0",
    "gn:asciiname":"Pako",
    "gn:country_code":"BJ",
    "gn:dem":260,
    "gn:feature_class":"P",
    "gn:feature_code":"PPL",
    "gn:name":"Pako",
    "gn:population":0,
    "gn:timezone":"Africa/Porto-Novo",
    "iso:country":"BJ",
    "name:bos_x_preferred":[
        "Pako"
    ],
    "name:ceb_x_preferred":[
        "Pako"
    ],
    "name:epo_x_preferred":[
        "Pako"
    ],
    "name:nld_x_preferred":[
        "Pako"
    ],
    "name:pol_x_preferred":[
        "Pako"
    ],
    "name:ron_x_preferred":[
        "Pako"
    ],
    "name:slv_x_preferred":[
        "Pako"
    ],
    "name:ukr_x_preferred":[
        "\u041f\u0430\u043a\u043e"
    ],
    "wof:name":"Pako",
    "wof:placetype":"locality"
},
  "geometry": {"coordinates":[2.53767,11.56226],"type":"Point"}
}