{
  "type": "Feature",
  "properties": {
    "gn:admin1_code":"18.0",
    "gn:asciiname":"Adjadjagon",
    "gn:country_code":"BJ",
    "gn:dem":127,
    "gn:feature_class":"P",
    "gn:feature_code":"PPL",
    "gn:name":"Adjadjagon",
    "gn:population":0,
    "gn:timezone":"Africa/Porto-Novo",
    "iso:country":"BJ",
    "wof:name":"Adjadjagon",
    "wof:placetype":"locality"
},
  "geometry": {"coordinates":[1.98333,7.46667],"type":"Point"}
}