{
  "type": "Feature",
  "properties": {
    "gn:admin1_code":"8.0",
    "gn:asciiname":"Bababa",
    "gn:country_code":"BJ",
    "gn:dem":332,
    "gn:feature_class":"P",
    "gn:feature_code":"PPL",
    "gn:name":"Bababa",
    "gn:population":0,
    "gn:timezone":"Africa/Porto-Novo",
    "iso:country":"BJ",
    "wof:name":"Bababa",
    "wof:placetype":"locality"
},
  "geometry": {"coordinates":[2.07858,10.58215],"type":"Point"}
}