{
  "type": "Feature",
  "properties": {
    "gn:admin1_code":"15.0",
    "gn:asciiname":"Tokpa",
    "gn:country_code":"BJ",
    "gn:dem":16,
    "gn:feature_class":"P",
    "gn:feature_code":"PPL",
    "gn:name":"Tokpa",
    "gn:population":0,
    "gn:timezone":"Africa/Porto-Novo",
    "iso:country":"BJ",
    "name:und_x_variant":[
        "Tokpo",
        "Tokpa"
    ],
    "wof:name":"Tokpa",
    "wof:placetype":"locality"
},
  "geometry": {"coordinates":[1.82423,6.65583],"type":"Point"}
}