{
  "type": "Feature",
  "properties": {
    "gn:admin1_code":"8.0",
    "gn:asciiname":"Tiori",
    "gn:country_code":"BJ",
    "gn:dem":540,
    "gn:feature_class":"P",
    "gn:feature_code":"PPL",
    "gn:name":"Tiori",
    "gn:population":0,
    "gn:timezone":"Africa/Porto-Novo",
    "iso:country":"BJ",
    "wof:name":"Tiori",
    "wof:placetype":"locality"
},
  "geometry": {"coordinates":[1.45,10.35],"type":"Point"}
}