{
  "type": "Feature",
  "properties": {
    "gn:admin1_code":"10.0",
    "gn:asciiname":"Do",
    "gn:country_code":"BJ",
    "gn:dem":296,
    "gn:feature_class":"P",
    "gn:feature_code":"PPL",
    "gn:name":"Do",
    "gn:population":0,
    "gn:timezone":"Africa/Porto-Novo",
    "iso:country":"BJ",
    "name:ara_x_preferred":[
        "\u062f\u0648"
    ],
    "name:fas_x_preferred":[
        "\u062f\u0648"
    ],
    "name:rus_x_preferred":[
        "\u0414\u043e"
    ],
    "name:swe_x_preferred":[
        "Do"
    ],
    "wof:name":"Do",
    "wof:placetype":"locality"
},
  "geometry": {"coordinates":[2.39354,9.34968],"type":"Point"}
}