{
  "type": "Feature",
  "properties": {
    "gn:admin1_code":"11.0",
    "gn:asciiname":"Tchokoladjou",
    "gn:country_code":"BJ",
    "gn:dem":196,
    "gn:feature_class":"P",
    "gn:feature_code":"PPL",
    "gn:name":"Tchokoladjou",
    "gn:population":0,
    "gn:timezone":"Africa/Porto-Novo",
    "iso:country":"BJ",
    "wof:name":"Tchokoladjou",
    "wof:placetype":"locality"
},
  "geometry": {"coordinates":[1.72731,7.86456],"type":"Point"}
}