{
  "type": "Feature",
  "properties": {
    "gn:admin1_code":"8.0",
    "gn:asciiname":"Gbirikorou",
    "gn:country_code":"BJ",
    "gn:dem":422,
    "gn:feature_class":"P",
    "gn:feature_code":"PPL",
    "gn:name":"Gbirikorou",
    "gn:population":0,
    "gn:timezone":"Africa/Porto-Novo",
    "iso:country":"BJ",
    "wof:name":"Gbirikorou",
    "wof:placetype":"locality"
},
  "geometry": {"coordinates":[1.70693,10.35558],"type":"Point"}
}