{
  "type": "Feature",
  "properties": {
    "gn:admin1_code":"8.0",
    "gn:asciiname":"Bogolori-Kapahoun",
    "gn:country_code":"BJ",
    "gn:dem":171,
    "gn:feature_class":"P",
    "gn:feature_code":"PPL",
    "gn:name":"Bogolori-Kapahoun",
    "gn:population":0,
    "gn:timezone":"Africa/Porto-Novo",
    "iso:country":"BJ",
    "wof:name":"Bogolori-Kapahoun",
    "wof:placetype":"locality"
},
  "geometry": {"coordinates":[0.96479,10.84913],"type":"Point"}
}