{
  "type": "Feature",
  "properties": {
    "gn:admin1_code":"8.0",
    "gn:asciiname":"Loouga",
    "gn:country_code":"BJ",
    "gn:dem":150,
    "gn:feature_class":"P",
    "gn:feature_code":"PPL",
    "gn:name":"Loouga",
    "gn:population":0,
    "gn:timezone":"Africa/Porto-Novo",
    "iso:country":"BJ",
    "wof:name":"Loouga",
    "wof:placetype":"locality"
},
  "geometry": {"coordinates":[0.8936,10.80309],"type":"Point"}
}