{
  "type": "Feature",
  "properties": {
    "gn:admin1_code":"18.0",
    "gn:asciiname":"Davougon",
    "gn:country_code":"BJ",
    "gn:dem":152,
    "gn:feature_class":"P",
    "gn:feature_code":"PPL",
    "gn:name":"Davougon",
    "gn:population":0,
    "gn:timezone":"Africa/Porto-Novo",
    "iso:country":"BJ",
    "wof:name":"Davougon",
    "wof:placetype":"locality"
},
  "geometry": {"coordinates":[1.93906,7.15842],"type":"Point"}
}