{
  "type": "Feature",
  "properties": {
    "gn:admin1_code":"8.0",
    "gn:asciiname":"Tiatingou",
    "gn:country_code":"BJ",
    "gn:dem":445,
    "gn:feature_class":"P",
    "gn:feature_code":"PPL",
    "gn:name":"Tiatingou",
    "gn:population":0,
    "gn:timezone":"Africa/Porto-Novo",
    "iso:country":"BJ",
    "wof:name":"Tiatingou",
    "wof:placetype":"locality"
},
  "geometry": {"coordinates":[1.47565,10.8158],"type":"Point"}
}