{
  "type": "Feature",
  "properties": {
    "gn:admin1_code":"11.0",
    "gn:asciiname":"Adjafa",
    "gn:country_code":"BJ",
    "gn:dem":144,
    "gn:feature_class":"P",
    "gn:feature_code":"PPL",
    "gn:name":"Adjafa",
    "gn:population":0,
    "gn:timezone":"Africa/Porto-Novo",
    "iso:country":"BJ",
    "wof:name":"Adjafa",
    "wof:placetype":"locality"
},
  "geometry": {"coordinates":[1.83694,7.81866],"type":"Point"}
}