{
  "type": "Feature",
  "properties": {
    "gn:admin1_code":"8.0",
    "gn:asciiname":"Kouaneyoko",
    "gn:country_code":"BJ",
    "gn:dem":576,
    "gn:feature_class":"P",
    "gn:feature_code":"PPL",
    "gn:name":"Kouan\u00e9yoko",
    "gn:population":0,
    "gn:timezone":"Africa/Porto-Novo",
    "iso:country":"BJ",
    "wof:name":"Kouaneyoko",
    "wof:placetype":"locality"
},
  "geometry": {"coordinates":[1.54721,10.40102],"type":"Point"}
}