{
  "type": "Feature",
  "properties": {
    "gn:admin1_code":"8.0",
    "gn:asciiname":"Yidi",
    "gn:country_code":"BJ",
    "gn:dem":230,
    "gn:feature_class":"P",
    "gn:feature_code":"PPL",
    "gn:name":"Yidi",
    "gn:population":0,
    "gn:timezone":"Africa/Porto-Novo",
    "iso:country":"BJ",
    "wof:name":"Yidi",
    "wof:placetype":"locality"
},
  "geometry": {"coordinates":[1.10194,10.51528],"type":"Point"}
}