{
  "type": "Feature",
  "properties": {
    "gn:admin1_code":"9.0",
    "gn:asciiname":"Tokoli",
    "gn:country_code":"BJ",
    "gn:dem":25,
    "gn:feature_class":"P",
    "gn:feature_code":"PPL",
    "gn:name":"Tokoli",
    "gn:population":0,
    "gn:timezone":"Africa/Porto-Novo",
    "iso:country":"BJ",
    "wof:name":"Tokoli",
    "wof:placetype":"locality"
},
  "geometry": {"coordinates":[2.1885,6.45764],"type":"Point"}
}