{
  "type": "Feature",
  "properties": {
    "gn:admin1_code":"10.0",
    "gn:asciiname":"Korintissou",
    "gn:country_code":"BJ",
    "gn:dem":334,
    "gn:feature_class":"P",
    "gn:feature_code":"PPL",
    "gn:name":"Korintissou",
    "gn:population":0,
    "gn:timezone":"Africa/Porto-Novo",
    "iso:country":"BJ",
    "wof:name":"Korintissou",
    "wof:placetype":"locality"
},
  "geometry": {"coordinates":[2.49495,9.94361],"type":"Point"}
}