{
  "type": "Feature",
  "properties": {
    "gn:admin1_code":"13.0",
    "gn:asciiname":"Wetenga",
    "gn:cc2":"BJ",
    "gn:country_code":"BJ",
    "gn:dem":443,
    "gn:feature_class":"P",
    "gn:feature_code":"PPL",
    "gn:name":"W\u00e9t\u00e8nga",
    "gn:population":0,
    "gn:timezone":"Africa/Porto-Novo",
    "iso:country":"BJ",
    "name:und_x_variant":[
        "Dempage Ti\u00e9n\u00e9",
        "W\u00e9t\u00e8nga"
    ],
    "wof:name":"Wetenga",
    "wof:placetype":"locality"
},
  "geometry": {"coordinates":[1.61667,9.76667],"type":"Point"}
}