{
  "type": "Feature",
  "properties": {
    "gn:admin1_code":"8.0",
    "gn:asciiname":"Mamazoura",
    "gn:country_code":"BJ",
    "gn:dem":430,
    "gn:feature_class":"P",
    "gn:feature_code":"PPL",
    "gn:name":"Mamazoura",
    "gn:population":0,
    "gn:timezone":"Africa/Porto-Novo",
    "iso:country":"BJ",
    "name:und_x_variant":[
        "Timolero",
        "Mamazoura"
    ],
    "wof:name":"Mamazoura",
    "wof:placetype":"locality"
},
  "geometry": {"coordinates":[1.66388,9.99262],"type":"Point"}
}