{
  "type": "Feature",
  "properties": {
    "gn:admin1_code":"13.0",
    "gn:asciiname":"Assoumanda",
    "gn:country_code":"BJ",
    "gn:dem":395,
    "gn:feature_class":"P",
    "gn:feature_code":"PPL",
    "gn:name":"Assoumanda",
    "gn:population":0,
    "gn:timezone":"Africa/Porto-Novo",
    "iso:country":"BJ",
    "wof:name":"Assoumanda",
    "wof:placetype":"locality"
},
  "geometry": {"coordinates":[1.46984,9.53229],"type":"Point"}
}