{
  "type": "Feature",
  "properties": {
    "gn:admin1_code":"10.0",
    "gn:admin2_code":"7669355.0",
    "gn:admin3_code":"11789998.0",
    "gn:asciiname":"Biro",
    "gn:country_code":"BJ",
    "gn:dem":419,
    "gn:feature_class":"P",
    "gn:feature_code":"PPL",
    "gn:name":"Biro",
    "gn:population":0,
    "gn:timezone":"Africa/Porto-Novo",
    "iso:country":"BJ",
    "name:und_x_variant":[
        "Birou",
        "Biro"
    ],
    "wof:name":"Biro",
    "wof:placetype":"locality"
},
  "geometry": {"coordinates":[2.94123,9.90759],"type":"Point"}
}