{
  "type": "Feature",
  "properties": {
    "gn:admin1_code":"8.0",
    "gn:asciiname":"Mahontinga",
    "gn:country_code":"BJ",
    "gn:dem":228,
    "gn:feature_class":"P",
    "gn:feature_code":"PPL",
    "gn:name":"Mahontinga",
    "gn:population":0,
    "gn:timezone":"Africa/Porto-Novo",
    "iso:country":"BJ",
    "wof:name":"Mahontinga",
    "wof:placetype":"locality"
},
  "geometry": {"coordinates":[1.06917,10.60741],"type":"Point"}
}