{
  "type": "Feature",
  "properties": {
    "gn:admin1_code":"16.0",
    "gn:asciiname":"Vante",
    "gn:cc2":"BJ",
    "gn:country_code":"BJ",
    "gn:dem":53,
    "gn:feature_class":"P",
    "gn:feature_code":"PPL",
    "gn:name":"Vant\u00e8",
    "gn:population":0,
    "gn:timezone":"Africa/Porto-Novo",
    "iso:country":"BJ",
    "name:und_x_variant":[
        "Vant\u00e9-Avamiti\u00e9",
        "Vant\u00e8"
    ],
    "wof:name":"Vante",
    "wof:placetype":"locality"
},
  "geometry": {"coordinates":[2.58333,6.61667],"type":"Point"}
}