{
  "type": "Feature",
  "properties": {
    "gn:admin1_code":"13.0",
    "gn:asciiname":"Tiatiala",
    "gn:country_code":"BJ",
    "gn:dem":416,
    "gn:feature_class":"P",
    "gn:feature_code":"PPL",
    "gn:name":"Tiatiala",
    "gn:population":0,
    "gn:timezone":"Africa/Porto-Novo",
    "iso:country":"BJ",
    "wof:name":"Tiatiala",
    "wof:placetype":"locality"
},
  "geometry": {"coordinates":[1.50375,9.39056],"type":"Point"}
}