{
  "type": "Feature",
  "properties": {
    "gn:admin1_code":"7.0",
    "gn:asciiname":"Badou",
    "gn:country_code":"BJ",
    "gn:dem":298,
    "gn:feature_class":"P",
    "gn:feature_code":"PPL",
    "gn:name":"Badou",
    "gn:population":0,
    "gn:timezone":"Africa/Porto-Novo",
    "iso:country":"BJ",
    "name:und_x_variant":[
        "Badu",
        "Badou"
    ],
    "wof:name":"Badou",
    "wof:placetype":"locality"
},
  "geometry": {"coordinates":[2.72848,10.89881],"type":"Point"}
}