{
  "type": "Feature",
  "properties": {
    "gn:admin1_code":"11.0",
    "gn:asciiname":"Paouignan",
    "gn:country_code":"BJ",
    "gn:dem":188,
    "gn:feature_class":"P",
    "gn:feature_code":"PPL",
    "gn:name":"Paouignan",
    "gn:population":0,
    "gn:timezone":"Africa/Porto-Novo",
    "iso:country":"BJ",
    "name:und_x_variant":[
        "Pawignan",
        "Paougnan",
        "Paouignan"
    ],
    "wof:name":"Paouignan",
    "wof:placetype":"locality"
},
  "geometry": {"coordinates":[2.22698,7.67777],"type":"Point"}
}