{
  "type": "Feature",
  "properties": {
    "gn:admin1_code":"8.0",
    "gn:asciiname":"Nielibounde",
    "gn:country_code":"BJ",
    "gn:dem":542,
    "gn:feature_class":"P",
    "gn:feature_code":"PPL",
    "gn:name":"Ni\u00e9libound\u00e9",
    "gn:population":0,
    "gn:timezone":"Africa/Porto-Novo",
    "iso:country":"BJ",
    "wof:name":"Nielibounde",
    "wof:placetype":"locality"
},
  "geometry": {"coordinates":[1.29245,10.54984],"type":"Point"}
}