{
  "type": "Feature",
  "properties": {
    "gn:admin1_code":"18.0",
    "gn:asciiname":"Djebatin",
    "gn:country_code":"BJ",
    "gn:dem":158,
    "gn:feature_class":"P",
    "gn:feature_code":"PPL",
    "gn:name":"Dj\u00e9batin",
    "gn:population":0,
    "gn:timezone":"Africa/Porto-Novo",
    "iso:country":"BJ",
    "name:und_x_variant":[
        "Dj\u00e9kbatin",
        "Dj\u00e9batin"
    ],
    "wof:name":"Djebatin",
    "wof:placetype":"locality"
},
  "geometry": {"coordinates":[1.90914,7.31522],"type":"Point"}
}