{
  "type": "Feature",
  "properties": {
    "gn:admin1_code":"8.0",
    "gn:asciiname":"Bansale",
    "gn:country_code":"BJ",
    "gn:dem":184,
    "gn:feature_class":"P",
    "gn:feature_code":"PPL",
    "gn:name":"Bansal\u00e9",
    "gn:population":0,
    "gn:timezone":"Africa/Porto-Novo",
    "iso:country":"BJ",
    "wof:name":"Bansale",
    "wof:placetype":"locality"
},
  "geometry": {"coordinates":[0.82038,10.45918],"type":"Point"}
}