{
  "type": "Feature",
  "properties": {
    "gn:admin1_code":"11.0",
    "gn:asciiname":"Vossa",
    "gn:country_code":"BJ",
    "gn:dem":154,
    "gn:feature_class":"P",
    "gn:feature_code":"PPL",
    "gn:name":"Vossa",
    "gn:population":0,
    "gn:timezone":"Africa/Porto-Novo",
    "iso:country":"BJ",
    "wof:name":"Vossa",
    "wof:placetype":"locality"
},
  "geometry": {"coordinates":[2.34617,8.50218],"type":"Point"}
}