{
  "type": "Feature",
  "properties": {
    "gn:admin1_code":"9.0",
    "gn:admin2_code":"7874152.0",
    "gn:admin3_code":"11789954.0",
    "gn:asciiname":"Glo-Djigbe",
    "gn:country_code":"BJ",
    "gn:dem":8,
    "gn:feature_class":"P",
    "gn:feature_code":"PPL",
    "gn:name":"Glo-Djigb\u00e9",
    "gn:population":0,
    "gn:timezone":"Africa/Porto-Novo",
    "iso:country":"BJ",
    "wof:name":"Glo-Djigbe",
    "wof:placetype":"locality"
},
  "geometry": {"coordinates":[2.3833,6.8333],"type":"Point"}
}