{
  "type": "Feature",
  "properties": {
    "gn:admin1_code":"11.0",
    "gn:asciiname":"Wedeme",
    "gn:country_code":"BJ",
    "gn:dem":200,
    "gn:feature_class":"P",
    "gn:feature_code":"PPL",
    "gn:name":"W\u00e9d\u00e9m\u00e9",
    "gn:population":0,
    "gn:timezone":"Africa/Porto-Novo",
    "iso:country":"BJ",
    "wof:name":"Wedeme",
    "wof:placetype":"locality"
},
  "geometry": {"coordinates":[2.1657,8.01517],"type":"Point"}
}