{
  "type": "Feature",
  "properties": {
    "gn:admin1_code":"11.0",
    "gn:asciiname":"Konene",
    "gn:country_code":"BJ",
    "gn:dem":281,
    "gn:feature_class":"P",
    "gn:feature_code":"PPL",
    "gn:name":"Kon\u00e9n\u00e9",
    "gn:population":0,
    "gn:timezone":"Africa/Porto-Novo",
    "iso:country":"BJ",
    "wof:name":"Konene",
    "wof:placetype":"locality"
},
  "geometry": {"coordinates":[1.77525,8.4571],"type":"Point"}
}