{
  "type": "Feature",
  "properties": {
    "gn:admin1_code":"12.0",
    "gn:admin2_code":"10344476.0",
    "gn:admin3_code":"11288100.0",
    "gn:asciiname":"Missinko",
    "gn:country_code":"BJ",
    "gn:dem":162,
    "gn:feature_class":"P",
    "gn:feature_code":"PPL",
    "gn:name":"Missinko",
    "gn:population":0,
    "gn:timezone":"Africa/Porto-Novo",
    "iso:country":"BJ",
    "name:ita_x_preferred":[
        "Missinko"
    ],
    "name:msa_x_preferred":[
        "Missinko"
    ],
    "wof:name":"Missinko",
    "wof:placetype":"locality"
},
  "geometry": {"coordinates":[1.817,6.884],"type":"Point"}
}