{
  "type": "Feature",
  "properties": {
    "gn:admin1_code":"8.0",
    "gn:asciiname":"Koutangou",
    "gn:country_code":"BJ",
    "gn:dem":198,
    "gn:feature_class":"P",
    "gn:feature_code":"PPL",
    "gn:name":"Koutangou",
    "gn:population":0,
    "gn:timezone":"Africa/Porto-Novo",
    "iso:country":"BJ",
    "wof:name":"Koutangou",
    "wof:placetype":"locality"
},
  "geometry": {"coordinates":[1.08878,10.24564],"type":"Point"}
}