{
  "type": "Feature",
  "properties": {
    "gn:admin1_code":"10.0",
    "gn:admin2_code":"7669270.0",
    "gn:admin3_code":"11790181.0",
    "gn:asciiname":"Gberouboue",
    "gn:country_code":"BJ",
    "gn:dem":328,
    "gn:feature_class":"P",
    "gn:feature_code":"PPL",
    "gn:name":"Gb\u00e9roubou\u00e8",
    "gn:population":0,
    "gn:timezone":"Africa/Porto-Novo",
    "iso:country":"BJ",
    "name:ceb_x_preferred":[
        "Gb\u00e9roubou\u00e8"
    ],
    "name:ita_x_preferred":[
        "B\u00e9roubouay"
    ],
    "name:msa_x_preferred":[
        "B\u00e9roubouay"
    ],
    "name:swe_x_preferred":[
        "Gb\u00e9roubou\u00e8"
    ],
    "name:und_x_variant":[
        "B\u00e9roubouay",
        "Berubuaye",
        "B\u00e9roubouaye",
        "Gb\u00e9roubou\u00e8"
    ],
    "wof:name":"Gberouboue",
    "wof:placetype":"locality"
},
  "geometry": {"coordinates":[2.72824,10.54158],"type":"Point"}
}