{
  "type": "Feature",
  "properties": {
    "gn:admin1_code":"10.0",
    "gn:asciiname":"Monon",
    "gn:country_code":"BJ",
    "gn:dem":291,
    "gn:feature_class":"P",
    "gn:feature_code":"PPL",
    "gn:name":"Monon",
    "gn:population":0,
    "gn:timezone":"Africa/Porto-Novo",
    "iso:country":"BJ",
    "wof:name":"Monon",
    "wof:placetype":"locality"
},
  "geometry": {"coordinates":[2.41446,9.4556],"type":"Point"}
}