{
  "type": "Feature",
  "properties": {
    "gn:admin1_code":"18.0",
    "gn:asciiname":"Haoula",
    "gn:country_code":"BJ",
    "gn:dem":171,
    "gn:feature_class":"P",
    "gn:feature_code":"PPL",
    "gn:name":"Haoula",
    "gn:population":0,
    "gn:timezone":"Africa/Porto-Novo",
    "iso:country":"BJ",
    "wof:name":"Haoula",
    "wof:placetype":"locality"
},
  "geometry": {"coordinates":[1.99436,7.11786],"type":"Point"}
}