{
  "type": "Feature",
  "properties": {
    "gn:admin1_code":"10.0",
    "gn:asciiname":"Beroubassi",
    "gn:country_code":"BJ",
    "gn:dem":349,
    "gn:feature_class":"P",
    "gn:feature_code":"PPL",
    "gn:name":"B\u00e9roubassi",
    "gn:population":0,
    "gn:timezone":"Africa/Porto-Novo",
    "iso:country":"BJ",
    "wof:name":"Beroubassi",
    "wof:placetype":"locality"
},
  "geometry": {"coordinates":[3.15574,10.27627],"type":"Point"}
}