{
  "type": "Feature",
  "properties": {
    "gn:admin1_code":"16.0",
    "gn:asciiname":"Houinvigue",
    "gn:country_code":"BJ",
    "gn:dem":74,
    "gn:feature_class":"P",
    "gn:feature_code":"PPLA3",
    "gn:name":"Houinvigue",
    "gn:population":0,
    "gn:timezone":"Africa/Porto-Novo",
    "iso:country":"BJ",
    "wof:name":"Houinvigue",
    "wof:placetype":"locality"
},
  "geometry": {"coordinates":[2.4806,6.8862],"type":"Point"}
}