{
  "type": "Feature",
  "properties": {
    "gn:admin1_code":"8.0",
    "gn:asciiname":"Santiahon",
    "gn:country_code":"BJ",
    "gn:dem":203,
    "gn:feature_class":"P",
    "gn:feature_code":"PPL",
    "gn:name":"Santiahon",
    "gn:population":0,
    "gn:timezone":"Africa/Porto-Novo",
    "iso:country":"BJ",
    "wof:name":"Santiahon",
    "wof:placetype":"locality"
},
  "geometry": {"coordinates":[1.08957,10.75163],"type":"Point"}
}