{
  "type": "Feature",
  "properties": {
    "gn:admin1_code":"8.0",
    "gn:asciiname":"Naataya",
    "gn:country_code":"BJ",
    "gn:dem":582,
    "gn:feature_class":"P",
    "gn:feature_code":"PPL",
    "gn:name":"Naataya",
    "gn:population":0,
    "gn:timezone":"Africa/Porto-Novo",
    "iso:country":"BJ",
    "wof:name":"Naataya",
    "wof:placetype":"locality"
},
  "geometry": {"coordinates":[1.41432,10.41119],"type":"Point"}
}