{
  "type": "Feature",
  "properties": {
    "gn:admin1_code":"8.0",
    "gn:asciiname":"Sandala",
    "gn:country_code":"BJ",
    "gn:dem":182,
    "gn:feature_class":"P",
    "gn:feature_code":"PPL",
    "gn:name":"Sandala",
    "gn:population":0,
    "gn:timezone":"Africa/Porto-Novo",
    "iso:country":"BJ",
    "name:ceb_x_preferred":[
        "Sandala"
    ],
    "name:swe_x_preferred":[
        "Sandala"
    ],
    "wof:name":"Sandala",
    "wof:placetype":"locality"
},
  "geometry": {"coordinates":[0.9531,10.58656],"type":"Point"}
}