{
  "type": "Feature",
  "properties": {
    "gn:admin1_code":"12.0",
    "gn:asciiname":"Chatehoue",
    "gn:country_code":"BJ",
    "gn:dem":168,
    "gn:feature_class":"P",
    "gn:feature_code":"PPL",
    "gn:name":"Chat\u00e9hou\u00e9",
    "gn:population":0,
    "gn:timezone":"Africa/Porto-Novo",
    "iso:country":"BJ",
    "wof:name":"Chatehoue",
    "wof:placetype":"locality"
},
  "geometry": {"coordinates":[1.83333,6.96667],"type":"Point"}
}