{
  "type": "Feature",
  "properties": {
    "gn:admin1_code":"7.0",
    "gn:asciiname":"Dogbouan",
    "gn:country_code":"BJ",
    "gn:dem":242,
    "gn:feature_class":"P",
    "gn:feature_code":"PPL",
    "gn:name":"Dogbouan",
    "gn:population":0,
    "gn:timezone":"Africa/Porto-Novo",
    "iso:country":"BJ",
    "wof:name":"Dogbouan",
    "wof:placetype":"locality"
},
  "geometry": {"coordinates":[2.97329,11.30719],"type":"Point"}
}