{
  "type": "Feature",
  "properties": {
    "gn:admin1_code":"9.0",
    "gn:asciiname":"Ouaouata",
    "gn:country_code":"BJ",
    "gn:dem":68,
    "gn:feature_class":"P",
    "gn:feature_code":"PPL",
    "gn:name":"Ouaouata",
    "gn:population":0,
    "gn:timezone":"Africa/Porto-Novo",
    "iso:country":"BJ",
    "wof:name":"Ouaouata",
    "wof:placetype":"locality"
},
  "geometry": {"coordinates":[2.29293,6.63739],"type":"Point"}
}