{
  "type": "Feature",
  "properties": {
    "gn:admin1_code":"8.0",
    "gn:asciiname":"Porga",
    "gn:country_code":"BJ",
    "gn:dem":150,
    "gn:feature_class":"P",
    "gn:feature_code":"PPL",
    "gn:name":"Porga",
    "gn:population":0,
    "gn:timezone":"Africa/Porto-Novo",
    "iso:country":"BJ",
    "name:chv_x_preferred":[
        "\u041f\u043e\u0440\u0433\u0430"
    ],
    "name:ron_x_preferred":[
        "Porga"
    ],
    "wof:name":"Porga",
    "wof:placetype":"locality"
},
  "geometry": {"coordinates":[0.96891,11.04801],"type":"Point"}
}