{
  "type": "Feature",
  "properties": {
    "gn:admin1_code":"8.0",
    "gn:asciiname":"Bouloumizake",
    "gn:country_code":"BJ",
    "gn:dem":206,
    "gn:feature_class":"P",
    "gn:feature_code":"PPL",
    "gn:name":"Bouloumizak\u00e9",
    "gn:population":0,
    "gn:timezone":"Africa/Porto-Novo",
    "iso:country":"BJ",
    "wof:name":"Bouloumizake",
    "wof:placetype":"locality"
},
  "geometry": {"coordinates":[1.16273,10.65569],"type":"Point"}
}