{
  "type": "Feature",
  "properties": {
    "gn:admin1_code":"10.0",
    "gn:asciiname":"Adohoukparou",
    "gn:country_code":"BJ",
    "gn:dem":328,
    "gn:feature_class":"P",
    "gn:feature_code":"PPL",
    "gn:name":"Adohoukparou",
    "gn:population":0,
    "gn:timezone":"Africa/Porto-Novo",
    "iso:country":"BJ",
    "wof:name":"Adohoukparou",
    "wof:placetype":"locality"
},
  "geometry": {"coordinates":[2.4916,9.03445],"type":"Point"}
}