{
  "type": "Feature",
  "properties": {
    "gn:admin1_code":"7.0",
    "gn:asciiname":"Yagouennda",
    "gn:country_code":"BJ",
    "gn:dem":312,
    "gn:feature_class":"P",
    "gn:feature_code":"PPL",
    "gn:name":"Yagouennda",
    "gn:population":0,
    "gn:timezone":"Africa/Porto-Novo",
    "iso:country":"BJ",
    "wof:name":"Yagouennda",
    "wof:placetype":"locality"
},
  "geometry": {"coordinates":[2.49728,11.39287],"type":"Point"}
}