{
  "type": "Feature",
  "properties": {
    "gn:admin1_code":"8.0",
    "gn:asciiname":"Kataban",
    "gn:country_code":"BJ",
    "gn:dem":418,
    "gn:feature_class":"P",
    "gn:feature_code":"PPL",
    "gn:name":"Kataban",
    "gn:population":0,
    "gn:timezone":"Africa/Porto-Novo",
    "iso:country":"BJ",
    "wof:name":"Kataban",
    "wof:placetype":"locality"
},
  "geometry": {"coordinates":[1.70227,10.30273],"type":"Point"}
}