{
  "type": "Feature",
  "properties": {
    "gn:admin1_code":"15.0",
    "gn:admin2_code":"7668926.0",
    "gn:asciiname":"Kpinnou",
    "gn:country_code":"BJ",
    "gn:dem":17,
    "gn:feature_class":"P",
    "gn:feature_code":"PPL",
    "gn:name":"Kpinnou",
    "gn:population":0,
    "gn:timezone":"Africa/Porto-Novo",
    "iso:country":"BJ",
    "name:ita_x_preferred":[
        "Kpinnou"
    ],
    "name:msa_x_preferred":[
        "Kpinnou"
    ],
    "wof:name":"Kpinnou",
    "wof:placetype":"locality"
},
  "geometry": {"coordinates":[1.77295,6.5823],"type":"Point"}
}