{
  "type": "Feature",
  "properties": {
    "gn:admin1_code":"8.0",
    "gn:asciiname":"Sireboine",
    "gn:country_code":"BJ",
    "gn:dem":157,
    "gn:feature_class":"P",
    "gn:feature_code":"PPL",
    "gn:name":"Sir\u00e9boin\u00e9",
    "gn:population":0,
    "gn:timezone":"Africa/Porto-Novo",
    "iso:country":"BJ",
    "wof:name":"Sireboine",
    "wof:placetype":"locality"
},
  "geometry": {"coordinates":[0.91066,10.87986],"type":"Point"}
}