{
  "type": "Feature",
  "properties": {
    "gn:admin1_code":"13.0",
    "gn:asciiname":"Narlirha",
    "gn:country_code":"BJ",
    "gn:dem":465,
    "gn:feature_class":"P",
    "gn:feature_code":"PPL",
    "gn:name":"Narlirha",
    "gn:population":0,
    "gn:timezone":"Africa/Porto-Novo",
    "iso:country":"BJ",
    "wof:name":"Narlirha",
    "wof:placetype":"locality"
},
  "geometry": {"coordinates":[1.5595,9.8777],"type":"Point"}
}