{
  "type": "Feature",
  "properties": {
    "gn:admin1_code":"8.0",
    "gn:asciiname":"Kolondoko",
    "gn:country_code":"BJ",
    "gn:dem":235,
    "gn:feature_class":"P",
    "gn:feature_code":"PPL",
    "gn:name":"Kolondoko",
    "gn:population":0,
    "gn:timezone":"Africa/Porto-Novo",
    "iso:country":"BJ",
    "wof:name":"Kolondoko",
    "wof:placetype":"locality"
},
  "geometry": {"coordinates":[1.16264,10.50181],"type":"Point"}
}