{
  "type": "Feature",
  "properties": {
    "gn:admin1_code":"13.0",
    "gn:asciiname":"Penelan",
    "gn:country_code":"BJ",
    "gn:dem":420,
    "gn:feature_class":"P",
    "gn:feature_code":"PPL",
    "gn:name":"P\u00e8n\u00e8lan",
    "gn:population":0,
    "gn:timezone":"Africa/Porto-Novo",
    "iso:country":"BJ",
    "name:und_x_variant":[
        "P\u00e9l\u00e9lan",
        "P\u00e8n\u00e8lan"
    ],
    "wof:name":"Penelan",
    "wof:placetype":"locality"
},
  "geometry": {"coordinates":[1.50817,9.24699],"type":"Point"}
}