{
  "type": "Feature",
  "properties": {
    "gn:admin1_code":"13.0",
    "gn:asciiname":"Bassaoutiouri",
    "gn:country_code":"BJ",
    "gn:dem":433,
    "gn:feature_class":"P",
    "gn:feature_code":"PPL",
    "gn:name":"Bassaoutiouri",
    "gn:population":0,
    "gn:timezone":"Africa/Porto-Novo",
    "iso:country":"BJ",
    "wof:name":"Bassaoutiouri",
    "wof:placetype":"locality"
},
  "geometry": {"coordinates":[1.61701,9.58136],"type":"Point"}
}