{
  "type": "Feature",
  "properties": {
    "gn:admin1_code":"13.0",
    "gn:asciiname":"Kassalia",
    "gn:country_code":"BJ",
    "gn:dem":386,
    "gn:feature_class":"P",
    "gn:feature_code":"PPL",
    "gn:name":"Kassalia",
    "gn:population":0,
    "gn:timezone":"Africa/Porto-Novo",
    "iso:country":"BJ",
    "wof:name":"Kassalia",
    "wof:placetype":"locality"
},
  "geometry": {"coordinates":[1.45777,9.52483],"type":"Point"}
}