{
  "type": "Feature",
  "properties": {
    "gn:admin1_code":"10.0",
    "gn:asciiname":"Tasse",
    "gn:country_code":"BJ",
    "gn:dem":346,
    "gn:feature_class":"P",
    "gn:feature_code":"PPL",
    "gn:name":"Tass\u00e9",
    "gn:population":0,
    "gn:timezone":"Africa/Porto-Novo",
    "iso:country":"BJ",
    "name:nld_x_preferred":[
        "Tasse"
    ],
    "wof:name":"Tasse",
    "wof:placetype":"locality"
},
  "geometry": {"coordinates":[2.87163,10.29778],"type":"Point"}
}