{
  "type": "Feature",
  "properties": {
    "gn:admin1_code":"14.0",
    "gn:admin2_code":"7874113.0",
    "gn:asciiname":"Zogbo",
    "gn:country_code":"BJ",
    "gn:dem":7,
    "gn:feature_class":"P",
    "gn:feature_code":"PPL",
    "gn:name":"Zogbo",
    "gn:population":0,
    "gn:timezone":"Africa/Porto-Novo",
    "iso:country":"BJ",
    "wof:name":"Zogbo",
    "wof:placetype":"locality"
},
  "geometry": {"coordinates":[2.38281,6.39213],"type":"Point"}
}