{
  "type": "Feature",
  "properties": {
    "gn:admin1_code":"8.0",
    "gn:asciiname":"Fitiparakou",
    "gn:country_code":"BJ",
    "gn:dem":513,
    "gn:feature_class":"P",
    "gn:feature_code":"PPL",
    "gn:name":"Fitiparakou",
    "gn:population":0,
    "gn:timezone":"Africa/Porto-Novo",
    "iso:country":"BJ",
    "wof:name":"Fitiparakou",
    "wof:placetype":"locality"
},
  "geometry": {"coordinates":[1.2945,10.46337],"type":"Point"}
}