{
  "type": "Feature",
  "properties": {
    "gn:admin1_code":"10.0",
    "gn:asciiname":"Ganegoussarou",
    "gn:country_code":"BJ",
    "gn:dem":348,
    "gn:feature_class":"P",
    "gn:feature_code":"PPL",
    "gn:name":"Gan\u00e9goussarou",
    "gn:population":0,
    "gn:timezone":"Africa/Porto-Novo",
    "iso:country":"BJ",
    "wof:name":"Ganegoussarou",
    "wof:placetype":"locality"
},
  "geometry": {"coordinates":[2.89432,10.2016],"type":"Point"}
}