{
  "type": "Feature",
  "properties": {
    "gn:admin1_code":"10.0",
    "gn:admin2_code":"7669269.0",
    "gn:asciiname":"Ndali",
    "gn:country_code":"BJ",
    "gn:dem":394,
    "gn:feature_class":"P",
    "gn:feature_code":"PPL",
    "gn:name":"Ndali",
    "gn:population":0,
    "gn:timezone":"Africa/Porto-Novo",
    "iso:country":"BJ",
    "name:azb_x_preferred":[
        "\u062f\u0627\u0644\u06cc"
    ],
    "name:fas_x_preferred":[
        "\u062f\u0627\u0644\u06cc"
    ],
    "name:fra_x_preferred":[
        "N'Dali"
    ],
    "name:frr_x_preferred":[
        "N'Dali"
    ],
    "name:ita_x_preferred":[
        "N'Dali"
    ],
    "name:msa_x_preferred":[
        "N'Dali"
    ],
    "name:nld_x_preferred":[
        "N'Dali"
    ],
    "name:pol_x_preferred":[
        "N\u2019Dali"
    ],
    "name:ron_x_preferred":[
        "N\u2019Dali"
    ],
    "name:spa_x_preferred":[
        "N'Dali"
    ],
    "name:swe_x_preferred":[
        "N'Dali"
    ],
    "name:und_x_variant":[
        "N\u2019dali",
        "Ndali"
    ],
    "name:zho_x_preferred":[
        "\u6069\u9054\u5229"
    ],
    "wof:name":"Ndali",
    "wof:placetype":"locality"
},
  "geometry": {"coordinates":[2.72094,9.8636],"type":"Point"}
}