{
  "type": "Feature",
  "properties": {
    "gn:admin1_code":"8.0",
    "gn:asciiname":"Kanbourfa",
    "gn:country_code":"BJ",
    "gn:dem":658,
    "gn:feature_class":"P",
    "gn:feature_code":"PPL",
    "gn:name":"Kanbourfa",
    "gn:population":0,
    "gn:timezone":"Africa/Porto-Novo",
    "iso:country":"BJ",
    "wof:name":"Kanbourfa",
    "wof:placetype":"locality"
},
  "geometry": {"coordinates":[1.54071,10.28435],"type":"Point"}
}