{
  "type": "Feature",
  "properties": {
    "gn:admin1_code":"8.0",
    "gn:asciiname":"Yari-Kate",
    "gn:country_code":"BJ",
    "gn:dem":583,
    "gn:feature_class":"P",
    "gn:feature_code":"PPL",
    "gn:name":"Yari-Kat\u00e9",
    "gn:population":0,
    "gn:timezone":"Africa/Porto-Novo",
    "iso:country":"BJ",
    "name:und_x_variant":[
        "Yari-Kat\u00e9re",
        "Yari-Kat\u00e9"
    ],
    "wof:name":"Yari-Kate",
    "wof:placetype":"locality"
},
  "geometry": {"coordinates":[1.40117,10.38842],"type":"Point"}
}