{
  "type": "Feature",
  "properties": {
    "gn:admin1_code":"8.0",
    "gn:asciiname":"Tanse",
    "gn:country_code":"BJ",
    "gn:dem":414,
    "gn:feature_class":"P",
    "gn:feature_code":"PPL",
    "gn:name":"Tans\u00e9",
    "gn:population":0,
    "gn:timezone":"Africa/Porto-Novo",
    "iso:country":"BJ",
    "name:und_x_variant":[
        "Tenc\u00e9",
        "Tans\u00e9"
    ],
    "wof:name":"Tanse",
    "wof:placetype":"locality"
},
  "geometry": {"coordinates":[1.69343,10.42966],"type":"Point"}
}