{
  "type": "Feature",
  "properties": {
    "gn:admin1_code":"11.0",
    "gn:asciiname":"Agon",
    "gn:country_code":"BJ",
    "gn:dem":234,
    "gn:feature_class":"P",
    "gn:feature_code":"PPL",
    "gn:name":"Agon",
    "gn:population":0,
    "gn:timezone":"Africa/Porto-Novo",
    "iso:country":"BJ",
    "wof:name":"Agon",
    "wof:placetype":"locality"
},
  "geometry": {"coordinates":[1.96667,8.15],"type":"Point"}
}