{
  "type": "Feature",
  "properties": {
    "gn:admin1_code":"11.0",
    "gn:asciiname":"Agon",
    "gn:country_code":"BJ",
    "gn:dem":234,
    "gn:feature_class":"P",
    "gn:feature_code":"PPL",
    "gn:name":"Agon",
    "gn:population":0,
    "gn:timezone":"Africa/Porto-Novo",
    "iso:country":"BJ",
    "name:cat_x_preferred":[
        "Agon"
    ],
    "name:dan_x_preferred":[
        "Agon"
    ],
    "name:deu_x_preferred":[
        "Agon"
    ],
    "name:ell_x_preferred":[
        "\u0391\u03b3\u03ce\u03bd"
    ],
    "name:epo_x_preferred":[
        "Agono"
    ],
    "name:fin_x_preferred":[
        "Agon"
    ],
    "name:fra_x_preferred":[
        "Ag\u00f4n"
    ],
    "name:glg_x_preferred":[
        "Ag\u00f3n"
    ],
    "name:heb_x_preferred":[
        "\u05d0\u05d2\u05d5\u05df"
    ],
    "name:hye_x_preferred":[
        "\u0531\u0563\u0578\u0576"
    ],
    "name:ind_x_preferred":[
        "Agon"
    ],
    "name:ita_x_preferred":[
        "Agone"
    ],
    "name:kaz_x_preferred":[
        "\u0410\u0433\u043e\u043d"
    ],
    "name:nld_x_preferred":[
        "Agon"
    ],
    "name:por_x_preferred":[
        "Agon"
    ],
    "name:rus_x_preferred":[
        "\u0410\u0433\u043e\u043d"
    ],
    "name:slv_x_preferred":[
        "Agon"
    ],
    "name:spa_x_preferred":[
        "Ag\u00f3n"
    ],
    "name:srp_x_preferred":[
        "\u0410\u0433\u043e\u043d"
    ],
    "name:swe_x_preferred":[
        "Agon"
    ],
    "name:tur_x_preferred":[
        "Agon"
    ],
    "name:ukr_x_preferred":[
        "\u0410\u0433\u043e\u043d"
    ],
    "name:uzb_x_preferred":[
        "Agonistiklar"
    ],
    "wof:name":"Agon",
    "wof:placetype":"locality"
},
  "geometry": {"coordinates":[1.96667,8.15],"type":"Point"}
}