{
  "type": "Feature",
  "properties": {
    "gn:admin1_code":"9.0",
    "gn:asciiname":"Ouali",
    "gn:country_code":"BJ",
    "gn:dem":108,
    "gn:feature_class":"P",
    "gn:feature_code":"PPL",
    "gn:name":"Ouali",
    "gn:population":0,
    "gn:timezone":"Africa/Porto-Novo",
    "iso:country":"BJ",
    "wof:name":"Ouali",
    "wof:placetype":"locality"
},
  "geometry": {"coordinates":[2.24874,6.70573],"type":"Point"}
}