{
  "type": "Feature",
  "properties": {
    "gn:admin1_code":"15.0",
    "gn:asciiname":"Ounhoue",
    "gn:cc2":"BJ",
    "gn:country_code":"BJ",
    "gn:dem":64,
    "gn:feature_class":"P",
    "gn:feature_code":"PPL",
    "gn:name":"Ounhou\u00e9",
    "gn:population":0,
    "gn:timezone":"Africa/Porto-Novo",
    "iso:country":"BJ",
    "name:und_x_variant":[
        "Onhou\u00e9",
        "Ounhou\u00e9"
    ],
    "wof:name":"Ounhoue",
    "wof:placetype":"locality"
},
  "geometry": {"coordinates":[1.91667,6.53333],"type":"Point"}
}