{
  "type": "Feature",
  "properties": {
    "gn:admin1_code":"8.0",
    "gn:asciiname":"Poungafaga",
    "gn:country_code":"BJ",
    "gn:dem":458,
    "gn:feature_class":"P",
    "gn:feature_code":"PPL",
    "gn:name":"Poungafaga",
    "gn:population":0,
    "gn:timezone":"Africa/Porto-Novo",
    "iso:country":"BJ",
    "wof:name":"Poungafaga",
    "wof:placetype":"locality"
},
  "geometry": {"coordinates":[1.38142,10.65251],"type":"Point"}
}