{
  "type": "Feature",
  "properties": {
    "gn:admin1_code":"8.0",
    "gn:asciiname":"Saniouri",
    "gn:country_code":"BJ",
    "gn:dem":229,
    "gn:feature_class":"P",
    "gn:feature_code":"PPL",
    "gn:name":"Saniouri",
    "gn:population":0,
    "gn:timezone":"Africa/Porto-Novo",
    "iso:country":"BJ",
    "wof:name":"Saniouri",
    "wof:placetype":"locality"
},
  "geometry": {"coordinates":[1.0225,10.53536],"type":"Point"}
}