{
  "type": "Feature",
  "properties": {
    "gn:admin1_code":"10.0",
    "gn:asciiname":"Badekparou",
    "gn:country_code":"BJ",
    "gn:dem":356,
    "gn:feature_class":"P",
    "gn:feature_code":"PPL",
    "gn:name":"Bad\u00e9kparou",
    "gn:population":0,
    "gn:timezone":"Africa/Porto-Novo",
    "iso:country":"BJ",
    "wof:name":"Badekparou",
    "wof:placetype":"locality"
},
  "geometry": {"coordinates":[2.56571,9.2179],"type":"Point"}
}