{
  "type": "Feature",
  "properties": {
    "gn:admin1_code":"8.0",
    "gn:asciiname":"Korongkore",
    "gn:country_code":"BJ",
    "gn:dem":528,
    "gn:feature_class":"P",
    "gn:feature_code":"PPL",
    "gn:name":"Korongkor\u00e9",
    "gn:population":0,
    "gn:timezone":"Africa/Porto-Novo",
    "iso:country":"BJ",
    "wof:name":"Korongkore",
    "wof:placetype":"locality"
},
  "geometry": {"coordinates":[1.32958,10.58207],"type":"Point"}
}