{
  "type": "Feature",
  "properties": {
    "gn:admin1_code":"9.0",
    "gn:asciiname":"Tanto",
    "gn:country_code":"BJ",
    "gn:dem":57,
    "gn:feature_class":"P",
    "gn:feature_code":"PPL",
    "gn:name":"Tanto",
    "gn:population":0,
    "gn:timezone":"Africa/Porto-Novo",
    "iso:country":"BJ",
    "name:deu_x_preferred":[
        "Tanto"
    ],
    "name:ita_x_preferred":[
        "Tanto"
    ],
    "name:jpn_x_preferred":[
        "\u30bf\u30f3\u30c8"
    ],
    "name:pol_x_preferred":[
        "Tanto"
    ],
    "name:por_x_preferred":[
        "Tanto"
    ],
    "name:swe_x_preferred":[
        "Tanto"
    ],
    "wof:name":"Tanto",
    "wof:placetype":"locality"
},
  "geometry": {"coordinates":[2.18275,6.55312],"type":"Point"}
}