{
  "type": "Feature",
  "properties": {
    "gn:admin1_code":"7.0",
    "gn:asciiname":"Arouna",
    "gn:country_code":"BJ",
    "gn:dem":238,
    "gn:feature_class":"P",
    "gn:feature_code":"PPL",
    "gn:name":"Arouna",
    "gn:population":0,
    "gn:timezone":"Africa/Porto-Novo",
    "iso:country":"BJ",
    "wof:name":"Arouna",
    "wof:placetype":"locality"
},
  "geometry": {"coordinates":[2.93748,11.29984],"type":"Point"}
}