{
  "type": "Feature",
  "properties": {
    "gn:admin1_code":"8.0",
    "gn:asciiname":"Yassenntini",
    "gn:country_code":"BJ",
    "gn:dem":215,
    "gn:feature_class":"P",
    "gn:feature_code":"PPL",
    "gn:name":"Yassenntini",
    "gn:population":0,
    "gn:timezone":"Africa/Porto-Novo",
    "iso:country":"BJ",
    "wof:name":"Yassenntini",
    "wof:placetype":"locality"
},
  "geometry": {"coordinates":[1.1987,10.76703],"type":"Point"}
}