{
  "type": "Feature",
  "properties": {
    "gn:admin1_code":"15.0",
    "gn:asciiname":"Guezin",
    "gn:country_code":"BJ",
    "gn:dem":9,
    "gn:feature_class":"P",
    "gn:feature_code":"PPL",
    "gn:name":"Gu\u00e9zin",
    "gn:population":0,
    "gn:timezone":"Africa/Porto-Novo",
    "iso:country":"BJ",
    "name:und_x_variant":[
        "Gbezin",
        "Gu\u00e9zin"
    ],
    "wof:name":"Guezin",
    "wof:placetype":"locality"
},
  "geometry": {"coordinates":[1.92245,6.39891],"type":"Point"}
}