{
  "type": "Feature",
  "properties": {
    "gn:admin1_code":"10.0",
    "gn:asciiname":"Mariguira",
    "gn:country_code":"BJ",
    "gn:dem":417,
    "gn:feature_class":"P",
    "gn:feature_code":"PPL",
    "gn:name":"Mariguira",
    "gn:population":0,
    "gn:timezone":"Africa/Porto-Novo",
    "iso:country":"BJ",
    "name:und_x_variant":[
        "Mariguinta",
        "Mariguira"
    ],
    "wof:name":"Mariguira",
    "wof:placetype":"locality"
},
  "geometry": {"coordinates":[3.28618,10.21739],"type":"Point"}
}