{
  "type": "Feature",
  "properties": {
    "gn:admin1_code":"7.0",
    "gn:asciiname":"Wopa",
    "gn:country_code":"BJ",
    "gn:dem":294,
    "gn:feature_class":"P",
    "gn:feature_code":"PPL",
    "gn:name":"Wopa",
    "gn:population":0,
    "gn:timezone":"Africa/Porto-Novo",
    "iso:country":"BJ",
    "wof:name":"Wopa",
    "wof:placetype":"locality"
},
  "geometry": {"coordinates":[2.85548,11.02519],"type":"Point"}
}