{
  "type": "Feature",
  "properties": {
    "gn:admin1_code":"8.0",
    "gn:asciiname":"Niarosson",
    "gn:country_code":"BJ",
    "gn:dem":525,
    "gn:feature_class":"P",
    "gn:feature_code":"PPL",
    "gn:name":"Niarosson",
    "gn:population":0,
    "gn:timezone":"Africa/Porto-Novo",
    "iso:country":"BJ",
    "name:und_x_variant":[
        "Nioroson",
        "Niarosson"
    ],
    "wof:name":"Niarosson",
    "wof:placetype":"locality"
},
  "geometry": {"coordinates":[1.60796,10.22656],"type":"Point"}
}