{
  "type": "Feature",
  "properties": {
    "gn:admin1_code":"13.0",
    "gn:asciiname":"Dogue",
    "gn:country_code":"BJ",
    "gn:dem":319,
    "gn:feature_class":"P",
    "gn:feature_code":"PPL",
    "gn:name":"Dogu\u00e9",
    "gn:population":0,
    "gn:timezone":"Africa/Porto-Novo",
    "iso:country":"BJ",
    "name:und_x_variant":[
        "Dogu\u00e9"
    ],
    "wof:name":"Dogue",
    "wof:placetype":"locality"
},
  "geometry": {"coordinates":[1.9329,9.10133],"type":"Point"}
}