{
  "type": "Feature",
  "properties": {
    "gn:admin1_code":"16.0",
    "gn:asciiname":"Gbekendji",
    "gn:country_code":"BJ",
    "gn:dem":72,
    "gn:feature_class":"P",
    "gn:feature_code":"PPL",
    "gn:name":"Gb\u00e9kendji",
    "gn:population":0,
    "gn:timezone":"Africa/Porto-Novo",
    "iso:country":"BJ",
    "name:und_x_variant":[
        "Bekandji",
        "Gb\u00e9kendji"
    ],
    "wof:name":"Gbekendji",
    "wof:placetype":"locality"
},
  "geometry": {"coordinates":[2.54405,6.68435],"type":"Point"}
}