{
  "type": "Feature",
  "properties": {
    "gn:admin1_code":"9.0",
    "gn:asciiname":"Tegbo",
    "gn:country_code":"BJ",
    "gn:dem":82,
    "gn:feature_class":"P",
    "gn:feature_code":"PPL",
    "gn:name":"Tegbo",
    "gn:population":0,
    "gn:timezone":"Africa/Porto-Novo",
    "iso:country":"BJ",
    "wof:name":"Tegbo",
    "wof:placetype":"locality"
},
  "geometry": {"coordinates":[2.06748,6.68228],"type":"Point"}
}