{
  "type": "Feature",
  "properties": {
    "gn:admin1_code":"11.0",
    "gn:asciiname":"Okoutaoko",
    "gn:country_code":"BJ",
    "gn:dem":284,
    "gn:feature_class":"P",
    "gn:feature_code":"PPL",
    "gn:name":"Okoutaoko",
    "gn:population":0,
    "gn:timezone":"Africa/Porto-Novo",
    "iso:country":"BJ",
    "wof:name":"Okoutaoko",
    "wof:placetype":"locality"
},
  "geometry": {"coordinates":[2.70317,8.54858],"type":"Point"}
}