{
  "type": "Feature",
  "properties": {
    "gn:admin1_code":"11.0",
    "gn:asciiname":"Ounbekuido",
    "gn:country_code":"BJ",
    "gn:dem":223,
    "gn:feature_class":"P",
    "gn:feature_code":"PPL",
    "gn:name":"Ounb\u00e8kuido",
    "gn:population":0,
    "gn:timezone":"Africa/Porto-Novo",
    "iso:country":"BJ",
    "wof:name":"Ounbekuido",
    "wof:placetype":"locality"
},
  "geometry": {"coordinates":[2.4094,8.50436],"type":"Point"}
}