{
  "type": "Feature",
  "properties": {
    "gn:admin1_code":"15.0",
    "gn:asciiname":"Agontome",
    "gn:country_code":"BJ",
    "gn:dem":1,
    "gn:feature_class":"P",
    "gn:feature_code":"PPL",
    "gn:name":"Agontom\u00e9",
    "gn:population":0,
    "gn:timezone":"Africa/Porto-Novo",
    "iso:country":"BJ",
    "name:und_x_variant":[
        "Agoutom\u00e9",
        "Agontom\u00e9"
    ],
    "wof:name":"Agontome",
    "wof:placetype":"locality"
},
  "geometry": {"coordinates":[1.89696,6.38497],"type":"Point"}
}