{
  "type": "Feature",
  "properties": {
    "gn:admin1_code":"10.0",
    "gn:asciiname":"Sebana",
    "gn:country_code":"BJ",
    "gn:dem":289,
    "gn:feature_class":"P",
    "gn:feature_code":"PPL",
    "gn:name":"S\u00e9bana",
    "gn:population":0,
    "gn:timezone":"Africa/Porto-Novo",
    "iso:country":"BJ",
    "wof:name":"Sebana",
    "wof:placetype":"locality"
},
  "geometry": {"coordinates":[3.5493,10.52645],"type":"Point"}
}