{
  "type": "Feature",
  "properties": {
    "gn:admin1_code":"7.0",
    "gn:admin2_code":"10344469.0",
    "gn:admin3_code":"11789990.0",
    "gn:asciiname":"Gogounou",
    "gn:country_code":"BJ",
    "gn:dem":328,
    "gn:feature_class":"P",
    "gn:feature_code":"PPL",
    "gn:name":"Gogounou",
    "gn:population":0,
    "gn:timezone":"Africa/Porto-Novo",
    "iso:country":"BJ",
    "name:ceb_x_preferred":[
        "Gogounou"
    ],
    "name:fin_x_preferred":[
        "Gogounou"
    ],
    "name:fra_x_preferred":[
        "Gogounou"
    ],
    "name:frr_x_preferred":[
        "Gogounou"
    ],
    "name:ita_x_preferred":[
        "Gogounou"
    ],
    "name:msa_x_preferred":[
        "Gogounou"
    ],
    "name:nld_x_preferred":[
        "Gogounou"
    ],
    "name:pol_x_preferred":[
        "Gogounou"
    ],
    "name:por_x_preferred":[
        "Gogounou"
    ],
    "name:spa_x_preferred":[
        "Gogounou"
    ],
    "name:swe_x_preferred":[
        "Gogounou"
    ],
    "name:und_x_variant":[
        "Gogonou",
        "Gogounou"
    ],
    "name:zho_x_preferred":[
        "\u6208\u53e4\u52aa"
    ],
    "wof:name":"Gogounou",
    "wof:placetype":"locality"
},
  "geometry": {"coordinates":[2.83174,10.8399],"type":"Point"}
}