{
  "type": "Feature",
  "properties": {
    "gn:admin1_code":"10.0",
    "gn:asciiname":"Tekparou",
    "gn:country_code":"BJ",
    "gn:dem":339,
    "gn:feature_class":"P",
    "gn:feature_code":"PPL",
    "gn:name":"Tekparou",
    "gn:population":0,
    "gn:timezone":"Africa/Porto-Novo",
    "iso:country":"BJ",
    "name:und_x_variant":[
        "Tekpara",
        "T\u00e9paramaro",
        "Tekparou"
    ],
    "wof:name":"Tekparou",
    "wof:placetype":"locality"
},
  "geometry": {"coordinates":[2.58474,9.00655],"type":"Point"}
}