{
  "type": "Feature",
  "properties": {
    "gn:admin1_code":"15.0",
    "gn:asciiname":"Gandjazoume",
    "gn:country_code":"BJ",
    "gn:dem":74,
    "gn:feature_class":"P",
    "gn:feature_code":"PPL",
    "gn:name":"Gandjazoum\u00e9",
    "gn:population":0,
    "gn:timezone":"Africa/Porto-Novo",
    "iso:country":"BJ",
    "wof:name":"Gandjazoume",
    "wof:placetype":"locality"
},
  "geometry": {"coordinates":[1.76667,6.73333],"type":"Point"}
}