{
  "type": "Feature",
  "properties": {
    "gn:admin1_code":"11.0",
    "gn:asciiname":"Akakadoho",
    "gn:country_code":"BJ",
    "gn:dem":170,
    "gn:feature_class":"P",
    "gn:feature_code":"PPL",
    "gn:name":"Akakadoho",
    "gn:population":0,
    "gn:timezone":"Africa/Porto-Novo",
    "iso:country":"BJ",
    "wof:name":"Akakadoho",
    "wof:placetype":"locality"
},
  "geometry": {"coordinates":[1.81667,7.86667],"type":"Point"}
}