{
  "type": "Feature",
  "properties": {
    "gn:admin1_code":"12.0",
    "gn:asciiname":"Tchiatome",
    "gn:country_code":"BJ",
    "gn:dem":42,
    "gn:feature_class":"P",
    "gn:feature_code":"PPL",
    "gn:name":"Tchiatom\u00e8",
    "gn:population":0,
    "gn:timezone":"Africa/Porto-Novo",
    "iso:country":"BJ",
    "wof:name":"Tchiatome",
    "wof:placetype":"locality"
},
  "geometry": {"coordinates":[1.96667,6.88333],"type":"Point"}
}