{
  "type": "Feature",
  "properties": {
    "gn:admin1_code":"10.0",
    "gn:asciiname":"Kourourou",
    "gn:country_code":"BJ",
    "gn:dem":385,
    "gn:feature_class":"P",
    "gn:feature_code":"PPL",
    "gn:name":"Kourourou",
    "gn:population":0,
    "gn:timezone":"Africa/Porto-Novo",
    "iso:country":"BJ",
    "wof:name":"Kourourou",
    "wof:placetype":"locality"
},
  "geometry": {"coordinates":[3.02783,9.93536],"type":"Point"}
}