{
  "type": "Feature",
  "properties": {
    "gn:admin1_code":"9.0",
    "gn:asciiname":"Ouakpe",
    "gn:country_code":"BJ",
    "gn:dem":2,
    "gn:feature_class":"P",
    "gn:feature_code":"PPL",
    "gn:name":"Ouakp\u00e9",
    "gn:population":0,
    "gn:timezone":"Africa/Porto-Novo",
    "iso:country":"BJ",
    "wof:name":"Ouakpe",
    "wof:placetype":"locality"
},
  "geometry": {"coordinates":[2.05,6.33333],"type":"Point"}
}