{
  "type": "Feature",
  "properties": {
    "gn:admin1_code":"10.0",
    "gn:asciiname":"Saore-Son",
    "gn:country_code":"BJ",
    "gn:dem":345,
    "gn:feature_class":"P",
    "gn:feature_code":"PPL",
    "gn:name":"Saor\u00e9-Son",
    "gn:population":0,
    "gn:timezone":"Africa/Porto-Novo",
    "iso:country":"BJ",
    "wof:name":"Saore-Son",
    "wof:placetype":"locality"
},
  "geometry": {"coordinates":[2.51274,10.23328],"type":"Point"}
}