{
  "type": "Feature",
  "properties": {
    "gn:admin1_code":"10.0",
    "gn:asciiname":"Kekopo",
    "gn:country_code":"BJ",
    "gn:dem":416,
    "gn:feature_class":"P",
    "gn:feature_code":"PPL",
    "gn:name":"K\u00e9kopo",
    "gn:population":0,
    "gn:timezone":"Africa/Porto-Novo",
    "iso:country":"BJ",
    "wof:name":"Kekopo",
    "wof:placetype":"locality"
},
  "geometry": {"coordinates":[3.05954,9.64773],"type":"Point"}
}