{
  "type": "Feature",
  "properties": {
    "gn:admin1_code":"8.0",
    "gn:asciiname":"Pikire",
    "gn:country_code":"BJ",
    "gn:dem":364,
    "gn:feature_class":"P",
    "gn:feature_code":"PPL",
    "gn:name":"Pikire",
    "gn:population":0,
    "gn:timezone":"Africa/Porto-Novo",
    "iso:country":"BJ",
    "name:und_x_variant":[
        "P\u00e9k\u00e9r\u00e9",
        "Pikire"
    ],
    "wof:name":"Pikire",
    "wof:placetype":"locality"
},
  "geometry": {"coordinates":[2.12548,10.73545],"type":"Point"}
}