{
  "type": "Feature",
  "properties": {
    "gn:admin1_code":"10.0",
    "gn:asciiname":"Babire",
    "gn:country_code":"BJ",
    "gn:dem":488,
    "gn:feature_class":"P",
    "gn:feature_code":"PPL",
    "gn:name":"Babir\u00e9",
    "gn:population":0,
    "gn:timezone":"Africa/Porto-Novo",
    "iso:country":"BJ",
    "wof:name":"Babire",
    "wof:placetype":"locality"
},
  "geometry": {"coordinates":[3.19351,9.67332],"type":"Point"}
}