{
  "type": "Feature",
  "properties": {
    "gn:admin1_code":"10.0",
    "gn:asciiname":"Serou",
    "gn:country_code":"BJ",
    "gn:dem":312,
    "gn:feature_class":"P",
    "gn:feature_code":"PPL",
    "gn:name":"Serou",
    "gn:population":0,
    "gn:timezone":"Africa/Porto-Novo",
    "iso:country":"BJ",
    "wof:name":"Serou",
    "wof:placetype":"locality"
},
  "geometry": {"coordinates":[2.62399,8.87429],"type":"Point"}
}