{
  "type": "Feature",
  "properties": {
    "gn:admin1_code":"13.0",
    "gn:asciiname":"Kpelrhou-Kparhoute",
    "gn:country_code":"BJ",
    "gn:dem":347,
    "gn:feature_class":"P",
    "gn:feature_code":"PPL",
    "gn:name":"Kpelrhou-Kparhout\u00e8",
    "gn:population":0,
    "gn:timezone":"Africa/Porto-Novo",
    "iso:country":"BJ",
    "name:und_x_variant":[
        "Pargout\u00e9",
        "Kpelrhou-Kparhout\u00e8"
    ],
    "wof:name":"Kpelrhou-Kparhoute",
    "wof:placetype":"locality"
},
  "geometry": {"coordinates":[1.40042,9.96449],"type":"Point"}
}