{
  "type": "Feature",
  "properties": {
    "gn:admin1_code":"10.0",
    "gn:asciiname":"Alafiarou",
    "gn:country_code":"BJ",
    "gn:dem":286,
    "gn:feature_class":"P",
    "gn:feature_code":"PPL",
    "gn:name":"Alafiarou",
    "gn:population":0,
    "gn:timezone":"Africa/Porto-Novo",
    "iso:country":"BJ",
    "name:azb_x_preferred":[
        "\u0627\u0644\u0627\u0641\u06cc\u0627\u0631\u0648"
    ],
    "name:fas_x_preferred":[
        "\u0627\u0644\u0627\u0641\u06cc\u0627\u0631\u0648"
    ],
    "name:fra_x_preferred":[
        "Alafiarou"
    ],
    "name:ita_x_preferred":[
        "Alafiarou"
    ],
    "name:msa_x_preferred":[
        "Alafiarou"
    ],
    "name:und_x_variant":[
        "Alafia",
        "Halatia",
        "Halafia",
        "Alafiarou"
    ],
    "wof:name":"Alafiarou",
    "wof:placetype":"locality"
},
  "geometry": {"coordinates":[2.40438,9.02839],"type":"Point"}
}