{
  "type": "Feature",
  "properties": {
    "gn:admin1_code":"10.0",
    "gn:asciiname":"Koni",
    "gn:country_code":"BJ",
    "gn:dem":387,
    "gn:feature_class":"P",
    "gn:feature_code":"PPL",
    "gn:name":"Koni",
    "gn:population":0,
    "gn:timezone":"Africa/Porto-Novo",
    "iso:country":"BJ",
    "name:aka_x_preferred":[
        "Koni"
    ],
    "name:ceb_x_preferred":[
        "Koni"
    ],
    "name:deu_x_preferred":[
        "Koni"
    ],
    "name:est_x_preferred":[
        "Koni"
    ],
    "name:fra_x_preferred":[
        "Koni"
    ],
    "name:kat_x_preferred":[
        "\u10d9\u10dd\u10dc\u10d8"
    ],
    "name:rus_x_preferred":[
        "\u041a\u043e\u043d\u0438"
    ],
    "name:srp_x_preferred":[
        "\u041a\u043e\u043d\u0438"
    ],
    "name:swe_x_preferred":[
        "Koni"
    ],
    "wof:name":"Koni",
    "wof:placetype":"locality"
},
  "geometry": {"coordinates":[3.08008,9.92324],"type":"Point"}
}