{
  "type": "Feature",
  "properties": {
    "gn:admin1_code":"10.0",
    "gn:asciiname":"Koni",
    "gn:country_code":"BJ",
    "gn:dem":387,
    "gn:feature_class":"P",
    "gn:feature_code":"PPL",
    "gn:name":"Koni",
    "gn:population":0,
    "gn:timezone":"Africa/Porto-Novo",
    "iso:country":"BJ",
    "wof:name":"Koni",
    "wof:placetype":"locality"
},
  "geometry": {"coordinates":[3.08008,9.92324],"type":"Point"}
}