{
  "type": "Feature",
  "properties": {
    "gn:admin1_code":"10.0",
    "gn:asciiname":"Wotere",
    "gn:country_code":"BJ",
    "gn:dem":451,
    "gn:feature_class":"P",
    "gn:feature_code":"PPL",
    "gn:name":"Wot\u00e9r\u00e9",
    "gn:population":0,
    "gn:timezone":"Africa/Porto-Novo",
    "iso:country":"BJ",
    "wof:name":"Wotere",
    "wof:placetype":"locality"
},
  "geometry": {"coordinates":[3.32029,9.91696],"type":"Point"}
}