{
  "type": "Feature",
  "properties": {
    "gn:admin1_code":"12.0",
    "gn:asciiname":"Venahoue",
    "gn:country_code":"BJ",
    "gn:dem":93,
    "gn:feature_class":"P",
    "gn:feature_code":"PPL",
    "gn:name":"V\u00e9nahou\u00e9",
    "gn:population":0,
    "gn:timezone":"Africa/Porto-Novo",
    "iso:country":"BJ",
    "wof:name":"Venahoue",
    "wof:placetype":"locality"
},
  "geometry": {"coordinates":[1.68333,6.81667],"type":"Point"}
}