{
  "type": "Feature",
  "properties": {
    "gn:admin1_code":"10.0",
    "gn:asciiname":"Bankoubou",
    "gn:country_code":"BJ",
    "gn:dem":371,
    "gn:feature_class":"P",
    "gn:feature_code":"PPL",
    "gn:name":"Bankoubou",
    "gn:population":0,
    "gn:timezone":"Africa/Porto-Novo",
    "iso:country":"BJ",
    "wof:name":"Bankoubou",
    "wof:placetype":"locality"
},
  "geometry": {"coordinates":[3.34365,10.27128],"type":"Point"}
}