{
  "type": "Feature",
  "properties": {
    "gn:admin1_code":"10.0",
    "gn:asciiname":"Goborou",
    "gn:country_code":"BJ",
    "gn:dem":393,
    "gn:feature_class":"P",
    "gn:feature_code":"PPL",
    "gn:name":"Goborou",
    "gn:population":0,
    "gn:timezone":"Africa/Porto-Novo",
    "iso:country":"BJ",
    "wof:name":"Goborou",
    "wof:placetype":"locality"
},
  "geometry": {"coordinates":[2.85883,9.7821],"type":"Point"}
}