{
  "type": "Feature",
  "properties": {
    "gn:admin1_code":"8.0",
    "gn:asciiname":"Tarissari",
    "gn:country_code":"BJ",
    "gn:dem":531,
    "gn:feature_class":"P",
    "gn:feature_code":"PPL",
    "gn:name":"Tarissari",
    "gn:population":0,
    "gn:timezone":"Africa/Porto-Novo",
    "iso:country":"BJ",
    "wof:name":"Tarissari",
    "wof:placetype":"locality"
},
  "geometry": {"coordinates":[1.51532,10.4079],"type":"Point"}
}