{
  "type": "Feature",
  "properties": {
    "gn:admin1_code":"7.0",
    "gn:asciiname":"Karagounkourou",
    "gn:country_code":"BJ",
    "gn:dem":330,
    "gn:feature_class":"P",
    "gn:feature_code":"PPL",
    "gn:name":"Karagounkourou",
    "gn:population":0,
    "gn:timezone":"Africa/Porto-Novo",
    "iso:country":"BJ",
    "wof:name":"Karagounkourou",
    "wof:placetype":"locality"
},
  "geometry": {"coordinates":[2.24308,11.10005],"type":"Point"}
}