{
  "type": "Feature",
  "properties": {
    "gn:admin1_code":"17.0",
    "gn:asciiname":"Isselou",
    "gn:country_code":"BJ",
    "gn:dem":233,
    "gn:feature_class":"P",
    "gn:feature_code":"PPL",
    "gn:name":"Iss\u00e9lou",
    "gn:population":0,
    "gn:timezone":"Africa/Porto-Novo",
    "iso:country":"BJ",
    "wof:name":"Isselou",
    "wof:placetype":"locality"
},
  "geometry": {"coordinates":[2.71866,7.47495],"type":"Point"}
}