{
  "type": "Feature",
  "properties": {
    "gn:admin1_code":"10.0",
    "gn:asciiname":"Borone",
    "gn:country_code":"BJ",
    "gn:dem":323,
    "gn:feature_class":"P",
    "gn:feature_code":"PPL",
    "gn:name":"Boron\u00e9",
    "gn:population":0,
    "gn:timezone":"Africa/Porto-Novo",
    "iso:country":"BJ",
    "wof:name":"Borone",
    "wof:placetype":"locality"
},
  "geometry": {"coordinates":[2.57893,8.89189],"type":"Point"}
}