{
  "type": "Feature",
  "properties": {
    "gn:admin1_code":"10.0",
    "gn:asciiname":"Dankou",
    "gn:country_code":"BJ",
    "gn:dem":342,
    "gn:feature_class":"P",
    "gn:feature_code":"PPL",
    "gn:name":"Dankou",
    "gn:population":0,
    "gn:timezone":"Africa/Porto-Novo",
    "iso:country":"BJ",
    "name:zho_x_preferred":[
        "\u4e39\u53e3\u9547"
    ],
    "wof:name":"Dankou",
    "wof:placetype":"locality"
},
  "geometry": {"coordinates":[3.3062,10.34852],"type":"Point"}
}