{
  "type": "Feature",
  "properties": {
    "gn:admin1_code":"8.0",
    "gn:asciiname":"Sapande",
    "gn:country_code":"BJ",
    "gn:dem":176,
    "gn:feature_class":"P",
    "gn:feature_code":"PPL",
    "gn:name":"Sapand\u00e9",
    "gn:population":0,
    "gn:timezone":"Africa/Porto-Novo",
    "iso:country":"BJ",
    "name:und_x_variant":[
        "Sapantandi",
        "Sapand\u00e9"
    ],
    "wof:name":"Sapande",
    "wof:placetype":"locality"
},
  "geometry": {"coordinates":[0.80794,10.55996],"type":"Point"}
}