{
  "type": "Feature",
  "properties": {
    "gn:admin1_code":"12.0",
    "gn:asciiname":"Sakpeta",
    "gn:country_code":"BJ",
    "gn:dem":171,
    "gn:feature_class":"P",
    "gn:feature_code":"PPL",
    "gn:name":"Sakp\u00e9ta",
    "gn:population":0,
    "gn:timezone":"Africa/Porto-Novo",
    "iso:country":"BJ",
    "wof:name":"Sakpeta",
    "wof:placetype":"locality"
},
  "geometry": {"coordinates":[1.66667,7.28333],"type":"Point"}
}