{
  "type": "Feature",
  "properties": {
    "gn:admin1_code":"7.0",
    "gn:asciiname":"Kotowe",
    "gn:country_code":"BJ",
    "gn:dem":190,
    "gn:feature_class":"P",
    "gn:feature_code":"PPL",
    "gn:name":"Kotow\u00e9",
    "gn:population":0,
    "gn:timezone":"Africa/Porto-Novo",
    "iso:country":"BJ",
    "wof:name":"Kotowe",
    "wof:placetype":"locality"
},
  "geometry": {"coordinates":[3.00047,12.12395],"type":"Point"}
}