{
  "type": "Feature",
  "properties": {
    "gn:admin1_code":"10.0",
    "gn:asciiname":"Ouenagourou",
    "gn:country_code":"BJ",
    "gn:dem":313,
    "gn:feature_class":"P",
    "gn:feature_code":"PPL",
    "gn:name":"Ou\u00e9nagourou",
    "gn:population":0,
    "gn:timezone":"Africa/Porto-Novo",
    "iso:country":"BJ",
    "name:und_x_variant":[
        "Wenagourou",
        "Ou\u00e9nagourou"
    ],
    "wof:name":"Ouenagourou",
    "wof:placetype":"locality"
},
  "geometry": {"coordinates":[3.19244,10.34389],"type":"Point"}
}