{
  "type": "Feature",
  "properties": {
    "gn:admin1_code":"8.0",
    "gn:asciiname":"Bounta",
    "gn:country_code":"BJ",
    "gn:dem":524,
    "gn:feature_class":"P",
    "gn:feature_code":"PPL",
    "gn:name":"Bounta",
    "gn:population":0,
    "gn:timezone":"Africa/Porto-Novo",
    "iso:country":"BJ",
    "wof:name":"Bounta",
    "wof:placetype":"locality"
},
  "geometry": {"coordinates":[1.34764,10.61682],"type":"Point"}
}