{
  "type": "Feature",
  "properties": {
    "gn:admin1_code":"8.0",
    "gn:asciiname":"Ouberekou",
    "gn:country_code":"BJ",
    "gn:dem":382,
    "gn:feature_class":"P",
    "gn:feature_code":"PPL",
    "gn:name":"Oub\u00e9r\u00e9kou",
    "gn:population":0,
    "gn:timezone":"Africa/Porto-Novo",
    "iso:country":"BJ",
    "wof:name":"Ouberekou",
    "wof:placetype":"locality"
},
  "geometry": {"coordinates":[2.02535,10.28566],"type":"Point"}
}