{
  "type": "Feature",
  "properties": {
    "gn:admin1_code":"9.0",
    "gn:asciiname":"Oueke-Zoume",
    "gn:country_code":"BJ",
    "gn:dem":26,
    "gn:feature_class":"P",
    "gn:feature_code":"PPL",
    "gn:name":"Ou\u00e9k\u00e8-Zoum\u00e8",
    "gn:population":0,
    "gn:timezone":"Africa/Porto-Novo",
    "iso:country":"BJ",
    "wof:name":"Oueke-Zoume",
    "wof:placetype":"locality"
},
  "geometry": {"coordinates":[2.33333,6.48333],"type":"Point"}
}