{
  "type": "Feature",
  "properties": {
    "gn:admin1_code":"13.0",
    "gn:asciiname":"Mborko",
    "gn:country_code":"BJ",
    "gn:dem":353,
    "gn:feature_class":"P",
    "gn:feature_code":"PPL",
    "gn:name":"Mborko",
    "gn:population":0,
    "gn:timezone":"Africa/Porto-Novo",
    "iso:country":"BJ",
    "name:und_x_variant":[
        "Borko",
        "Mborko"
    ],
    "wof:name":"Mborko",
    "wof:placetype":"locality"
},
  "geometry": {"coordinates":[1.7438,9.18663],"type":"Point"}
}