{
  "type": "Feature",
  "properties": {
    "gn:admin1_code":"7.0",
    "gn:asciiname":"Louanzi",
    "gn:country_code":"BJ",
    "gn:dem":302,
    "gn:feature_class":"P",
    "gn:feature_code":"PPL",
    "gn:name":"Louanzi",
    "gn:population":0,
    "gn:timezone":"Africa/Porto-Novo",
    "iso:country":"BJ",
    "wof:name":"Louanzi",
    "wof:placetype":"locality"
},
  "geometry": {"coordinates":[3.67913,10.87229],"type":"Point"}
}