{
  "type": "Feature",
  "properties": {
    "gn:admin1_code":"18.0",
    "gn:asciiname":"Ouansougon",
    "gn:country_code":"BJ",
    "gn:dem":79,
    "gn:feature_class":"P",
    "gn:feature_code":"PPL",
    "gn:name":"Ouansougon",
    "gn:population":0,
    "gn:timezone":"Africa/Porto-Novo",
    "iso:country":"BJ",
    "name:und_x_variant":[
        "Wassugon",
        "Ouansougon"
    ],
    "wof:name":"Ouansougon",
    "wof:placetype":"locality"
},
  "geometry": {"coordinates":[2.06117,7.0218],"type":"Point"}
}