{
  "type": "Feature",
  "properties": {
    "gn:admin1_code":"7.0",
    "gn:asciiname":"Gbenkourouna",
    "gn:country_code":"BJ",
    "gn:dem":298,
    "gn:feature_class":"P",
    "gn:feature_code":"PPL",
    "gn:name":"Gb\u00e9nkourouna",
    "gn:population":0,
    "gn:timezone":"Africa/Porto-Novo",
    "iso:country":"BJ",
    "name:und_x_variant":[
        "Bekourona",
        "Gb\u00e9nkourouna"
    ],
    "wof:name":"Gbenkourouna",
    "wof:placetype":"locality"
},
  "geometry": {"coordinates":[3.49776,10.97644],"type":"Point"}
}