{
  "type": "Feature",
  "properties": {
    "gn:admin1_code":"8.0",
    "gn:asciiname":"Naffa",
    "gn:country_code":"BJ",
    "gn:dem":208,
    "gn:feature_class":"P",
    "gn:feature_code":"PPL",
    "gn:name":"Naffa",
    "gn:population":0,
    "gn:timezone":"Africa/Porto-Novo",
    "iso:country":"BJ",
    "wof:name":"Naffa",
    "wof:placetype":"locality"
},
  "geometry": {"coordinates":[3.51275,11.65894],"type":"Point"}
}