{
  "type": "Feature",
  "properties": {
    "gn:admin1_code":"13.0",
    "gn:asciiname":"Bandessar",
    "gn:country_code":"BJ",
    "gn:dem":462,
    "gn:feature_class":"P",
    "gn:feature_code":"PPL",
    "gn:name":"Band\u00e9ssar",
    "gn:population":0,
    "gn:timezone":"Africa/Porto-Novo",
    "iso:country":"BJ",
    "wof:name":"Bandessar",
    "wof:placetype":"locality"
},
  "geometry": {"coordinates":[1.55367,9.70003],"type":"Point"}
}