{
  "type": "Feature",
  "properties": {
    "gn:admin1_code":"8.0",
    "gn:asciiname":"Koko Tombo",
    "gn:country_code":"BJ",
    "gn:dem":199,
    "gn:feature_class":"P",
    "gn:feature_code":"PPL",
    "gn:name":"Koko Tombo",
    "gn:population":0,
    "gn:timezone":"Africa/Porto-Novo",
    "iso:country":"BJ",
    "wof:name":"Koko Tombo",
    "wof:placetype":"locality"
},
  "geometry": {"coordinates":[3.47758,11.67957],"type":"Point"}
}