{
  "type": "Feature",
  "properties": {
    "gn:admin1_code":"10.0",
    "gn:asciiname":"Gorobani",
    "gn:country_code":"BJ",
    "gn:dem":379,
    "gn:feature_class":"P",
    "gn:feature_code":"PPL",
    "gn:name":"Gorobani",
    "gn:population":0,
    "gn:timezone":"Africa/Porto-Novo",
    "iso:country":"BJ",
    "wof:name":"Gorobani",
    "wof:placetype":"locality"
},
  "geometry": {"coordinates":[2.56402,9.34904],"type":"Point"}
}