{
  "type": "Feature",
  "properties": {
    "gn:admin1_code":"8.0",
    "gn:asciiname":"Tassahounpourouporga",
    "gn:country_code":"BJ",
    "gn:dem":155,
    "gn:feature_class":"P",
    "gn:feature_code":"PPL",
    "gn:name":"Tassahounpourouporga",
    "gn:population":0,
    "gn:timezone":"Africa/Porto-Novo",
    "iso:country":"BJ",
    "wof:name":"Tassahounpourouporga",
    "wof:placetype":"locality"
},
  "geometry": {"coordinates":[0.90823,10.80166],"type":"Point"}
}