{
  "type": "Feature",
  "properties": {
    "gn:admin1_code":"8.0",
    "gn:asciiname":"Tingourou",
    "gn:country_code":"BJ",
    "gn:dem":360,
    "gn:feature_class":"P",
    "gn:feature_code":"PPL",
    "gn:name":"Tingourou",
    "gn:population":0,
    "gn:timezone":"Africa/Porto-Novo",
    "iso:country":"BJ",
    "wof:name":"Tingourou",
    "wof:placetype":"locality"
},
  "geometry": {"coordinates":[2.16088,10.86052],"type":"Point"}
}