{
  "type": "Feature",
  "properties": {
    "gn:admin1_code":"10.0",
    "gn:asciiname":"Waroua",
    "gn:country_code":"BJ",
    "gn:dem":315,
    "gn:feature_class":"P",
    "gn:feature_code":"PPL",
    "gn:name":"Waroua",
    "gn:population":0,
    "gn:timezone":"Africa/Porto-Novo",
    "iso:country":"BJ",
    "wof:name":"Waroua",
    "wof:placetype":"locality"
},
  "geometry": {"coordinates":[2.53281,9.71787],"type":"Point"}
}