{
  "type": "Feature",
  "properties": {
    "gn:admin1_code":"9.0",
    "gn:asciiname":"Ouagbo-Aliho",
    "gn:country_code":"BJ",
    "gn:dem":158,
    "gn:feature_class":"P",
    "gn:feature_code":"PPL",
    "gn:name":"Ouagbo-Aliho",
    "gn:population":0,
    "gn:timezone":"Africa/Porto-Novo",
    "iso:country":"BJ",
    "name:und_x_variant":[
        "Ouagbo",
        "Wagbo",
        "Ouagbo-Aliho"
    ],
    "wof:name":"Ouagbo-Aliho",
    "wof:placetype":"locality"
},
  "geometry": {"coordinates":[2.18258,6.83221],"type":"Point"}
}