{
  "type": "Feature",
  "properties": {
    "gn:admin1_code":"7.0",
    "gn:asciiname":"Goussissare",
    "gn:country_code":"BJ",
    "gn:dem":269,
    "gn:feature_class":"P",
    "gn:feature_code":"PPL",
    "gn:name":"Goussissar\u00e9",
    "gn:population":0,
    "gn:timezone":"Africa/Porto-Novo",
    "iso:country":"BJ",
    "name:und_x_variant":[
        "Goussin Sar\u00e9",
        "Goussissar\u00e9"
    ],
    "wof:name":"Goussissare",
    "wof:placetype":"locality"
},
  "geometry": {"coordinates":[3.73704,10.92433],"type":"Point"}
}