{
  "type": "Feature",
  "properties": {
    "gn:admin1_code":"8.0",
    "gn:asciiname":"Tissofonti",
    "gn:country_code":"BJ",
    "gn:dem":550,
    "gn:feature_class":"P",
    "gn:feature_code":"PPL",
    "gn:name":"Tissofonti",
    "gn:population":0,
    "gn:timezone":"Africa/Porto-Novo",
    "iso:country":"BJ",
    "name:und_x_variant":[
        "Tisofonti",
        "Tissofonti"
    ],
    "wof:name":"Tissofonti",
    "wof:placetype":"locality"
},
  "geometry": {"coordinates":[1.26974,10.29223],"type":"Point"}
}