{
  "type": "Feature",
  "properties": {
    "gn:admin1_code":"10.0",
    "gn:asciiname":"Baoussi",
    "gn:country_code":"BJ",
    "gn:dem":411,
    "gn:feature_class":"P",
    "gn:feature_code":"PPL",
    "gn:name":"Baoussi",
    "gn:population":0,
    "gn:timezone":"Africa/Porto-Novo",
    "iso:country":"BJ",
    "wof:name":"Baoussi",
    "wof:placetype":"locality"
},
  "geometry": {"coordinates":[3.17881,9.90379],"type":"Point"}
}