{
  "type": "Feature",
  "properties": {
    "gn:admin1_code":"8.0",
    "gn:asciiname":"Tanfere",
    "gn:country_code":"BJ",
    "gn:dem":525,
    "gn:feature_class":"P",
    "gn:feature_code":"PPL",
    "gn:name":"Tanf\u00e9r\u00e9",
    "gn:population":0,
    "gn:timezone":"Africa/Porto-Novo",
    "iso:country":"BJ",
    "wof:name":"Tanfere",
    "wof:placetype":"locality"
},
  "geometry": {"coordinates":[1.33047,10.60339],"type":"Point"}
}