{
  "type": "Feature",
  "properties": {
    "gn:admin1_code":"7.0",
    "gn:admin2_code":"7874155.0",
    "gn:admin3_code":"11790269.0",
    "gn:asciiname":"Bogo Bogo",
    "gn:country_code":"BJ",
    "gn:dem":192,
    "gn:feature_class":"P",
    "gn:feature_code":"PPL",
    "gn:name":"Bogo Bogo",
    "gn:population":0,
    "gn:timezone":"Africa/Porto-Novo",
    "iso:country":"BJ",
    "name:ita_x_preferred":[
        "Bogo-Bogo"
    ],
    "name:msa_x_preferred":[
        "Bogo-Bogo"
    ],
    "name:swe_x_preferred":[
        "Bogo-Bogo"
    ],
    "wof:name":"Bogo Bogo",
    "wof:placetype":"locality"
},
  "geometry": {"coordinates":[3.1051,12.10646],"type":"Point"}
}