{
  "type": "Feature",
  "properties": {
    "gn:admin1_code":"13.0",
    "gn:asciiname":"Tchembere",
    "gn:country_code":"BJ",
    "gn:dem":492,
    "gn:feature_class":"P",
    "gn:feature_code":"PPL",
    "gn:name":"Tch\u00e8mb\u00e8r\u00e9",
    "gn:population":0,
    "gn:timezone":"Africa/Porto-Novo",
    "iso:country":"BJ",
    "name:und_x_variant":[
        "Tch\u00e8mb\u00e8r\u00e9"
    ],
    "wof:name":"Tchembere",
    "wof:placetype":"locality"
},
  "geometry": {"coordinates":[1.42579,9.33913],"type":"Point"}
}