{
  "type": "Feature",
  "properties": {
    "gn:admin1_code":"7.0",
    "gn:asciiname":"Pede",
    "gn:country_code":"BJ",
    "gn:dem":266,
    "gn:feature_class":"P",
    "gn:feature_code":"PPL",
    "gn:name":"P\u00e9d\u00e9",
    "gn:population":0,
    "gn:timezone":"Africa/Porto-Novo",
    "iso:country":"BJ",
    "name:est_x_preferred":[
        "Pede"
    ],
    "wof:name":"Pede",
    "wof:placetype":"locality"
},
  "geometry": {"coordinates":[2.9532,11.19103],"type":"Point"}
}