{
  "type": "Feature",
  "properties": {
    "gn:admin1_code":"7.0",
    "gn:admin2_code":"7668935.0",
    "gn:admin3_code":"11789988.0",
    "gn:asciiname":"Goumori",
    "gn:country_code":"BJ",
    "gn:dem":303,
    "gn:feature_class":"P",
    "gn:feature_code":"PPLA3",
    "gn:name":"Goumori",
    "gn:population":0,
    "gn:timezone":"Africa/Porto-Novo",
    "iso:country":"BJ",
    "name:ceb_x_preferred":[
        "Goumori"
    ],
    "name:ita_x_preferred":[
        "Goumori"
    ],
    "name:msa_x_preferred":[
        "Goumori"
    ],
    "name:swe_x_preferred":[
        "Goumori"
    ],
    "wof:name":"Goumori",
    "wof:placetype":"locality"
},
  "geometry": {"coordinates":[2.29295,11.18131],"type":"Point"}
}