{
  "type": "Feature",
  "properties": {
    "gn:admin1_code":"7.0",
    "gn:asciiname":"Bepouna",
    "gn:country_code":"BJ",
    "gn:dem":318,
    "gn:feature_class":"P",
    "gn:feature_code":"PPL",
    "gn:name":"B\u00e9pouna",
    "gn:population":0,
    "gn:timezone":"Africa/Porto-Novo",
    "iso:country":"BJ",
    "wof:name":"Bepouna",
    "wof:placetype":"locality"
},
  "geometry": {"coordinates":[3.5562,10.74568],"type":"Point"}
}