{
  "type": "Feature",
  "properties": {
    "gn:admin1_code":"7.0",
    "gn:asciiname":"Ninianegourou",
    "gn:country_code":"BJ",
    "gn:dem":314,
    "gn:feature_class":"P",
    "gn:feature_code":"PPL",
    "gn:name":"Ninian\u00e9gourou",
    "gn:population":0,
    "gn:timezone":"Africa/Porto-Novo",
    "iso:country":"BJ",
    "wof:name":"Ninianegourou",
    "wof:placetype":"locality"
},
  "geometry": {"coordinates":[2.83305,10.63772],"type":"Point"}
}