{
  "type": "Feature",
  "properties": {
    "gn:admin1_code":"15.0",
    "gn:asciiname":"Igonza",
    "gn:country_code":"BJ",
    "gn:dem":45,
    "gn:feature_class":"P",
    "gn:feature_code":"PPL",
    "gn:name":"Igonza",
    "gn:population":0,
    "gn:timezone":"Africa/Porto-Novo",
    "iso:country":"BJ",
    "name:und_x_variant":[
        "Azizonja",
        "Igonza"
    ],
    "wof:name":"Igonza",
    "wof:placetype":"locality"
},
  "geometry": {"coordinates":[1.71198,6.70356],"type":"Point"}
}