{
  "type": "Feature",
  "properties": {
    "gn:admin1_code":"14.0",
    "gn:asciiname":"Dandji",
    "gn:country_code":"BJ",
    "gn:dem":2,
    "gn:feature_class":"P",
    "gn:feature_code":"PPL",
    "gn:name":"Dandji",
    "gn:population":0,
    "gn:timezone":"Africa/Porto-Novo",
    "iso:country":"BJ",
    "wof:name":"Dandji",
    "wof:placetype":"locality"
},
  "geometry": {"coordinates":[2.39086,6.37034],"type":"Point"}
}