{
  "type": "Feature",
  "properties": {
    "gn:admin1_code":"10.0",
    "gn:asciiname":"Dagarogoiparou",
    "gn:country_code":"BJ",
    "gn:dem":353,
    "gn:feature_class":"P",
    "gn:feature_code":"PPL",
    "gn:name":"Dagarogoiparou",
    "gn:population":0,
    "gn:timezone":"Africa/Porto-Novo",
    "iso:country":"BJ",
    "wof:name":"Dagarogoiparou",
    "wof:placetype":"locality"
},
  "geometry": {"coordinates":[2.74421,10.49344],"type":"Point"}
}