{
  "type": "Feature",
  "properties": {
    "gn:admin1_code":"8.0",
    "gn:asciiname":"Tikou",
    "gn:country_code":"BJ",
    "gn:dem":424,
    "gn:feature_class":"P",
    "gn:feature_code":"PPL",
    "gn:name":"Tikou",
    "gn:population":0,
    "gn:timezone":"Africa/Porto-Novo",
    "iso:country":"BJ",
    "name:und_x_variant":[
        "Ticou",
        "Tikou"
    ],
    "wof:name":"Tikou",
    "wof:placetype":"locality"
},
  "geometry": {"coordinates":[1.64445,10.40536],"type":"Point"}
}