{
  "type": "Feature",
  "properties": {
    "gn:admin1_code":"12.0",
    "gn:asciiname":"Adjaglame",
    "gn:cc2":"BJ",
    "gn:country_code":"BJ",
    "gn:dem":71,
    "gn:feature_class":"P",
    "gn:feature_code":"PPL",
    "gn:name":"Adjaglam\u00e9",
    "gn:population":0,
    "gn:timezone":"Africa/Porto-Novo",
    "iso:country":"BJ",
    "name:und_x_variant":[
        "Alassane",
        "Adjaglam\u00e9"
    ],
    "wof:name":"Adjaglame",
    "wof:placetype":"locality"
},
  "geometry": {"coordinates":[1.91667,6.91667],"type":"Point"}
}