{
  "type": "Feature",
  "properties": {
    "gn:admin1_code":"8.0",
    "gn:asciiname":"Datori-Ganganba",
    "gn:country_code":"BJ",
    "gn:dem":153,
    "gn:feature_class":"P",
    "gn:feature_code":"PPL",
    "gn:name":"Datori-Ganganba",
    "gn:population":0,
    "gn:timezone":"Africa/Porto-Novo",
    "iso:country":"BJ",
    "wof:name":"Datori-Ganganba",
    "wof:placetype":"locality"
},
  "geometry": {"coordinates":[0.80327,10.44144],"type":"Point"}
}