{
  "type": "Feature",
  "properties": {
    "gn:admin1_code":"10.0",
    "gn:asciiname":"Kossia",
    "gn:country_code":"BJ",
    "gn:dem":354,
    "gn:feature_class":"P",
    "gn:feature_code":"PPL",
    "gn:name":"Kossia",
    "gn:population":0,
    "gn:timezone":"Africa/Porto-Novo",
    "iso:country":"BJ",
    "wof:name":"Kossia",
    "wof:placetype":"locality"
},
  "geometry": {"coordinates":[2.44318,10.28287],"type":"Point"}
}