{
  "type": "Feature",
  "properties": {
    "gn:admin1_code":"11.0",
    "gn:asciiname":"Cossa-Kame",
    "gn:cc2":"BJ",
    "gn:country_code":"BJ",
    "gn:dem":194,
    "gn:feature_class":"P",
    "gn:feature_code":"PPL",
    "gn:name":"Cossa-Kam\u00e9",
    "gn:population":0,
    "gn:timezone":"Africa/Porto-Novo",
    "iso:country":"BJ",
    "name:und_x_variant":[
        "Kossokam",
        "Cosso-Kame",
        "Kossa-Kam\u00e9",
        "Kosso-Kam\u00e9",
        "Cossa-Kam\u00e9"
    ],
    "wof:name":"Cossa-Kame",
    "wof:placetype":"locality"
},
  "geometry": {"coordinates":[2.23333,7.91667],"type":"Point"}
}