{
  "type": "Feature",
  "properties": {
    "gn:admin1_code":"7.0",
    "gn:asciiname":"Serekibe",
    "gn:country_code":"BJ",
    "gn:dem":336,
    "gn:feature_class":"P",
    "gn:feature_code":"PPL",
    "gn:name":"S\u00e9r\u00e9kib\u00e9",
    "gn:population":0,
    "gn:timezone":"Africa/Porto-Novo",
    "iso:country":"BJ",
    "wof:name":"Serekibe",
    "wof:placetype":"locality"
},
  "geometry": {"coordinates":[3.46988,10.82988],"type":"Point"}
}