{
  "type": "Feature",
  "properties": {
    "gn:admin1_code":"13.0",
    "gn:asciiname":"Kandia Koubong",
    "gn:country_code":"BJ",
    "gn:dem":476,
    "gn:feature_class":"P",
    "gn:feature_code":"PPL",
    "gn:name":"Kandia Koubong",
    "gn:population":0,
    "gn:timezone":"Africa/Porto-Novo",
    "iso:country":"BJ",
    "wof:name":"Kandia Koubong",
    "wof:placetype":"locality"
},
  "geometry": {"coordinates":[1.47173,9.63688],"type":"Point"}
}