{
  "type": "Feature",
  "properties": {
    "gn:admin1_code":"10.0",
    "gn:asciiname":"Kigissoa",
    "gn:country_code":"BJ",
    "gn:dem":380,
    "gn:feature_class":"P",
    "gn:feature_code":"PPL",
    "gn:name":"Kigissoa",
    "gn:population":0,
    "gn:timezone":"Africa/Porto-Novo",
    "iso:country":"BJ",
    "wof:name":"Kigissoa",
    "wof:placetype":"locality"
},
  "geometry": {"coordinates":[2.80139,9.73947],"type":"Point"}
}