{
  "type": "Feature",
  "properties": {
    "gn:admin1_code":"8.0",
    "gn:asciiname":"Yoyoli",
    "gn:country_code":"BJ",
    "gn:dem":159,
    "gn:feature_class":"P",
    "gn:feature_code":"PPL",
    "gn:name":"Yoyoli",
    "gn:population":0,
    "gn:timezone":"Africa/Porto-Novo",
    "iso:country":"BJ",
    "wof:name":"Yoyoli",
    "wof:placetype":"locality"
},
  "geometry": {"coordinates":[0.89955,10.66385],"type":"Point"}
}