{
  "type": "Feature",
  "properties": {
    "gn:admin1_code":"13.0",
    "gn:asciiname":"Limeda",
    "gn:country_code":"BJ",
    "gn:dem":458,
    "gn:feature_class":"P",
    "gn:feature_code":"PPL",
    "gn:name":"Lim\u00e8da",
    "gn:population":0,
    "gn:timezone":"Africa/Porto-Novo",
    "iso:country":"BJ",
    "wof:name":"Limeda",
    "wof:placetype":"locality"
},
  "geometry": {"coordinates":[1.45887,9.66163],"type":"Point"}
}