{
  "type": "Feature",
  "properties": {
    "gn:admin1_code":"8.0",
    "gn:asciiname":"Fotire",
    "gn:country_code":"BJ",
    "gn:dem":418,
    "gn:feature_class":"P",
    "gn:feature_code":"PPL",
    "gn:name":"Fotir\u00e9",
    "gn:population":0,
    "gn:timezone":"Africa/Porto-Novo",
    "iso:country":"BJ",
    "name:und_x_variant":[
        "Fotid\u00e9",
        "Fotir\u00e9"
    ],
    "wof:name":"Fotire",
    "wof:placetype":"locality"
},
  "geometry": {"coordinates":[1.41207,10.48767],"type":"Point"}
}