{
  "type": "Feature",
  "properties": {
    "gn:admin1_code":"7.0",
    "gn:asciiname":"Kpessidara",
    "gn:country_code":"BJ",
    "gn:dem":275,
    "gn:feature_class":"P",
    "gn:feature_code":"PPL",
    "gn:name":"Kp\u00e9ssidara",
    "gn:population":0,
    "gn:timezone":"Africa/Porto-Novo",
    "iso:country":"BJ",
    "wof:name":"Kpessidara",
    "wof:placetype":"locality"
},
  "geometry": {"coordinates":[2.37266,11.45231],"type":"Point"}
}