{
  "type": "Feature",
  "properties": {
    "gn:admin1_code":"9.0",
    "gn:asciiname":"Niaouli",
    "gn:country_code":"BJ",
    "gn:dem":97,
    "gn:feature_class":"P",
    "gn:feature_code":"PPL",
    "gn:name":"Niaouli",
    "gn:population":0,
    "gn:timezone":"Africa/Porto-Novo",
    "iso:country":"BJ",
    "wof:name":"Niaouli",
    "wof:placetype":"locality"
},
  "geometry": {"coordinates":[2.11863,6.74778],"type":"Point"}
}