{
  "type": "Feature",
  "properties": {
    "gn:admin1_code":"18.0",
    "gn:asciiname":"Petagba",
    "gn:country_code":"BJ",
    "gn:dem":219,
    "gn:feature_class":"P",
    "gn:feature_code":"PPL",
    "gn:name":"P\u00e9tagba",
    "gn:population":0,
    "gn:timezone":"Africa/Porto-Novo",
    "iso:country":"BJ",
    "name:und_x_variant":[
        "Akoutagba",
        "P\u00e9tagba"
    ],
    "wof:name":"Petagba",
    "wof:placetype":"locality"
},
  "geometry": {"coordinates":[1.69088,7.52083],"type":"Point"}
}