{
  "type": "Feature",
  "properties": {
    "gn:admin1_code":"12.0",
    "gn:asciiname":"Bozikpe",
    "gn:country_code":"BJ",
    "gn:dem":209,
    "gn:feature_class":"P",
    "gn:feature_code":"PPL",
    "gn:name":"Bozikp\u00e9",
    "gn:population":0,
    "gn:timezone":"Africa/Porto-Novo",
    "iso:country":"BJ",
    "name:und_x_variant":[
        "Bosikp\u00ea",
        "Bozikp\u00e9"
    ],
    "wof:name":"Bozikpe",
    "wof:placetype":"locality"
},
  "geometry": {"coordinates":[1.67287,6.97319],"type":"Point"}
}