{
  "type": "Feature",
  "properties": {
    "gn:admin1_code":"10.0",
    "gn:asciiname":"Tinde",
    "gn:country_code":"BJ",
    "gn:dem":435,
    "gn:feature_class":"P",
    "gn:feature_code":"PPL",
    "gn:name":"Tind\u00e9",
    "gn:population":0,
    "gn:timezone":"Africa/Porto-Novo",
    "iso:country":"BJ",
    "name:spa_x_preferred":[
        "Tinde"
    ],
    "wof:name":"Tinde",
    "wof:placetype":"locality"
},
  "geometry": {"coordinates":[3.12451,9.47795],"type":"Point"}
}