{
  "type": "Feature",
  "properties": {
    "gn:admin1_code":"10.0",
    "gn:asciiname":"Bouka Krikoube",
    "gn:country_code":"BJ",
    "gn:dem":319,
    "gn:feature_class":"P",
    "gn:feature_code":"PPL",
    "gn:name":"Bouka Krikoub\u00e9",
    "gn:population":0,
    "gn:timezone":"Africa/Porto-Novo",
    "iso:country":"BJ",
    "wof:name":"Bouka Krikoube",
    "wof:placetype":"locality"
},
  "geometry": {"coordinates":[3.07715,10.26407],"type":"Point"}
}