{
  "type": "Feature",
  "properties": {
    "gn:admin1_code":"13.0",
    "gn:asciiname":"Niala",
    "gn:country_code":"BJ",
    "gn:dem":391,
    "gn:feature_class":"P",
    "gn:feature_code":"PPL",
    "gn:name":"Niala",
    "gn:population":0,
    "gn:timezone":"Africa/Porto-Novo",
    "iso:country":"BJ",
    "wof:name":"Niala",
    "wof:placetype":"locality"
},
  "geometry": {"coordinates":[1.45409,9.28492],"type":"Point"}
}