{
  "type": "Feature",
  "properties": {
    "gn:admin1_code":"8.0",
    "gn:asciiname":"Pourniari",
    "gn:country_code":"BJ",
    "gn:dem":203,
    "gn:feature_class":"P",
    "gn:feature_code":"PPL",
    "gn:name":"Pourniari",
    "gn:population":0,
    "gn:timezone":"Africa/Porto-Novo",
    "iso:country":"BJ",
    "wof:name":"Pourniari",
    "wof:placetype":"locality"
},
  "geometry": {"coordinates":[0.98464,10.80415],"type":"Point"}
}