{
  "type": "Feature",
  "properties": {
    "gn:admin1_code":"10.0",
    "gn:asciiname":"Tokou",
    "gn:country_code":"BJ",
    "gn:dem":384,
    "gn:feature_class":"P",
    "gn:feature_code":"PPL",
    "gn:name":"Tokou",
    "gn:population":0,
    "gn:timezone":"Africa/Porto-Novo",
    "iso:country":"BJ",
    "wof:name":"Tokou",
    "wof:placetype":"locality"
},
  "geometry": {"coordinates":[2.85579,9.94953],"type":"Point"}
}