{
  "type": "Feature",
  "properties": {
    "gn:admin1_code":"13.0",
    "gn:asciiname":"Koukokolo",
    "gn:country_code":"BJ",
    "gn:dem":386,
    "gn:feature_class":"P",
    "gn:feature_code":"PPL",
    "gn:name":"Koukokolo",
    "gn:population":0,
    "gn:timezone":"Africa/Porto-Novo",
    "iso:country":"BJ",
    "name:und_x_variant":[
        "Kokokolo",
        "Koukokolo"
    ],
    "wof:name":"Koukokolo",
    "wof:placetype":"locality"
},
  "geometry": {"coordinates":[1.42129,9.54091],"type":"Point"}
}