{
  "type": "Feature",
  "properties": {
    "gn:admin1_code":"10.0",
    "gn:admin2_code":"7669349.0",
    "gn:admin3_code":"11239741.0",
    "gn:asciiname":"Dunkassa",
    "gn:country_code":"BJ",
    "gn:dem":305,
    "gn:feature_class":"P",
    "gn:feature_code":"PPL",
    "gn:name":"Dunkassa",
    "gn:population":0,
    "gn:timezone":"Africa/Porto-Novo",
    "iso:country":"BJ",
    "name:ita_x_preferred":[
        "Dunkassa"
    ],
    "name:msa_x_preferred":[
        "Dunkassa"
    ],
    "name:und_x_variant":[
        "Duncassa"
    ],
    "wof:name":"Dunkassa",
    "wof:placetype":"locality"
},
  "geometry": {"coordinates":[3.14715,10.3545],"type":"Point"}
}