{
  "type": "Feature",
  "properties": {
    "gn:admin1_code":"8.0",
    "gn:asciiname":"Touka",
    "gn:country_code":"BJ",
    "gn:dem":261,
    "gn:feature_class":"P",
    "gn:feature_code":"PPL",
    "gn:name":"Touka",
    "gn:population":0,
    "gn:timezone":"Africa/Porto-Novo",
    "iso:country":"BJ",
    "name:azb_x_preferred":[
        "\u062a\u0648\u06a9\u0627"
    ],
    "name:ceb_x_preferred":[
        "Touka"
    ],
    "name:fas_x_preferred":[
        "\u062a\u0648\u06a9\u0627"
    ],
    "name:fra_x_preferred":[
        "Touka"
    ],
    "name:swe_x_preferred":[
        "Touka"
    ],
    "wof:name":"Touka",
    "wof:placetype":"locality"
},
  "geometry": {"coordinates":[1.05133,10.47955],"type":"Point"}
}