{
  "type": "Feature",
  "properties": {
    "gn:admin1_code":"10.0",
    "gn:asciiname":"Toume",
    "gn:country_code":"BJ",
    "gn:dem":374,
    "gn:feature_class":"P",
    "gn:feature_code":"PPL",
    "gn:name":"Toum\u00e9",
    "gn:population":0,
    "gn:timezone":"Africa/Porto-Novo",
    "iso:country":"BJ",
    "name:und_x_variant":[
        "Toumi",
        "Toum\u00e9"
    ],
    "wof:name":"Toume",
    "wof:placetype":"locality"
},
  "geometry": {"coordinates":[2.46078,10.08772],"type":"Point"}
}