{
  "type": "Feature",
  "properties": {
    "gn:admin1_code":"7.0",
    "gn:asciiname":"Danissani",
    "gn:country_code":"BJ",
    "gn:dem":297,
    "gn:feature_class":"P",
    "gn:feature_code":"PPL",
    "gn:name":"Danissani",
    "gn:population":0,
    "gn:timezone":"Africa/Porto-Novo",
    "iso:country":"BJ",
    "wof:name":"Danissani",
    "wof:placetype":"locality"
},
  "geometry": {"coordinates":[2.52956,11.45605],"type":"Point"}
}