{
  "type": "Feature",
  "properties": {
    "gn:admin1_code":"16.0",
    "gn:asciiname":"Djegan-Daho",
    "gn:country_code":"BJ",
    "gn:dem":18,
    "gn:feature_class":"P",
    "gn:feature_code":"PPL",
    "gn:name":"Djegan-Daho",
    "gn:population":0,
    "gn:timezone":"Africa/Porto-Novo",
    "iso:country":"BJ",
    "wof:name":"Djegan-Daho",
    "wof:placetype":"locality"
},
  "geometry": {"coordinates":[2.65061,6.47938],"type":"Point"}
}