{
  "type": "Feature",
  "properties": {
    "gn:admin1_code":"13.0",
    "gn:asciiname":"Setmsi-Kpemrhou",
    "gn:cc2":"BJ",
    "gn:country_code":"BJ",
    "gn:dem":373,
    "gn:feature_class":"P",
    "gn:feature_code":"PPL",
    "gn:name":"Setmsi-Kpemrhou",
    "gn:population":0,
    "gn:timezone":"Africa/Porto-Novo",
    "iso:country":"BJ",
    "name:und_x_variant":[
        "S\u00e9timsi",
        "Setmsi-Kpemrhou"
    ],
    "wof:name":"Setmsi-Kpemrhou",
    "wof:placetype":"locality"
},
  "geometry": {"coordinates":[1.86667,9.55],"type":"Point"}
}