{
  "type": "Feature",
  "properties": {
    "gn:admin1_code":"10.0",
    "gn:asciiname":"Gbassa",
    "gn:country_code":"BJ",
    "gn:dem":292,
    "gn:feature_class":"P",
    "gn:feature_code":"PPL",
    "gn:name":"Gbassa",
    "gn:population":0,
    "gn:timezone":"Africa/Porto-Novo",
    "iso:country":"BJ",
    "wof:name":"Gbassa",
    "wof:placetype":"locality"
},
  "geometry": {"coordinates":[2.35768,9.23148],"type":"Point"}
}