{
  "type": "Feature",
  "properties": {
    "gn:admin1_code":"10.0",
    "gn:asciiname":"Sanssandowero",
    "gn:country_code":"BJ",
    "gn:dem":402,
    "gn:feature_class":"P",
    "gn:feature_code":"PPL",
    "gn:name":"Sanssandow\u00e9ro",
    "gn:population":0,
    "gn:timezone":"Africa/Porto-Novo",
    "iso:country":"BJ",
    "wof:name":"Sanssandowero",
    "wof:placetype":"locality"
},
  "geometry": {"coordinates":[3.16542,9.86116],"type":"Point"}
}