{
  "type": "Feature",
  "properties": {
    "gn:admin1_code":"13.0",
    "gn:asciiname":"Marhou",
    "gn:country_code":"BJ",
    "gn:dem":387,
    "gn:feature_class":"P",
    "gn:feature_code":"PPL",
    "gn:name":"Marhou",
    "gn:population":0,
    "gn:timezone":"Africa/Porto-Novo",
    "iso:country":"BJ",
    "wof:name":"Marhou",
    "wof:placetype":"locality"
},
  "geometry": {"coordinates":[1.44809,9.96053],"type":"Point"}
}