{
  "type": "Feature",
  "properties": {
    "gn:admin1_code":"8.0",
    "gn:admin2_code":"10344466.0",
    "gn:admin3_code":"11789881.0",
    "gn:asciiname":"Cobly",
    "gn:country_code":"BJ",
    "gn:dem":247,
    "gn:feature_class":"P",
    "gn:feature_code":"PPL",
    "gn:name":"Cobly",
    "gn:population":0,
    "gn:timezone":"Africa/Porto-Novo",
    "iso:country":"BJ",
    "name:ceb_x_preferred":[
        "Cobly"
    ],
    "name:fra_x_preferred":[
        "Cobly"
    ],
    "name:frr_x_preferred":[
        "Cobly"
    ],
    "name:ita_x_preferred":[
        "Cobly"
    ],
    "name:msa_x_preferred":[
        "Cobly"
    ],
    "name:nld_x_preferred":[
        "Cobly"
    ],
    "name:pol_x_preferred":[
        "Cobly"
    ],
    "name:spa_x_preferred":[
        "Cobly"
    ],
    "name:swe_x_preferred":[
        "Cobly"
    ],
    "name:zho_x_preferred":[
        "\u514b\u5e03\u91cc"
    ],
    "wof:name":"Cobly",
    "wof:placetype":"locality"
},
  "geometry": {"coordinates":[0.99972,10.49222],"type":"Point"}
}