{
  "type": "Feature",
  "properties": {
    "gn:admin1_code":"8.0",
    "gn:asciiname":"Mahoun",
    "gn:country_code":"BJ",
    "gn:dem":193,
    "gn:feature_class":"P",
    "gn:feature_code":"PPL",
    "gn:name":"Mahoun",
    "gn:population":0,
    "gn:timezone":"Africa/Porto-Novo",
    "iso:country":"BJ",
    "wof:name":"Mahoun",
    "wof:placetype":"locality"
},
  "geometry": {"coordinates":[0.98227,10.86389],"type":"Point"}
}