{
  "type": "Feature",
  "properties": {
    "gn:admin1_code":"10.0",
    "gn:asciiname":"Borosson",
    "gn:country_code":"BJ",
    "gn:dem":343,
    "gn:feature_class":"P",
    "gn:feature_code":"PPL",
    "gn:name":"Borosson",
    "gn:population":0,
    "gn:timezone":"Africa/Porto-Novo",
    "iso:country":"BJ",
    "wof:name":"Borosson",
    "wof:placetype":"locality"
},
  "geometry": {"coordinates":[2.50992,9.86661],"type":"Point"}
}