{
  "type": "Feature",
  "properties": {
    "gn:admin1_code":"13.0",
    "gn:asciiname":"Ananinga",
    "gn:country_code":"BJ",
    "gn:dem":369,
    "gn:feature_class":"P",
    "gn:feature_code":"PPL",
    "gn:name":"Ananinga",
    "gn:population":0,
    "gn:timezone":"Africa/Porto-Novo",
    "iso:country":"BJ",
    "wof:name":"Ananinga",
    "wof:placetype":"locality"
},
  "geometry": {"coordinates":[1.90157,9.71499],"type":"Point"}
}