{
  "type": "Feature",
  "properties": {
    "gn:admin1_code":"12.0",
    "gn:asciiname":"Agoreadji",
    "gn:country_code":"BJ",
    "gn:dem":118,
    "gn:feature_class":"P",
    "gn:feature_code":"PPL",
    "gn:name":"Agor\u00e9adji",
    "gn:population":0,
    "gn:timezone":"Africa/Porto-Novo",
    "iso:country":"BJ",
    "wof:name":"Agoreadji",
    "wof:placetype":"locality"
},
  "geometry": {"coordinates":[1.88333,7.06667],"type":"Point"}
}