{
  "type": "Feature",
  "properties": {
    "gn:admin1_code":"7.0",
    "gn:asciiname":"Winsene",
    "gn:country_code":"BJ",
    "gn:dem":331,
    "gn:feature_class":"P",
    "gn:feature_code":"PPL",
    "gn:name":"Wins\u00e9n\u00e9",
    "gn:population":0,
    "gn:timezone":"Africa/Porto-Novo",
    "iso:country":"BJ",
    "name:und_x_variant":[
        "Gu\u00e9ss\u00e9n\u00e9",
        "Ou\u00e9ss\u00e9n\u00e9",
        "Wesseme",
        "Ouess\u00e9m\u00e9",
        "Wins\u00e9n\u00e9"
    ],
    "wof:name":"Winsene",
    "wof:placetype":"locality"
},
  "geometry": {"coordinates":[2.8322,10.69272],"type":"Point"}
}